Workbook

Sheet Matrix Algebra
A2: Matrices | C2: M = | D2: 2 | E2: 1 | F2: 3
D3: 4 | E3: 6 | F3: 12
C5: N = | D5: 1 | E5: 2 | F5: 3
D6: 3 | E6: 2 | F6: 1
A8: Adición | C8: M + N = | D8: {=M+N} -> 3 | E8: 3 | F8: 6
D9: 7 | E9: 8 | F9: 13
A11: Adición no posible | C11: O = | D11: 2 | E11: 2
D12: 3 | E12: 4
C14: M + O = | D14: {=M+O} -> 4 | E14: 3 | F14: #N/A
D15: 7 | E15: 10 | F15: #N/A
A17: Igualdad | C17: M = N | D17: {=M=N} -> 0 | E17: 0 | F17: 1 | H17: {=M=N} -> 0 | I17: 0 | J17: 1
D18: 0 | E18: 0 | F18: 0 | H18: 0 | I18: 0 | J18: 0
A20: Resta | C20: D = M - N = | D20: {=M-N} -> 1 | E20: -1 | F20: 0
D21: 1 | E21: 4 | F21: 11
A23: Matriz nula | C23: ZETA = | D23: 0 | E23: 0 | F23: 0
D24: 0 | E24: 0 | F24: 0
C26: M + ZETA = | D26: {=M + ZETA} -> 2 | E26: 1 | F26: 3
D27: 4 | E27: 6 | F27: 12
A29: Multiplicación por un escalar | C29: M * 2 = | D29: {=M*2} -> 4 | E29: 2 | F29: 6 | H29: {=M*2} -> 4 | I29: 2 | J29: 6
D30: 8 | E30: 12 | F30: 24 | H30: 8 | I30: 12 | J30: 24
A32: Multiplicación de matrices | C32: Q = | D32: 2 | E32: 0 | F32: 4
D33: 1 | E33: 1 | F33: 2 | H33: {=MMULT(M,Q)} -> 14 | I33: 13 | J33: 25
D34: 3 | E34: 4 | F34: 5 | H34: 50 | I34: 54 | J34: 88
C36: M * Q = | D36: {=MMULT(M,Q)} -> 14 | E36: 13 | F36: 25
D37: 50 | E37: 54 | F37: 88
A39: Multiplicación no posible | C39: Q * M = | D39: =MMULT(Q,M) -> #VALUE! | E39: =#VALUE! -> #VALUE! | F39: =#VALUE! -> #VALUE!
D40: =#VALUE! -> #VALUE! | E40: =#VALUE! -> #VALUE! | F40: =#VALUE! -> #VALUE!
D41: =#VALUE! -> #VALUE! | E41: =#VALUE! -> #VALUE! | F41: =#VALUE! -> #VALUE!
A43: Matriz identidad incorrecta | C43: TM = | D43: 1 | E43: 1 | F43: 1
D44: 1 | E44: 1 | F44: 1
D45: 1 | E45: 1 | F45: 1
C47: M * TM = | D47: {=MMULT(M,TM)} -> 6 | E47: 6 | F47: 6
D48: 22 | E48: 22 | F48: 22
A50: Matriz identidad para posmultiplicación | C50: I = | D50: {=_xlfn.MUNIT(3)} -> 1 | E50: 0 | F50: 0
D51: 0 | E51: 1 | F51: 0
D52: 0 | E52: 0 | F52: 1
C54: M * I = | D54: {=MMULT(M,I)} -> 2 | E54: 1 | F54: 3
D55: 4 | E55: 6 | F55: 12
A57: Matriz identidad para premultiplicación | C57: IP = | D57: {=_xlfn.MUNIT(2)} -> 1 | E57: 0
D58: 0 | E58: 1
C60: IP * M = | D60: {=MMULT(IP,M)} -> 2 | E60: 1 | F60: 3
D61: 4 | E61: 6 | F61: 12
A64: Sistemas de ecuaciones | C64: 2x1 + x2 = 10
C65: 5x1 + 3x2 = 26
C69: A | D69: 2 | E69: 1
D70: 5 | E70: 3
C72: b | D72: 10
D73: 26
C75: A^-1 = | D75: {=MINVERSE(A)} -> 3 | E75: -1
D76: -5 | E76: 2
C78: C = | D78: 2 | E78: 6
D79: 4 | E79: 12
C81: C^-1 = | D81: {=MINVERSE(CMAT)} -> #VALUE! | E81: #VALUE!
D82: #VALUE! | E82: #VALUE!
C84: x = A^-1 * b = | D84: {=MMULT(AINV,b)} -> 4 | F84: {=MMULT(AINV,b)} -> 4
D85: 2 | F85: 2
E87: x1 | H87: x2
B88: 2x1 + x2 = 10 | C88: Test | D88: 2 | E88: =D84 -> 4 | F88: + | G88: 1 | H88: =D85 -> 2 | I88: = | J88: =D88*E88+G88*H88 -> 10
B89: 5x1 + 3x2 = 26 | D89: 5 | E89: =D84 -> 4 | F89: + | G89: 3 | H89: =D85 -> 2 | I89: = | J89: =D89*E89+G89*H89 -> 26
A92: Vectores sumatorios | C92: ISUM | D92: 1
D93: 1
D94: 1
A96: Suma de columnas | C96: M * ISUM = | D96: {=MMULT(M,ISUM)} -> 6
D97: 22
C99: ISUM2 | D99: 1 | E99: 1
A101: Suma de filas | C101: ISUM2 * M = | D101: {=MMULT(ISUM2,M)} -> 6 | E101: 7 | F101: 15
A104: Vector horizontal | C104: g'= | D104: 8 | E104: 9 | F104: 17
A106: Matriz de vector horizontal diagonal | C106: g'hat = | D106: {=IF(D104:F104=TRANSPOSE(D104:F104),D104:F104,0)} -> 8 | E106: 0 | F106: 0 | H106: {=IF(D104:F104=TRANSPOSE(D104:F104),D104:F104,0)} -> 8 | I106: 0 | J106: 0
D107: 0 | E107: 9 | F107: 0 | H107: 0 | I107: 9 | J107: 0
D108: 0 | E108: 0 | F108: 17 | H108: 0 | I108: 0 | J108: 17
A110: Diagonal invertida | C110: g'hat^-1= | D110: {=MINVERSE(GPRIMEHAT)} -> 0.125 | E110: 0 | F110: 0 | H110: {=MINVERSE(D106:F108)} -> 0.125 | I110: 0 | J110: 0
D111: 0 | E111: 0.11111111 | F111: 0 | H111: 0 | I111: 0.11111111 | J111: 0
D112: 0 | E112: 0 | F112: 0.058823529 | H112: 0 | I112: 0 | J112: 0.058823529
A114: Matrices recíprocas | C114: g'hat^-1 * g'hat= | D114: {=MMULT(GPRIMEHAT,GPRIMEHATINV)} -> 1 | E114: 0 | F114: 0 | H114: {=MMULT(D106:F108,D110:F112)} -> 1 | I114: 0 | J114: 0
D115: 0 | E115: 1 | F115: 0 | H115: 0 | I115: 1 | J115: 0
D116: 0 | E116: 0 | F116: 1 | H116: 0 | I116: 0 | J116: 1
C119: M = | D119: 2 | E119: 1 | F119: 3
D120: 4 | E120: 6 | F120: 12
C122: suma filas | D122: =SUM(D119:F119) -> 6
D123: =SUM(D120:F120) -> 22
C125: suma columnas | D125: =SUM(D119:D120) -> 6 | E125: =SUM(E119:E120) -> 7 | F125: =SUM(F119:F120) -> 15

Sheet Input-Output Model
C3: Agriculture | D3: Manufacturing | E3: Final demand | G3: Total Output (x)
B4: Agriculture | C4: 150 | D4: 500 | E4: 350 | G4: =SUM(C4:E4) -> 1000
B5: Manufacturing | C5: 200 | D5: 100 | E5: 1700 | G5: =SUM(C5:E5) -> 2000
B7: Payments | C7: 650 | D7: 1400 | E7: 1100
B8: Total outlays | C8: 1000 | D8: 2000 | E8: 3150
B12: xhat | C12: {=IF(G4:G5=TRANSPOSE(G4:G5),G4:G5,0)} -> 1000 | D12: 0
C13: 0 | D13: 2000
B15: xhat ^-1 | C15: {=MINVERSE(xhat)} -> 0.001 | D15: 0
C16: 0 | D16: 0.0005
B18: A = Z * xhat ^-1 = | C18: {=MMULT(Z,xhatinv)} -> 0.15 | D18: 0.25
C19: 0.2 | D19: 0.05
B21: Identity matrix | C21: {=_xlfn.MUNIT(2)} -> 1 | D21: 0
C22: 0 | D22: 1
B24: Leontief = L = | C24: {=MINVERSE((identity-REQ))} -> 1.2541254 | D24: 0.330033
C25: 0.2640264 | D25: 1.1221122
B27: Model Calibration | C27: {=MMULT(L,fdem)} -> 1000
C28: 2000
B30: New Demand | C30: 600
C31: 1500
B33: L * Fnew = Xnew | C33: {=MMULT(L,fdemnew)} -> 1247.5248
C34: 1841.5842
B36: Xnew diag | C36: {=IF(C33:C34=TRANSPOSE(C33:C34),C33:C34,0)} -> 1247.5248 | D36: 0
C37: 0 | D37: 1841.5842
B39: A * xnew diag = | C39: {=MMULT(REQ,xnewdiag)} -> 187.12871 | D39: 460.39604
C40: 249.50495 | D40: 92.079208
B42: New table
C44: Agriculture | D44: Manufacturing | E44: Final demand | G44: Total Output (x)
B45: Agriculture | C45: {=C39:D40} -> 187.12871 | D45: 460.39604 | E45: {=C30:C31} -> 600 | G45: =SUM(C45:E45) -> 1247.5248
B46: Manufacturing | C46: 249.50495 | D46: 92.079208 | E46: 1500 | G46: =SUM(C46:E46) -> 1841.5842
B48: Payments | C48: =C49-SUM(C45:C46) -> 810.89109 | D48: =D49-SUM(D45:D46) -> 1289.1089 | E48: 1100
B49: Total outlays | C49: =G45 -> 1247.5248 | D49: =G46 -> 1841.5842 | E49: 3200

Sheet Tool
A1: The World Bank
A2: Kyrgyz Republic
A3: Rapid Environmentally Extended Input-Output Analysis Tool
A4: (current prices, $ million)
D5: Initial setup | H5: Output | L5: Employment | P5: Modeled regional employment | Z5: Modeled Environmental Factors
D6: Total Initial Final Demand | E6: Changes in final demand per sector | F6: New final demand | H6: Initial Output | I6: New Output | J6: Changes in Output | L6: Initial Employment | M6: Total Modeled employment | N6: Changes in Employment | P6: Batken oblast | Q6: Djalal-Abad | R6: Issyk-Kul | S6: Naryn oblast | T6: Osh oblast | U6: Talas oblast | V6: Chui oblast | W6: Bishkek city | X6: Osh city | Z6: Energy Usage (TJ) | AA6: Total CO2 emissions (Gg) | AB6: WFN: Total water footprint (Mm3/yr) - Blue | AC6: WFN: Total water footprint (Mm3/yr) - Green | AD6: WFN: Total water footprint (Mm3/yr) - Grey
A8: Agriculture, hunting, forestry, and fishing | B8: c1 | D8: 1483.3513 | E8: 0 | F8: =D8*(1+E8) -> 1483.3513 | H8: 3054.468 | I8: {=MMULT(KYZ_EEIO_2017!$D$265:$AK$298,Tool!F8:F41)} -> 3054.468 | J8: =IF(H8=0,0,(I8-H8)/H8) -> 0 | L8: 541400 | M8: =SUM(P8:X8) -> 541400 | N8: =M8-L8 -> 0 | P8: =$I8*KYZ_EEIO_2017!CD8 -> 52400 | Q8: =$I8*KYZ_EEIO_2017!CE8 -> 125200 | R8: =$I8*KYZ_EEIO_2017!CF8 -> 42300 | S8: =$I8*KYZ_EEIO_2017!CG8 -> 41000 | T8: =$I8*KYZ_EEIO_2017!CH8 -> 175600 | U8: =$I8*KYZ_EEIO_2017!CI8 -> 58400 | V8: =$I8*KYZ_EEIO_2017!CJ8 -> 42100 | W8: =$I8*KYZ_EEIO_2017!CK8 -> 3200 | X8: =$I8*KYZ_EEIO_2017!CL8 -> 1200 | Z8: =$I8*KYZ_EEIO_2017!CY8 -> 1912.0999 | AA8: =$I8*KYZ_EEIO_2017!CZ8 -> 1350.7742 | AB8: =$I8*KYZ_EEIO_2017!DA8 -> 7117.8215 | AC8: =$I8*KYZ_EEIO_2017!DB8 -> 11933.122 | AD8: =$I8*KYZ_EEIO_2017!DC8 -> 432.85533
A9: Mining and quarrying | B9: c2 | D9: 53.702231 | E9: 0 | F9: =D9*(1+E9) -> 53.702231 | H9: 145.42287 | I9: 145.42287 | J9: =IF(H9=0,0,(I9-H9)/H9) -> 0 | L9: 12700 | M9: =SUM(P9:X9) -> 12700 | N9: =M9-L9 -> 0 | P9: =$I9*KYZ_EEIO_2017!CD9 -> 4200 | Q9: =$I9*KYZ_EEIO_2017!CE9 -> 1400 | R9: =$I9*KYZ_EEIO_2017!CF9 -> 2100 | S9: =$I9*KYZ_EEIO_2017!CG9 -> 3300 | T9: =$I9*KYZ_EEIO_2017!CH9 -> 0 | U9: =$I9*KYZ_EEIO_2017!CI9 -> 100 | V9: =$I9*KYZ_EEIO_2017!CJ9 -> 1600 | W9: =$I9*KYZ_EEIO_2017!CK9 -> 0 | X9: =$I9*KYZ_EEIO_2017!CL9 -> 0 | Z9: =$I9*KYZ_EEIO_2017!CY9 -> 147.72395 | AA9: =$I9*KYZ_EEIO_2017!CZ9 -> 181.80787 | AB9: =$I9*KYZ_EEIO_2017!DA9 -> 0.22026195 | AC9: =$I9*KYZ_EEIO_2017!DB9 -> 0 | AD9: =$I9*KYZ_EEIO_2017!DC9 -> 3.055247
A10: Food, beverages, and tobacco | B10: c3 | D10: 389.24916 | E10: 0 | F10: =D10*(1+E10) -> 389.24916 | H10: 643.01735 | I10: 643.01735 | J10: =IF(H10=0,0,(I10-H10)/H10) -> 0 | L10: 37064.291 | M10: =SUM(P10:X10) -> 37064.291 | N10: =M10-L10 -> 0 | P10: =$I10*KYZ_EEIO_2017!CD10 -> 1314.7806 | Q10: =$I10*KYZ_EEIO_2017!CE10 -> 5306.0789 | R10: =$I10*KYZ_EEIO_2017!CF10 -> 1596.5193 | S10: =$I10*KYZ_EEIO_2017!CG10 -> 313.043 | T10: =$I10*KYZ_EEIO_2017!CH10 -> 3928.6897 | U10: =$I10*KYZ_EEIO_2017!CI10 -> 626.086 | V10: =$I10*KYZ_EEIO_2017!CJ10 -> 11269.548 | W10: =$I10*KYZ_EEIO_2017!CK10 -> 11504.33 | X10: =$I10*KYZ_EEIO_2017!CL10 -> 1205.2156 | Z10: =$I10*KYZ_EEIO_2017!CY10 -> 736.61604 | AA10: =$I10*KYZ_EEIO_2017!CZ10 -> 280.60886 | AB10: =$I10*KYZ_EEIO_2017!DA10 -> 1.187814 | AC10: =$I10*KYZ_EEIO_2017!DB10 -> 0 | AD10: =$I10*KYZ_EEIO_2017!DC10 -> 16.476134
A11: Textiles and textile products | B11: c4 | D11: 118.23605 | E11: 0 | F11: =D11*(1+E11) -> 118.23605 | H11: 128.31083 | I11: 128.31083 | J11: =IF(H11=0,0,(I11-H11)/H11) -> 0 | L11: 8792.7829 | M11: =SUM(P11:X11) -> 8792.7829 | N11: =M11-L11 -> 0 | P11: =$I11*KYZ_EEIO_2017!CD11 -> 311.90615 | Q11: =$I11*KYZ_EEIO_2017!CE11 -> 1258.7641 | R11: =$I11*KYZ_EEIO_2017!CF11 -> 378.74318 | S11: =$I11*KYZ_EEIO_2017!CG11 -> 74.263369 | T11: =$I11*KYZ_EEIO_2017!CH11 -> 932.00528 | U11: =$I11*KYZ_EEIO_2017!CI11 -> 148.52674 | V11: =$I11*KYZ_EEIO_2017!CJ11 -> 2673.4813 | W11: =$I11*KYZ_EEIO_2017!CK11 -> 2729.1788 | X11: =$I11*KYZ_EEIO_2017!CL11 -> 285.91397 | Z11: =$I11*KYZ_EEIO_2017!CY11 -> 257.57702 | AA11: =$I11*KYZ_EEIO_2017!CZ11 -> 63.024613 | AB11: =$I11*KYZ_EEIO_2017!DA11 -> 0.48447421 | AC11: =$I11*KYZ_EEIO_2017!DB11 -> 0 | AD11: =$I11*KYZ_EEIO_2017!DC11 -> 6.7201275
A12: Leather, leather products, and footwear | B12: c5 | D12: 12.504728 | E12: 0 | F12: =D12*(1+E12) -> 12.504728 | H12: 13.595506 | I12: 13.595506 | J12: =IF(H12=0,0,(I12-H12)/H12) -> -4.1810449e-15 | L12: 931.66201 | M12: =SUM(P12:X12) -> 931.66201 | N12: =M12-L12 -> 0 | P12: =$I12*KYZ_EEIO_2017!CD12 -> 33.048821 | Q12: =$I12*KYZ_EEIO_2017!CE12 -> 133.3756 | R12: =$I12*KYZ_EEIO_2017!CF12 -> 40.130712 | S12: =$I12*KYZ_EEIO_2017!CG12 -> 7.868767 | T12: =$I12*KYZ_EEIO_2017!CH12 -> 98.753026 | U12: =$I12*KYZ_EEIO_2017!CI12 -> 15.737534 | V12: =$I12*KYZ_EEIO_2017!CJ12 -> 283.27561 | W12: =$I12*KYZ_EEIO_2017!CK12 -> 289.17719 | X12: =$I12*KYZ_EEIO_2017!CL12 -> 30.294753 | Z12: =$I12*KYZ_EEIO_2017!CY12 -> 33.107265 | AA12: =$I12*KYZ_EEIO_2017!CZ12 -> 6.1392604 | AB12: =$I12*KYZ_EEIO_2017!DA12 -> 0.065430241 | AC12: =$I12*KYZ_EEIO_2017!DB12 -> 0 | AD12: =$I12*KYZ_EEIO_2017!DC12 -> 0.90758096
A13: Wood and products of wood and cork | B13: c6 | D13: 2.8206512 | E13: 0 | F13: =D13*(1+E13) -> 2.8206512 | H13: 3.9497932 | I13: 3.9497932 | J13: =IF(H13=0,0,(I13-H13)/H13) -> 0 | L13: 358.07881 | M13: =SUM(P13:X13) -> 358.07881 | N13: =M13-L13 -> 0 | P13: =$I13*KYZ_EEIO_2017!CD13 -> 12.70212 | Q13: =$I13*KYZ_EEIO_2017!CE13 -> 51.262127 | R13: =$I13*KYZ_EEIO_2017!CF13 -> 15.424003 | S13: =$I13*KYZ_EEIO_2017!CG13 -> 3.0243143 | T13: =$I13*KYZ_EEIO_2017!CH13 -> 37.955145 | U13: =$I13*KYZ_EEIO_2017!CI13 -> 6.0486286 | V13: =$I13*KYZ_EEIO_2017!CJ13 -> 108.87531 | W13: =$I13*KYZ_EEIO_2017!CK13 -> 111.14355 | X13: =$I13*KYZ_EEIO_2017!CL13 -> 11.64361 | Z13: =$I13*KYZ_EEIO_2017!CY13 -> 22.713789 | AA13: =$I13*KYZ_EEIO_2017!CZ13 -> 1.7543551 | AB13: =$I13*KYZ_EEIO_2017!DA13 -> 0.049561495 | AC13: =$I13*KYZ_EEIO_2017!DB13 -> 0 | AD13: =$I13*KYZ_EEIO_2017!DC13 -> 0.68746605
A14: Pulp, paper, paper products, printing, and publishing | B14: c7 | D14: 26.361181 | E14: 0 | F14: =D14*(1+E14) -> 26.361181 | H14: 39.479936 | I14: 39.479936 | J14: =IF(H14=0,0,(I14-H14)/H14) -> 0 | L14: 2820.6013 | M14: =SUM(P14:X14) -> 2820.6013 | N14: =M14-L14 -> 0 | P14: =$I14*KYZ_EEIO_2017!CD14 -> 100.05511 | Q14: =$I14*KYZ_EEIO_2017!CE14 -> 403.79385 | R14: =$I14*KYZ_EEIO_2017!CF14 -> 121.49549 | S14: =$I14*KYZ_EEIO_2017!CG14 -> 23.822646 | T14: =$I14*KYZ_EEIO_2017!CH14 -> 298.97421 | U14: =$I14*KYZ_EEIO_2017!CI14 -> 47.645292 | V14: =$I14*KYZ_EEIO_2017!CJ14 -> 857.61526 | W14: =$I14*KYZ_EEIO_2017!CK14 -> 875.48224 | X14: =$I14*KYZ_EEIO_2017!CL14 -> 91.717187 | Z14: =$I14*KYZ_EEIO_2017!CY14 -> 78.993743 | AA14: =$I14*KYZ_EEIO_2017!CZ14 -> 17.757572 | AB14: =$I14*KYZ_EEIO_2017!DA14 -> 0.15893346 | AC14: =$I14*KYZ_EEIO_2017!DB14 -> 0 | AD14: =$I14*KYZ_EEIO_2017!DC14 -> 2.2045613
A15: Coke, refined petroleum, and nuclear fuel | B15: c8 | D15: 49.222067 | E15: 0 | F15: =D15*(1+E15) -> 49.222067 | H15: 84.707159 | I15: 84.707159 | J15: =IF(H15=0,0,(I15-H15)/H15) -> 0 | L15: 6285.5449 | M15: =SUM(P15:X15) -> 6285.5449 | N15: =M15-L15 -> 0 | P15: =$I15*KYZ_EEIO_2017!CD15 -> 222.96696 | Q15: =$I15*KYZ_EEIO_2017!CE15 -> 899.83096 | R15: =$I15*KYZ_EEIO_2017!CF15 -> 270.7456 | S15: =$I15*KYZ_EEIO_2017!CG15 -> 53.087372 | T15: =$I15*KYZ_EEIO_2017!CH15 -> 666.24652 | U15: =$I15*KYZ_EEIO_2017!CI15 -> 106.17474 | V15: =$I15*KYZ_EEIO_2017!CJ15 -> 1911.1454 | W15: =$I15*KYZ_EEIO_2017!CK15 -> 1950.9609 | X15: =$I15*KYZ_EEIO_2017!CL15 -> 204.38638 | Z15: =$I15*KYZ_EEIO_2017!CY15 -> 8207.6301 | AA15: =$I15*KYZ_EEIO_2017!CZ15 -> 93.403021 | AB15: =$I15*KYZ_EEIO_2017!DA15 -> 0.11881106 | AC15: =$I15*KYZ_EEIO_2017!DB15 -> 0 | AD15: =$I15*KYZ_EEIO_2017!DC15 -> 1.6480247
A16: Chemicals and chemical products | B16: c9 | D16: 22.504599 | E16: 0 | F16: =D16*(1+E16) -> 22.504599 | H16: 39.147976 | I16: 39.147976 | J16: =IF(H16=0,0,(I16-H16)/H16) -> 0 | L16: 2906.5273 | M16: =SUM(P16:X16) -> 2906.5273 | N16: =M16-L16 -> 0 | P16: =$I16*KYZ_EEIO_2017!CD16 -> 103.10316 | Q16: =$I16*KYZ_EEIO_2017!CE16 -> 416.09491 | R16: =$I16*KYZ_EEIO_2017!CF16 -> 125.1967 | S16: =$I16*KYZ_EEIO_2017!CG16 -> 24.548372 | T16: =$I16*KYZ_EEIO_2017!CH16 -> 308.08207 | U16: =$I16*KYZ_EEIO_2017!CI16 -> 49.096745 | V16: =$I16*KYZ_EEIO_2017!CJ16 -> 883.74141 | W16: =$I16*KYZ_EEIO_2017!CK16 -> 902.15269 | X16: =$I16*KYZ_EEIO_2017!CL16 -> 94.511234 | Z16: =$I16*KYZ_EEIO_2017!CY16 -> 128.44983 | AA16: =$I16*KYZ_EEIO_2017!CZ16 -> 39.609975 | AB16: =$I16*KYZ_EEIO_2017!DA16 -> 0.26535046 | AC16: =$I16*KYZ_EEIO_2017!DB16 -> 0 | AD16: =$I16*KYZ_EEIO_2017!DC16 -> 3.6806685
A17: Rubber and plastics | B17: c10 | D17: 26.775083 | E17: 0 | F17: =D17*(1+E17) -> 26.775083 | H17: 76.339825 | I17: 76.339825 | J17: =IF(H17=0,0,(I17-H17)/H17) -> 0 | L17: 5805.0953 | M17: =SUM(P17:X17) -> 5805.0953 | N17: =M17-L17 -> 0 | P17: =$I17*KYZ_EEIO_2017!CD17 -> 205.92399 | Q17: =$I17*KYZ_EEIO_2017!CE17 -> 831.05038 | R17: =$I17*KYZ_EEIO_2017!CF17 -> 250.05056 | S17: =$I17*KYZ_EEIO_2017!CG17 -> 49.029521 | T17: =$I17*KYZ_EEIO_2017!CH17 -> 615.32049 | U17: =$I17*KYZ_EEIO_2017!CI17 -> 98.059042 | V17: =$I17*KYZ_EEIO_2017!CJ17 -> 1765.0628 | W17: =$I17*KYZ_EEIO_2017!CK17 -> 1801.8349 | X17: =$I17*KYZ_EEIO_2017!CL17 -> 188.76366 | Z17: =$I17*KYZ_EEIO_2017!CY17 -> 6052.6366 | AA17: =$I17*KYZ_EEIO_2017!CZ17 -> 89.757302 | AB17: =$I17*KYZ_EEIO_2017!DA17 -> 0.47699451 | AC17: =$I17*KYZ_EEIO_2017!DB17 -> 0 | AD17: =$I17*KYZ_EEIO_2017!DC17 -> 6.6163769
A18: Other nonmetallic minerals | B18: c11 | D18: 106.14314 | E18: 0 | F18: =D18*(1+E18) -> 106.14314 | H18: 280.28864 | I18: 280.28864 | J18: =IF(H18=0,0,(I18-H18)/H18) -> 0 | L18: 21313.938 | M18: =SUM(P18:X18) -> 21313.938 | N18: =M18-L18 -> 0 | P18: =$I18*KYZ_EEIO_2017!CD18 -> 756.06873 | Q18: =$I18*KYZ_EEIO_2017!CE18 -> 3051.2774 | R18: =$I18*KYZ_EEIO_2017!CF18 -> 918.08346 | S18: =$I18*KYZ_EEIO_2017!CG18 -> 180.01636 | T18: =$I18*KYZ_EEIO_2017!CH18 -> 2259.2054 | U18: =$I18*KYZ_EEIO_2017!CI18 -> 360.03273 | V18: =$I18*KYZ_EEIO_2017!CJ18 -> 6480.5891 | W18: =$I18*KYZ_EEIO_2017!CK18 -> 6615.6014 | X18: =$I18*KYZ_EEIO_2017!CL18 -> 693.063 | Z18: =$I18*KYZ_EEIO_2017!CY18 -> 436.36594 | AA18: =$I18*KYZ_EEIO_2017!CZ18 -> 351.34226 | AB18: =$I18*KYZ_EEIO_2017!DA18 -> 0.80348773 | AC18: =$I18*KYZ_EEIO_2017!DB18 -> 0 | AD18: =$I18*KYZ_EEIO_2017!DC18 -> 11.145155
A19: Basic metals and fabricated metal | B19: c12 | D19: 983.22603 | E19: 0 | F19: =D19*(1+E19) -> 983.22603 | H19: 1728.3904 | I19: 1728.3904 | J19: =IF(H19=0,0,(I19-H19)/H19) -> 0 | L19: 142341.87 | M19: =SUM(P19:X19) -> 142341.87 | N19: =M19-L19 -> 0 | P19: =$I19*KYZ_EEIO_2017!CD19 -> 5049.2891 | Q19: =$I19*KYZ_EEIO_2017!CE19 -> 20377.488 | R19: =$I19*KYZ_EEIO_2017!CF19 -> 6131.2797 | S19: =$I19*KYZ_EEIO_2017!CG19 -> 1202.2117 | T19: =$I19*KYZ_EEIO_2017!CH19 -> 15087.757 | U19: =$I19*KYZ_EEIO_2017!CI19 -> 2404.4234 | V19: =$I19*KYZ_EEIO_2017!CJ19 -> 43279.621 | W19: =$I19*KYZ_EEIO_2017!CK19 -> 44181.28 | X19: =$I19*KYZ_EEIO_2017!CL19 -> 4628.515 | Z19: =$I19*KYZ_EEIO_2017!CY19 -> 1297.7736 | AA19: =$I19*KYZ_EEIO_2017!CZ19 -> 2080.1698 | AB19: =$I19*KYZ_EEIO_2017!DA19 -> 1.3834284 | AC19: =$I19*KYZ_EEIO_2017!DB19 -> 0 | AD19: =$I19*KYZ_EEIO_2017!DC19 -> 19.189494
A20: Machinery, nec | B20: c13 | D20: 17.612922 | E20: 0 | F20: =D20*(1+E20) -> 17.612922 | H20: 34.198262 | I20: 34.198262 | J20: =IF(H20=0,0,(I20-H20)/H20) -> 0 | L20: 3292.1999 | M20: =SUM(P20:X20) -> 3292.1999 | N20: =M20-L20 -> 0 | P20: =$I20*KYZ_EEIO_2017!CD20 -> 116.78412 | Q20: =$I20*KYZ_EEIO_2017!CE20 -> 471.30734 | R20: =$I20*KYZ_EEIO_2017!CF20 -> 141.80929 | S20: =$I20*KYZ_EEIO_2017!CG20 -> 27.805743 | T20: =$I20*KYZ_EEIO_2017!CH20 -> 348.96207 | U20: =$I20*KYZ_EEIO_2017!CI20 -> 55.611485 | V20: =$I20*KYZ_EEIO_2017!CJ20 -> 1001.0067 | W20: =$I20*KYZ_EEIO_2017!CK20 -> 1021.861 | X20: =$I20*KYZ_EEIO_2017!CL20 -> 107.05211 | Z20: =$I20*KYZ_EEIO_2017!CY20 -> 4162.2653 | AA20: =$I20*KYZ_EEIO_2017!CZ20 -> 42.037746 | AB20: =$I20*KYZ_EEIO_2017!DA20 -> 0.046555572 | AC20: =$I20*KYZ_EEIO_2017!DB20 -> 0 | AD20: =$I20*KYZ_EEIO_2017!DC20 -> 0.64577097
... A41: Other community, social, and personal services | B41: c34 | D41: 171.62248 | E41: 0 | F41: =D41*(1+E41) -> 171.62248 | H41: 229.81577 | I41: 229.81577 | J41: =IF(H41=0,0,(I41-H41)/H41) -> 0 | L41: 71200 | M41: =SUM(P41:X41) -> 71200 | N41: =M41-L41 -> 0 | P41: =$I41*KYZ_EEIO_2017!CD41 -> 5400 | Q41: =$I41*KYZ_EEIO_2017!CE41 -> 8200 | R41: =$I41*KYZ_EEIO_2017!CF41 -> 3800 | S41: =$I41*KYZ_EEIO_2017!CG41 -> 2900 | T41: =$I41*KYZ_EEIO_2017!CH41 -> 5100 | U41: =$I41*KYZ_EEIO_2017!CI41 -> 1800 | V41: =$I41*KYZ_EEIO_2017!CJ41 -> 8300 | W41: =$I41*KYZ_EEIO_2017!CK41 -> 30900 | X41: =$I41*KYZ_EEIO_2017!CL41 -> 4800 | Z41: =$I41*KYZ_EEIO_2017!CY41 -> 481.27813 | AA41: =$I41*KYZ_EEIO_2017!CZ41 -> 100.88187 | AB41: =$I41*KYZ_EEIO_2017!DA41 -> 1.0234676 | AC41: =$I41*KYZ_EEIO_2017!DB41 -> 0 | AD41: =$I41*KYZ_EEIO_2017!DC41 -> 14.19649
A42: Total | D42: =SUM(D8:D41) -> 9443.3367 | E42: =AVERAGE(E8:E41) -> 0 | F42: =SUM(F8:F41) -> 9443.3367 | H42: =SUM(H8:H41) -> 16084.194 | I42: =SUM(I8:I41) -> 16084.194 | J42: =AVERAGE(J8:J41) -> -1.2297191e-16 | L42: =SUM(L8:L41) -> 2351200 | M42: =SUM(M8:M41) -> 2351200 | N42: =M42-L42 -> 0 | P42: =SUM(P8:P41) -> 184800 | Q42: =SUM(Q8:Q41) -> 380100 | R42: =SUM(R8:R41) -> 158200 | S42: =SUM(S8:S41) -> 87700 | T42: =SUM(T8:T41) -> 537300 | U42: =SUM(U8:U41) -> 111300 | V42: =SUM(V8:V41) -> 333800 | W42: =SUM(W8:W41) -> 456500 | X42: =SUM(X8:X41) -> 101500 | Z42: =SUM(Z8:Z41) -> 846641.5 | AA42: =SUM(AA8:AA41) -> 23187.083 | AB42: =SUM(AB8:AB41) -> 7136.9483 | AC42: =SUM(AC8:AC41) -> 11933.122 | AD42: =SUM(AD8:AD41) -> 698.16202

Sheet KYZ_EEIO_2017
A1: Input-Output Table for 2017 | B1: Kyrgyz Republic Input-Output Table, 2017
B2: (current prices, $ million)
A3: in current prices | BB3: Regional disaggregation of value added | BO3: Employment | CB3: Employment/Output Coefficients | CO3: Environmental Factors | CW3: Environmental Factors by unit of output
A4: (industry-by-industry) | D4: AtB | E4: C | F4: 15t16 | G4: 17t18 | H4: 19 | I4: 20 | J4: 21t22 | K4: 23 | L4: 24 | M4: 25 | N4: 26 | O4: 27t28 | P4: 29 | Q4: 30t33 | R4: 34t35 | S4: 36t37 | T4: E | U4: F | V4: 50 | W4: 51 | X4: 52 | Y4: H | Z4: 60 | AA4: 61 | AB4: 62 | AC4: 63 | AD4: 64 | AE4: J | AF4: 70 | AG4: 71t74 | AH4: L | AI4: M | AJ4: N | AK4: O
A5: (millions of US$) | B5: Industry | D5: Agriculture, Hunting, Forestry, and Fishing | E5: Mining and Quarrying | F5: Food, Beverages, and Tobacco | G5: Textiles and Textile Products | H5: Leather, Leather Products, and Footwear | I5: Wood and Products of Wood and Cork | J5: Pulp, Paper, Paper Products, Printing, and Publishing | K5: Coke, Refined Petroleum, and Nuclear Fuel | L5: Chemicals and Chemical Products | M5: Rubber and Plastics | N5: Other Nonmetallic Minerals | O5: Basic Metals and Fabricated Metal | P5: Machinery, nec | Q5: Electrical and Optical Equipment | R5: Transport Equipment | S5: Manufacturing, nec; Recycling | T5: Electricity, Gas, and Water Supply | U5: Construction | V5: Sale, Maintenance, and Repair of Motor Vehicles and Motorcycles; Retail Sale of Fuel | W5: Wholesale Trade and Commission Trade, Except of Motor Vehicles and Motorcycles | X5: Retail Trade, Except of Motor Vehicles and Motorcycles; Repair of Household Goods | Y5: Hotels and Restaurants | Z5: Inland Transport | AA5: Water Transport | AB5: Air Transport | AC5: Other Supporting and Auxiliary Transport Activities; Activities of Travel Agencies | AD5: Post and Telecommunications | AE5: Financial Intermediation | AF5: Real Estate Activities | AG5: Renting of M&Eq and Other Business Activities | AH5: Public Administration and Defense; Compulsory Social Security | AI5: Education | AJ5: Health and Social Work | AK5: Other Community, Social, and Personal Services | AL5: Final Consumption Expenditure by Households | AM5: Final Consumption Expenditure by NPISHs | AN5: Final Consumption Expenditure by Government | AO5: Gross Fixed Capital Formation | AP5: Changes in Inventories and Valuables | AQ5: Exports | AR5: Total Output | AT5: Total Final Demand | AV5: Modeled Output (test) | AW5: Calibration | AY5: Value Added | AZ5: Value Added Coefficient | BD5: Batken oblast | BE5: Djalal-Abad | BF5: Issyk-Kul | BG5: Naryn oblast | BH5: Osh oblast | BI5: Talas oblast | BJ5: Chui oblast | BK5: Bishkek city | BL5: Osh city | BM5: Total | BQ5: Batken oblast | BR5: Djalal-Abad | BS5: Issyk-Kul | BT5: Naryn oblast | BU5: Osh oblast | BV5: Talas oblast | BW5: Chui oblast | BX5: Bishkek city | BY5: Osh city | BZ5: Total | CD5: Batken oblast | CE5: Djalal-Abad | CF5: Issyk-Kul | CG5: Naryn oblast | CH5: Osh oblast | CI5: Talas oblast | CJ5: Chui oblast | CK5: Bishkek city | CL5: Osh city | CM5: Total | CQ5: Energy Usage (TJ) | CR5: Total CO2 emissions (Gg) from EDGAR | CS5: WFN: Total water footprint (Mm3/yr) - Blue | CT5: WFN: Total water footprint (Mm3/yr) - Green | CU5: WFN: Total water footprint (Mm3/yr) - Grey | CY5: Energy Usage (TJ) | CZ5: Total CO2 emissions (Gg) from EDGAR | DA5: WFN: Total water footprint (Mm3/yr) - Blue | DB5: WFN: Total water footprint (Mm3/yr) - Green | DC5: WFN: Total water footprint (Mm3/yr) - Grey
D6: c1 | E6: c2 | F6: c3 | G6: c4 | H6: c5 | I6: c6 | J6: c7 | K6: c8 | L6: c9 | M6: c10 | N6: c11 | O6: c12 | P6: c13 | Q6: c14 | R6: c15 | S6: c16 | T6: c17 | U6: c18 | V6: c19 | W6: c20 | X6: c21 | Y6: c22 | Z6: c23 | AA6: c24 | AB6: c25 | AC6: c26 | AD6: c27 | AE6: c28 | AF6: c29 | AG6: c30 | AH6: c31 | AI6: c32 | AJ6: c33 | AK6: c34 | AL6: c36 | AM6: c37 | AN6: c38 | AO6: c39 | AP6: c40 | AQ6: c41
B7: Domestic
A8: AtB | B8: Agriculture, hunting, forestry, and fishing | C8: c1 | D8: 1378.3353 | E8: 0.32228241 | F8: 115.25778 | G8: 17.084252 | H8: 1.6513547 | I8: 0.008947298 | J8: 0.076101759 | K8: 0.2438327 | L8: 0.11898101 | M8: 0.055009628 | N8: 0.20030818 | O8: 0.045141771 | P8: 0 | Q8: 0 | R8: 0 | S8: 0 | T8: 0 | U8: 0.1738221 | V8: 0 | W8: 0.97974936 | X8: 0.13626731 | Y8: 12.342067 | Z8: 0 | AA8: 0 | AB8: 0 | AC8: 0 | AD8: 0 | AE8: 0 | AF8: 0.27517008 | AG8: 0.21189528 | AH8: 20.888329 | AI8: 10.639964 | AJ8: 11.998817 | AK8: 0.071295647 | AL8: 1088.3774 | AM8: 0.075040674 | AN8: 10.112054 | AO8: 10.78594 | AP8: -6.4143727 | AQ8: 380.41525 | AR8: 3054.468 | AT8: 1483.3513 | AV8: {=MMULT(D265:AK298,AT8:AT41)} -> 3054.468 | AW8: =AV8-AR8 -> 0 | AY8: 908.06214 | AZ8: =AY8/$AR8 -> 0.29728979 | BB8: c1 | BC8: Agriculture | BD8: =$AY8*BQ8/$BZ8 -> 87.887802 | BE8: =$AY8*BR8/$BZ8 -> 209.99147 | BF8: =$AY8*BS8/$BZ8 -> 70.947596 | BG8: =$AY8*BT8/$BZ8 -> 68.767174 | BH8: =$AY8*BU8/$BZ8 -> 294.52477 | BI8: =$AY8*BV8/$BZ8 -> 97.951291 | BJ8: =$AY8*BW8/$BZ8 -> 70.612146 | BK8: =$AY8*BX8/$BZ8 -> 5.367194 | BL8: =$AY8*BY8/$BZ8 -> 2.0126978 | BM8: =SUM(BD8:BL8) -> 908.06214 | BO8: c1 | BP8: Agriculture, hunting, forestry, and fishing | BQ8: 52400 | BR8: 125200 | BS8: 42300 | BT8: 41000 | BU8: 175600 | BV8: 58400 | BW8: 42100 | BX8: 3200 | BY8: 1200 | BZ8: 541400 | CB8: c1 | CC8: Agriculture, hunting, forestry, and fishing | CD8: =BQ8/$AR8 -> 17.155197 | CE8: =BR8/$AR8 -> 40.989135 | CF8: =BS8/$AR8 -> 13.848566 | CG8: =BT8/$AR8 -> 13.42296 | CH8: =BU8/$AR8 -> 57.489553 | CI8: =BV8/$AR8 -> 19.119533 | CJ8: =BW8/$AR8 -> 13.783088 | CK8: =BX8/$AR8 -> 1.0476456 | ... CM8: =BZ8/$AR8 -> 177.24854 | CO8: 1 | CP8: Agriculture, Hunting, Forestry, and Fishing | CQ8: 1912.0999 | CR8: 1350.7742 | CS8: 7117.8215 | CT8: 11933.122 | CU8: 432.85533 | CW8: 1 | CX8: Agriculture, Hunting, Forestry, and Fishing | CY8: =CQ8/$AR8 -> 0.62600097 | CZ8: =CR8/$AR8 -> 0.44222896 | DA8: =CS8/$AR8 -> 2.3302983 | DB8: =CT8/$AR8 -> 3.9067759 | DC8: =CU8/$AR8 -> 0.14171219
A9: C | B9: Mining and quarrying | C9: c2 | D9: 0.0028508189 | E9: 4.6143258 | F9: 2.8864094 | G9: 0.30416723 | H9: 0.032104905 | I9: 0.0028554454 | J9: 0.023218348 | K9: 8.3909665 | L9: 3.8761458 | M9: 1.882613 | N9: 6.8552143 | O9: 13.959651 | P9: 0.98480748 | Q9: 0.22346957 | R9: 0.56805703 | S9: 0.97188221 | T9: 22.130386 | U9: 13.959292 | V9: 0.22576287 | W9: 0.09627378 | X9: 0.45871501 | Y9: 0.17408476 | Z9: 0.66830111 | AA9: 0.0064488929 | AB9: 0.034474038 | AC9: 0.20273007 | AD9: 0.5113689 | AE9: 0 | AF9: 0.010026945 | AG9: 0.0077212692 | AH9: 1.701523 | AI9: 5.763147 | AJ9: 0.042799537 | AK9: 0.14884766 | AL9: 25.268908 | AM9: 0 | AN9: 0 | AO9: 3.7043922 | AP9: -0.39176031 | AQ9: 25.120691 | AR9: 145.42287 | AT9: 53.702231 | AV9: 145.42287 | AW9: =AV9-AR9 -> 0 | AY9: 70.980728 | AZ9: =AY9/$AR9 -> 0.48809879 | BB9: c2 | BC9: Mining and quarrying | BD9: =$AY9*BQ9/$BZ9 -> 23.473942 | BE9: =$AY9*BR9/$BZ9 -> 7.8246472 | BF9: =$AY9*BS9/$BZ9 -> 11.736971 | BG9: =$AY9*BT9/$BZ9 -> 18.443811 | BH9: =$AY9*BU9/$BZ9 -> 0 | BI9: =$AY9*BV9/$BZ9 -> 0.55890337 | BJ9: =$AY9*BW9/$BZ9 -> 8.9424539 | BK9: =$AY9*BX9/$BZ9 -> 0 | BL9: =$AY9*BY9/$BZ9 -> 0 | BM9: =SUM(BD9:BL9) -> 70.980728 | BO9: c2 | BP9: Mining and quarrying | BQ9: 4200 | BR9: 1400 | BS9: 2100 | BT9: 3300 | BU9: 0 | BV9: 100 | BW9: 1600 | BX9: 0 | BY9: 0 | BZ9: 12700 | CB9: c2 | CC9: Mining and quarrying | CD9: =BQ9/$AR9 -> 28.881289 | CE9: =BR9/$AR9 -> 9.6270963 | CF9: =BS9/$AR9 -> 14.440645 | CG9: =BT9/$AR9 -> 22.692441 | CH9: =BU9/$AR9 -> 0 | CI9: =BV9/$AR9 -> 0.68764974 | CJ9: =BW9/$AR9 -> 11.002396 | CK9: =BX9/$AR9 -> 0 | ... CM9: =BZ9/$AR9 -> 87.331517 | CO9: 2 | CP9: Mining and Quarrying | CQ9: 147.72395 | CR9: 181.80787 | CS9: 0.22026195 | CT9: 0 | CU9: 3.055247 | CW9: 2 | CX9: Mining and Quarrying | CY9: =CQ9/$AR9 -> 1.0158234 | CZ9: =CR9/$AR9 -> 1.2502013 | DA9: =CS9/$AR9 -> 0.0015146307 | DB9: =CT9/$AR9 -> 0 | DC9: =CU9/$AR9 -> 0.021009398
A10: 15t16 | B10: Food, beverages, and tobacco | C10: c3 | D10: 7.4546054 | E10: 0.17528078 | F10: 60.077878 | G10: 0.95281997 | H10: 0.10057032 | I10: 0.00046414201 | J10: 0.022884429 | K10: 2.2453305 | L10: 1.0370204 | M10: 0.4874213 | N10: 1.7748616 | O10: 1.3347884 | P10: 0.0036609658 | Q10: 0.00083073543 | R10: 0.0021117197 | S10: 0.0051796772 | T10: 1.3755839 | U10: 33.639682 | V10: 0.0042342592 | W10: 4.5028237 | X10: 56.710564 | Y10: 24.287439 | Z10: 2.9643079 | AA10: 0.028604627 | AB10: 0.15291261 | AC10: 0.89922691 | AD10: 4.0487025 | AE10: 0.30455039 | AF10: 5.2924821 | AG10: 4.0754867 | AH10: 21.267983 | AI10: 10.009758 | AJ10: 6.1944984 | AK10: 2.3336426 | AL10: 322.93788 | AM10: 0.49457835 | AN10: 0 | AO10: 24.004034 | AP10: 16.376746 | AQ10: 25.435918 | AR10: 643.01735 | AT10: 389.24916 | AV10: 643.01735 | AW10: =AV10-AR10 -> 0 | AY10: 174.12816 | AZ10: =AY10/$AR10 -> 0.27079854 | BB10: c3 | BC10: Food, beverages, and tobacco | BD10: =$AY10*BQ10/$BZ10 -> 6.1768434 | BE10: =$AY10*BR10/$BZ10 -> 24.927975 | BF10: =$AY10*BS10/$BZ10 -> 7.5004528 | BG10: =$AY10*BT10/$BZ10 -> 1.470677 | BH10: =$AY10*BU10/$BZ10 -> 18.456996 | BI10: =$AY10*BV10/$BZ10 -> 2.941354 | BJ10: =$AY10*BW10/$BZ10 -> 52.944372 | BK10: =$AY10*BX10/$BZ10 -> 54.04738 | BL10: =$AY10*BY10/$BZ10 -> 5.6621065 | BM10: =SUM(BD10:BL10) -> 174.12816 | BO10: c3 | BP10: Food, beverages, and tobacco | BQ10: 1314.7806 | BR10: 5306.0789 | BS10: 1596.5193 | BT10: 313.043 | BU10: 3928.6897 | BV10: 626.086 | BW10: 11269.548 | BX10: 11504.33 | BY10: 1205.2156 | BZ10: 37064.291 | CB10: c3 | CC10: Food, beverages, and tobacco | CD10: =BQ10/$AR10 -> 2.0447047 | CE10: =BR10/$AR10 -> 8.2518441 | CF10: =BS10/$AR10 -> 2.4828557 | CG10: =BT10/$AR10 -> 0.48683446 | CH10: =BU10/$AR10 -> 6.1097725 | CI10: =BV10/$AR10 -> 0.97366892 | CJ10: =BW10/$AR10 -> 17.526041 | CK10: =BX10/$AR10 -> 17.891166 | ... CM10: =BZ10/$AR10 -> 57.6412 | CO10: 3 | CP10: Food, Beverages, and Tobacco | CQ10: 736.61604 | CR10: 280.60886 | CS10: 1.187814 | CT10: 0 | CU10: 16.476134 | CW10: 3 | CX10: Food, Beverages, and Tobacco | CY10: =CQ10/$AR10 -> 1.1455617 | CZ10: =CR10/$AR10 -> 0.43639393 | DA10: =CS10/$AR10 -> 0.0018472504 | DB10: =CT10/$AR10 -> 0 | DC10: =CU10/$AR10 -> 0.025623156
A11: 17t18 | B11: Textiles and textile products | C11: c4 | D11: 0.0019179564 | E11: 0.035643025 | F11: 0.28227247 | G11: 3.3471472 | H11: 0.37845463 | I11: 0.0065982685 | J11: 0.084192735 | K11: 0.77681805 | L11: 0.35877844 | M11: 0.06761791 | N11: 0.24621909 | O11: 0.2302144 | P11: 0.09999728 | Q11: 0.022691084 | R11: 0.05768047 | S11: 0.24737829 | T11: 0.12832944 | U11: 0.024255061 | V11: 0.0035012439 | W11: 0.026120492 | X11: 0.22132882 | Y11: 0.98336914 | Z11: 0.070045362 | AA11: 0.00067591544 | AB11: 0.0036132613 | AC11: 0.021248358 | AD11: 0.077014289 | AE11: 0.0011700838 | AF11: 0.045537474 | AG11: 0.035066224 | AH11: 0.78931775 | AI11: 0.44280834 | AJ11: 0.56376094 | AK11: 0.39399717 | AL11: 84.96462 | AM11: 0.38056023 | AN11: 0 | AO11: 0.10511489 | AP11: 1.1652032 | AQ11: 31.620554 | AR11: 128.31083 | AT11: 118.23605 | AV11: 128.31083 | AW11: =AV11-AR11 -> 0 | AY11: 41.308522 | AZ11: =AY11/$AR11 -> 0.32194103 | BB11: c4 | BC11: Textile products | BD11: =$AY11*BQ11/$BZ11 -> 1.4653361 | BE11: =$AY11*BR11/$BZ11 -> 5.9136777 | BF11: =$AY11*BS11/$BZ11 -> 1.7793367 | BG11: =$AY11*BT11/$BZ11 -> 0.34888954 | BH11: =$AY11*BU11/$BZ11 -> 4.3785638 | BI11: =$AY11*BV11/$BZ11 -> 0.69777909 | BJ11: =$AY11*BW11/$BZ11 -> 12.560024 | BK11: =$AY11*BX11/$BZ11 -> 12.821691 | BL11: =$AY11*BY11/$BZ11 -> 1.3432247 | BM11: =SUM(BD11:BL11) -> 41.308522 | BO11: c4 | BP11: Textiles and textile products | BQ11: 311.90615 | BR11: 1258.7641 | BS11: 378.74318 | BT11: 74.263369 | BU11: 932.00528 | BV11: 148.52674 | BW11: 2673.4813 | BX11: 2729.1788 | BY11: 285.91397 | BZ11: 8792.7829 | CB11: c4 | CC11: Textiles and textile products | CD11: =BQ11/$AR11 -> 2.4308637 | CE11: =BR11/$AR11 -> 9.8102715 | CF11: =BS11/$AR11 -> 2.9517631 | CG11: =BT11/$AR11 -> 0.57877708 | CH11: =BU11/$AR11 -> 7.2636524 | CI11: =BV11/$AR11 -> 1.1575542 | CJ11: =BW11/$AR11 -> 20.835975 | CK11: =BX11/$AR11 -> 21.270058 | ... CM11: =BZ11/$AR11 -> 68.527206 | CO11: 4 | CP11: Textiles and Textile Products | CQ11: 257.57702 | CR11: 63.024613 | CS11: 0.48447421 | CT11: 0 | CU11: 6.7201275 | CW11: 4 | CX11: Textiles and Textile Products | CY11: =CQ11/$AR11 -> 2.0074456 | CZ11: =CR11/$AR11 -> 0.491187 | DA11: =CS11/$AR11 -> 0.0037757857 | DB11: =CT11/$AR11 -> 0 | DC11: =CU11/$AR11 -> 0.052373813
A12: 19 | B12: Leather, leather products, and footwear | C12: c5 | D12: 0.0002028535 | E12: 0.0037698002 | F12: 0.029854671 | G12: 0.37922646 | H12: 0.04002742 | I12: 0.00069786876 | J12: 0.0089046816 | K12: 0.082160502 | L12: 0.037946359 | M12: 0.007151638 | N12: 0.026041471 | O12: 0.024348727 | P12: 0.010576256 | Q12: 0.0023999325 | R12: 0.0061006002 | S12: 0.026164074 | T12: 0.01357282 | U12: 0.0025653472 | V12: 0.0003703106 | W12: 0.0027626453 | X12: 0.023408939 | Y12: 0.10400647 | Z12: 0.0074083785 | AA12: 7.1488493e-05 | AB12: 0.00038215816 | AC12: 0.0022473419 | AD12: 0.0081454501 | AE12: 0.00012375443 | AF12: 0.0048162909 | AG12: 0.0037087946 | AH12: 0.083482538 | AI12: 0.046833818 | AJ12: 0.059626423 | AK12: 0.041671283 | AL12: 8.9863204 | AM12: 0.04025012 | AN12: 0 | AO12: 0.011117523 | AP12: 0.12326842 | AQ12: 3.3437715 | AR12: 13.595506 | AT12: 12.504728 | AV12: 13.595506 | AW12: =AV12-AR12 -> -5.6843419e-14 | AY12: 4.3769511 | AZ12: =AY12/$AR12 -> 0.32194103 | BB12: c5 | BC12: Leather products & footwear | BD12: =$AY12*BQ12/$BZ12 -> 0.15526347 | BE12: =$AY12*BR12/$BZ12 -> 0.62659899 | BF12: =$AY12*BS12/$BZ12 -> 0.18853421 | BG12: =$AY12*BT12/$BZ12 -> 0.036967492 | BH12: =$AY12*BU12/$BZ12 -> 0.46394203 | BI12: =$AY12*BV12/$BZ12 -> 0.073934984 | BJ12: =$AY12*BW12/$BZ12 -> 1.3308297 | BK12: =$AY12*BX12/$BZ12 -> 1.3585553 | BL12: =$AY12*BY12/$BZ12 -> 0.14232484 | BM12: =SUM(BD12:BL12) -> 4.3769511 | BO12: c5 | BP12: Leather, leather products, and footwear | BQ12: 33.048821 | BR12: 133.3756 | BS12: 40.130712 | BT12: 7.868767 | BU12: 98.753026 | BV12: 15.737534 | BW12: 283.27561 | BX12: 289.17719 | BY12: 30.294753 | BZ12: 931.66201 | CB12: c5 | CC12: Leather, leather products, and footwear | CD12: =BQ12/$AR12 -> 2.4308637 | CE12: =BR12/$AR12 -> 9.8102715 | CF12: =BS12/$AR12 -> 2.9517631 | CG12: =BT12/$AR12 -> 0.57877708 | CH12: =BU12/$AR12 -> 7.2636524 | CI12: =BV12/$AR12 -> 1.1575542 | CJ12: =BW12/$AR12 -> 20.835975 | CK12: =BX12/$AR12 -> 21.270058 | ... CM12: =BZ12/$AR12 -> 68.527206 | CO12: 5 | CP12: Leather, Leather Products, and Footwear | CQ12: 33.107265 | CR12: 6.1392604 | CS12: 0.065430241 | CT12: 0 | CU12: 0.90758096 | CW12: 5 | CX12: Leather, Leather Products, and Footwear | CY12: =CQ12/$AR12 -> 2.4351625 | CZ12: =CR12/$AR12 -> 0.45156544 | DA12: =CS12/$AR12 -> 0.0048126376 | DB12: =CT12/$AR12 -> 0 | DC12: =CU12/$AR12 -> 0.066755955
A13: 20 | B13: Wood and products of wood and cork | C13: c6 | D13: 0.0003851752 | E13: 0.0030833725 | F13: 0.023914115 | G13: 0.00029565573 | H13: 3.1206515e-05 | I13: 0.016626927 | J13: 0.15233446 | K13: 0.013481925 | L13: 0.0062267143 | M13: 0.013500973 | N13: 0.049161491 | O13: 0.072919217 | P13: 0.0065897943 | Q13: 0.0014953364 | R13: 0.0038011277 | S13: 0.099972398 | T13: 0.016183525 | U13: 0.34998044 | V13: 0.0010601191 | W13: 0.045637327 | X13: 0.06188032 | Y13: 0.060578199 | Z13: 0.0073946369 | AA13: 7.1355891e-05 | AB13: 0.00038144931 | AC13: 0.0022431733 | AD13: 0.010550598 | AE13: 4.6996612e-05 | AF13: 0.0065738699 | AG13: 0.0050622219 | AH13: 0.024156231 | AI13: 0.026508898 | AJ13: 0.0027706604 | AK13: 0.044242046 | AL13: 1.8517087 | AM13: 0.00025575996 | AN13: 0 | AO13: 0.0069802045 | AP13: 0.010329341 | AQ13: 0.95137723 | AR13: 3.9497932 | AT13: 2.8206512 | AV13: 3.9497932 | AW13: =AV13-AR13 -> 0 | AY13: 1.6822554 | AZ13: =AY13/$AR13 -> 0.42590974 | BB13: c6 | BC13: Wood products | BD13: =$AY13*BQ13/$BZ13 -> 0.0596746 | BE13: =$AY13*BR13/$BZ13 -> 0.24082964 | BF13: =$AY13*BS13/$BZ13 -> 0.072462014 | BG13: =$AY13*BT13/$BZ13 -> 0.014208238 | BH13: =$AY13*BU13/$BZ13 -> 0.17831339 | BI13: =$AY13*BV13/$BZ13 -> 0.028416476 | BJ13: =$AY13*BW13/$BZ13 -> 0.51149657 | BK13: =$AY13*BX13/$BZ13 -> 0.52215275 | BL13: =$AY13*BY13/$BZ13 -> 0.054701717 | BM13: =SUM(BD13:BL13) -> 1.6822554 | BO13: c6 | BP13: Wood and products of wood and cork | BQ13: 12.70212 | BR13: 51.262127 | BS13: 15.424003 | BT13: 3.0243143 | BU13: 37.955145 | BV13: 6.0486286 | BW13: 108.87531 | BX13: 111.14355 | BY13: 11.64361 | BZ13: 358.07881 | CB13: c6 | CC13: Wood and products of wood and cork | CD13: =BQ13/$AR13 -> 3.215895 | CE13: =BR13/$AR13 -> 12.978433 | CF13: =BS13/$AR13 -> 3.9050153 | CG13: =BT13/$AR13 -> 0.76568928 | CH13: =BU13/$AR13 -> 9.6094005 | CI13: =BV13/$AR13 -> 1.5313786 | CJ13: =BW13/$AR13 -> 27.564814 | CK13: =BX13/$AR13 -> 28.139081 | ... CM13: =BZ13/$AR13 -> 90.657611 | CO13: 6 | CP13: Wood and Products of Wood and Cork | CQ13: 22.713789 | CR13: 1.7543551 | CS13: 0.049561495 | CT13: 0 | CU13: 0.68746605 | CW13: 6 | CX13: Wood and Products of Wood and Cork | CY13: =CQ13/$AR13 -> 5.7506275 | CZ13: =CR13/$AR13 -> 0.44416379 | DA13: =CS13/$AR13 -> 0.012547871 | DB13: =CT13/$AR13 -> 0 | DC13: =CU13/$AR13 -> 0.17405115
A14: 21t22 | B14: Pulp, paper, paper products, printing, and publishing | C14: c7 | D14: 0.011230723 | E14: 0.087607995 | F14: 0.3431279 | G14: 0.023196666 | H14: 0.0024484121 | I14: 0.20582269 | J14: 1.3532635 | K14: 0.18267617 | L14: 0.084370168 | M14: 0.13162048 | N14: 0.47927356 | O14: 0.94402353 | P14: 0.099656615 | Q14: 0.022613781 | R14: 0.057483967 | S14: 0.87684298 | T14: 0.28172083 | U14: 3.0704924 | V14: 0.015453588 | W14: 0.48384833 | X14: 1.2888536 | Y14: 0.73539986 | Z14: 0.074604433 | AA14: 0.00071990902 | AB14: 0.0038484391 | AC14: 0.022631358 | AD14: 0.12696248 | AE14: 0.080066201 | AF14: 0.06541754 | AG14: 0.05037491 | AH14: 0.44159581 | AI14: 0.78944447 | AJ14: 0.12968381 | AK14: 0.55237798 | AL14: 16.282416 | AM14: 0.003945684 | AN14: 0.17572229 | AO14: 0.058627837 | AP14: 0.19917203 | AQ14: 9.6412972 | AR14: 39.479936 | AT14: 26.361181 | AV14: 39.479936 | AW14: =AV14-AR14 -> 0 | AY14: 13.251194 | AZ14: =AY14/$AR14 -> 0.33564375 | BB14: c7 | BC14: Paper products | BD14: =$AY14*BQ14/$BZ14 -> 0.47005924 | BE14: =$AY14*BR14/$BZ14 -> 1.8970248 | BF14: =$AY14*BS14/$BZ14 -> 0.57078622 | BG14: =$AY14*BT14/$BZ14 -> 0.11191887 | BH14: =$AY14*BU14/$BZ14 -> 1.4045818 | BI14: =$AY14*BV14/$BZ14 -> 0.22383773 | BJ14: =$AY14*BW14/$BZ14 -> 4.0290792 | BK14: =$AY14*BX14/$BZ14 -> 4.1130183 | BL14: =$AY14*BY14/$BZ14 -> 0.43088763 | BM14: =SUM(BD14:BL14) -> 13.251194 | BO14: c7 | BP14: Pulp, paper, paper products, printing, and publishing | BQ14: 100.05511 | BR14: 403.79385 | BS14: 121.49549 | BT14: 23.822646 | BU14: 298.97421 | BV14: 47.645292 | BW14: 857.61526 | BX14: 875.48224 | BY14: 91.717187 | BZ14: 2820.6013 | CB14: c7 | CC14: Pulp, paper, paper products, printing, and publishing | CD14: =BQ14/$AR14 -> 2.5343281 | CE14: =BR14/$AR14 -> 10.227824 | CF14: =BS14/$AR14 -> 3.0773985 | CG14: =BT14/$AR14 -> 0.60341146 | CH14: =BU14/$AR14 -> 7.5728139 | CI14: =BV14/$AR14 -> 1.2068229 | CJ14: =BW14/$AR14 -> 21.722813 | CK14: =BX14/$AR14 -> 22.175371 | ... CM14: =BZ14/$AR14 -> 71.443917 | CO14: 7 | CP14: Pulp, Paper, Paper Products, Printing, and Publishing | CQ14: 78.993743 | CR14: 17.757572 | CS14: 0.15893346 | CT14: 0 | CU14: 2.2045613 | CW14: 7 | CX14: Pulp, Paper, Paper Products, Printing, and Publishing | CY14: =CQ14/$AR14 -> 2.0008579 | CZ14: =CR14/$AR14 -> 0.44978727 | DA14: =CS14/$AR14 -> 0.0040256767 | DB14: =CT14/$AR14 -> 0 | DC14: =CU14/$AR14 -> 0.055840043
A15: 23 | B15: Coke, refined petroleum, and nuclear fuel | C15: c8 | D15: 2.2130152 | E15: 0.95280034 | F15: 0.19098439 | G15: 0.14112795 | H15: 0.01489608 | I15: 0.010911788 | J15: 0.16828598 | K15: 0.44978891 | L15: 0.20773792 | M15: 0.045088967 | N15: 0.16418379 | O15: 1.5555215 | P15: 0.12195166 | Q15: 0.027672907 | R15: 0.070344204 | S15: 0.019759601 | T15: 1.6404699 | U15: 8.6613919 | V15: 0.10687937 | W15: 0.94616081 | X15: 6.5938172 | Y15: 0.016129211 | Z15: 5.1022493 | AA15: 0.041192671 | AB15: 0.22020489 | AC15: 1.5196828 | AD15: 2.2148989 | AE15: 0.04700809 | AF15: 0.37705137 | AG15: 0.29034918 | AH15: 0.71652913 | AI15: 0.032257144 | AJ15: 0.40635281 | AK15: 0.19839645 | AL15: 30.250183 | AM15: 0.61423419 | AN15: 0 | AO15: 7.0251813 | AP15: 1.926133 | AQ15: 9.406335 | AR15: 84.707159 | AT15: 49.222067 | AV15: 84.707159 | AW15: =AV15-AR15 -> 0 | AY15: 29.52951 | AZ15: =AY15/$AR15 -> 0.34860701 | BB15: c8 | BC15: Coke, refined petroleum, and nuclear fuel | BD15: =$AY15*BQ15/$BZ15 -> 1.0474995 | BE15: =$AY15*BR15/$BZ15 -> 4.2274087 | BF15: =$AY15*BS15/$BZ15 -> 1.2719637 | BG15: =$AY15*BT15/$BZ15 -> 0.24940464 | BH15: =$AY15*BU15/$BZ15 -> 3.1300283 | BI15: =$AY15*BV15/$BZ15 -> 0.49880929 | BJ15: =$AY15*BW15/$BZ15 -> 8.9785671 | BK15: =$AY15*BX15/$BZ15 -> 9.1656206 | BL15: =$AY15*BY15/$BZ15 -> 0.96020787 | BM15: =SUM(BD15:BL15) -> 29.52951 | BO15: c8 | BP15: Coke, refined petroleum, and nuclear fuel | BQ15: 222.96696 | BR15: 899.83096 | BS15: 270.7456 | BT15: 53.087372 | BU15: 666.24652 | BV15: 106.17474 | BW15: 1911.1454 | BX15: 1950.9609 | BY15: 204.38638 | BZ15: 6285.5449 | CB15: c8 | CC15: Coke, refined petroleum, and nuclear fuel | CD15: =BQ15/$AR15 -> 2.6322092 | CE15: =BR15/$AR15 -> 10.622844 | CF15: =BS15/$AR15 -> 3.196254 | CG15: =BT15/$AR15 -> 0.62671648 | CH15: =BU15/$AR15 -> 7.8652918 | CI15: =BV15/$AR15 -> 1.253433 | CJ15: =BW15/$AR15 -> 22.561793 | CK15: =BX15/$AR15 -> 23.031831 | ... CM15: =BZ15/$AR15 -> 74.203231 | CO15: 8 | CP15: Coke, Refined Petroleum, and Nuclear Fuel | CQ15: 8207.6301 | CR15: 93.403021 | CS15: 0.11881106 | CT15: 0 | CU15: 1.6480247 | CW15: 8 | CX15: Coke, Refined Petroleum, and Nuclear Fuel | CY15: =CQ15/$AR15 -> 96.894173 | CZ15: =CR15/$AR15 -> 1.1026579 | DA15: =CS15/$AR15 -> 0.0014026094 | DB15: =CT15/$AR15 -> 0 | DC15: =CU15/$AR15 -> 0.019455554
A16: 24 | B16: Chemicals and chemical products | C16: c9 | D16: 1.012228 | E16: 0.48455264 | F16: 0.087355813 | G16: 0.064551593 | H16: 0.006813432 | I16: 0.0049910263 | J16: 0.076973613 | K16: 0.2057324 | L16: 0.095018837 | M16: 0.020623588 | N16: 0.075097281 | O16: 0.7114919 | P16: 0.055780405 | Q16: 0.012657523 | R16: 0.032175275 | S16: 0.0090379951 | T16: 0.84134828 | U16: 3.9617004 | V16: 0.05969197 | W16: 0.4931462 | X16: 3.3940046 | Y16: 0.0073774632 | Z16: 2.1860292 | AA16: 0.023746204 | AB16: 0.12694079 | AC16: 0.63534815 | AD16: 1.0130896 | AE16: 0.021501391 | AF16: 0.17246242 | AG16: 0.13280504 | AH16: 0.32773875 | AI16: 0.014754342 | AJ16: 0.18586482 | AK16: 0.090746071 | AL16: 13.836363 | AM16: 0.28094928 | AN16: 0 | AO16: 3.2133015 | AP16: 0.88178625 | AQ16: 4.2921988 | AR16: 39.147976 | AT16: 22.504599 | AV16: 39.147976 | AW16: =AV16-AR16 -> 0 | AY16: 13.654874 | AZ16: =AY16/$AR16 -> 0.34880155 | BB16: c9 | BC16: Chemical products | BD16: =$AY16*BQ16/$BZ16 -> 0.48437899 | BE16: =$AY16*BR16/$BZ16 -> 1.9548152 | BF16: =$AY16*BS16/$BZ16 -> 0.58817449 | BG16: =$AY16*BT16/$BZ16 -> 0.11532833 | BH16: =$AY16*BU16/$BZ16 -> 1.4473706 | BI16: =$AY16*BV16/$BZ16 -> 0.23065666 | BJ16: =$AY16*BW16/$BZ16 -> 4.1518199 | BK16: =$AY16*BX16/$BZ16 -> 4.2383162 | BL16: =$AY16*BY16/$BZ16 -> 0.44401408 | BM16: =SUM(BD16:BL16) -> 13.654874 | BO16: c9 | BP16: Chemicals and chemical products | BQ16: 103.10316 | BR16: 416.09491 | BS16: 125.1967 | BT16: 24.548372 | BU16: 308.08207 | BV16: 49.096745 | BW16: 883.74141 | BX16: 902.15269 | BY16: 94.511234 | BZ16: 2906.5273 | CB16: c9 | CC16: Chemicals and chemical products | CD16: =BQ16/$AR16 -> 2.6336781 | CE16: =BR16/$AR16 -> 10.628772 | CF16: =BS16/$AR16 -> 3.1980376 | CG16: =BT16/$AR16 -> 0.6270662 | CH16: =BU16/$AR16 -> 7.8696808 | CI16: =BV16/$AR16 -> 1.2541324 | CJ16: =BW16/$AR16 -> 22.574383 | CK16: =BX16/$AR16 -> 23.044683 | ... CM16: =BZ16/$AR16 -> 74.244638 | CO16: 9 | CP16: Chemicals and Chemical Products | CQ16: 128.44983 | CR16: 39.609975 | CS16: 0.26535046 | CT16: 0 | CU16: 3.6806685 | CW16: 9 | CX16: Chemicals and Chemical Products | CY16: =CQ16/$AR16 -> 3.2811359 | CZ16: =CR16/$AR16 -> 1.0118014 | DA16: =CS16/$AR16 -> 0.00677814 | DB16: =CT16/$AR16 -> 0 | DC16: =CU16/$AR16 -> 0.094019382
A17: 25 | B17: Rubber and plastics | C17: c10 | D17: 0.10100093 | E17: 0.01321659 | F17: 0.78944415 | G17: 0.036063585 | H17: 0.0038065178 | I17: 0.00016242853 | J17: 0.0034703842 | K17: 0.016133593 | L17: 0.007451404 | M17: 2.1045083 | N17: 7.6632084 | O17: 0.043316434 | P17: 0.067143821 | Q17: 0.015236075 | R17: 0.038729925 | S17: 0.01043199 | T17: 0.78056237 | U17: 28.221606 | V17: 0.00014112358 | W17: 1.1601364 | X17: 4.4560687 | Y17: 0.4281154 | Z17: 1.1252652 | AA17: 0.01085845 | AB17: 0.058046341 | AC17: 0.34135074 | AD17: 0.69847301 | AE17: 0.0012262176 | AF17: 0.6578214 | AG17: 0.50655671 | AH17: 0.041606396 | AI17: 0.055534743 | AJ17: 0.0077454652 | AK17: 0.10030262 | AL17: 13.113181 | AM17: 0.012706102 | AN17: 0 | AO17: 3.3823209 | AP17: 0.99270697 | AQ17: 9.2741681 | AR17: 76.339825 | AT17: 26.775083 | AV17: 76.339825 | AW17: =AV17-AR17 -> 0 | AY17: 27.272356 | AZ17: =AY17/$AR17 -> 0.35724939 | BB17: c10 | BC17: Rubber and plastics | BD17: =$AY17*BQ17/$BZ17 -> 0.96743154 | BE17: =$AY17*BR17/$BZ17 -> 3.9042773 | BF17: =$AY17*BS17/$BZ17 -> 1.1747383 | BG17: =$AY17*BT17/$BZ17 -> 0.23034084 | BH17: =$AY17*BU17/$BZ17 -> 2.8907776 | BI17: =$AY17*BV17/$BZ17 -> 0.46068169 | BJ17: =$AY17*BW17/$BZ17 -> 8.2922704 | BK17: =$AY17*BX17/$BZ17 -> 8.465026 | BL17: =$AY17*BY17/$BZ17 -> 0.88681225 | BM17: =SUM(BD17:BL17) -> 27.272356 | BO17: c10 | BP17: Rubber and plastics | BQ17: 205.92399 | BR17: 831.05038 | BS17: 250.05056 | BT17: 49.029521 | BU17: 615.32049 | BV17: 98.059042 | BW17: 1765.0628 | BX17: 1801.8349 | BY17: 188.76366 | BZ17: 5805.0953 | CB17: c10 | CC17: Rubber and plastics | CD17: =BQ17/$AR17 -> 2.6974647 | CE17: =BR17/$AR17 -> 10.886197 | CF17: =BS17/$AR17 -> 3.2754929 | CG17: =BT17/$AR17 -> 0.64225351 | CH17: =BU17/$AR17 -> 8.0602816 | CI17: =BV17/$AR17 -> 1.284507 | CJ17: =BW17/$AR17 -> 23.121126 | CK17: =BX17/$AR17 -> 23.602817 | ... CM17: =BZ17/$AR17 -> 76.042816 | CO17: 10 | CP17: Rubber and Plastics | CQ17: 6052.6366 | CR17: 89.757302 | CS17: 0.47699451 | CT17: 0 | CU17: 6.6163769 | CW17: 10 | CX17: Rubber and Plastics | CY17: =CQ17/$AR17 -> 79.285439 | CZ17: =CR17/$AR17 -> 1.1757599 | DA17: =CS17/$AR17 -> 0.006248305 | DB17: =CT17/$AR17 -> 0 | DC17: =CU17/$AR17 -> 0.086670056
A18: 26 | B18: Other nonmetallic minerals | C18: c11 | D18: 0.38473113 | E18: 0.050344426 | F18: 3.0071382 | G18: 0.13737284 | H18: 0.014499727 | I18: 0.0006187202 | J18: 0.013219333 | K18: 0.061455826 | L18: 0.028383771 | M18: 6.6776852 | N18: 26.753112 | O18: 0.16500027 | P18: 0.25576318 | Q18: 0.058037017 | R18: 0.14752942 | S18: 0.039737372 | T18: 2.9733059 | U18: 96.621799 | V18: 0.0005375657 | W18: 4.4191732 | X18: 16.973987 | Y18: 1.6307704 | Z18: 4.2863423 | AA18: 0.041361838 | AB18: 0.22110921 | AC18: 1.3002679 | AD18: 2.6606124 | AE18: 0.0046708886 | AF18: 2.5057629 | AG18: 1.9295678 | AH18: 0.15848642 | AI18: 0.21154207 | AJ18: 0.029503904 | AK18: 0.38207114 | AL18: 49.950522 | AM18: 0.048399885 | AN18: 0 | AO18: 12.883883 | AP18: 3.7562968 | AQ18: 39.50404 | AR18: 280.28864 | AT18: 106.14314 | AV18: 280.28864 | AW18: =AV18-AR18 -> 0 | AY18: 100.13295 | AZ18: =AY18/$AR18 -> 0.35724939 | BB18: c11 | BC18: Other nonmetallic minerals | BD18: =$AY18*BQ18/$BZ18 -> 3.5520133 | BE18: =$AY18*BR18/$BZ18 -> 14.334911 | BF18: =$AY18*BS18/$BZ18 -> 4.313159 | BG18: =$AY18*BT18/$BZ18 -> 0.84571745 | BH18: =$AY18*BU18/$BZ18 -> 10.613754 | BI18: =$AY18*BV18/$BZ18 -> 1.6914349 | BJ18: =$AY18*BW18/$BZ18 -> 30.445828 | BK18: =$AY18*BX18/$BZ18 -> 31.080116 | BL18: =$AY18*BY18/$BZ18 -> 3.2560122 | BM18: =SUM(BD18:BL18) -> 100.13295 | BO18: c11 | BP18: Other nonmetallic minerals | BQ18: 756.06873 | BR18: 3051.2774 | BS18: 918.08346 | BT18: 180.01636 | BU18: 2259.2054 | BV18: 360.03273 | BW18: 6480.5891 | BX18: 6615.6014 | BY18: 693.063 | BZ18: 21313.938 | CB18: c11 | CC18: Other nonmetallic minerals | CD18: =BQ18/$AR18 -> 2.6974647 | CE18: =BR18/$AR18 -> 10.886197 | CF18: =BS18/$AR18 -> 3.2754929 | CG18: =BT18/$AR18 -> 0.64225351 | CH18: =BU18/$AR18 -> 8.0602816 | CI18: =BV18/$AR18 -> 1.284507 | CJ18: =BW18/$AR18 -> 23.121126 | CK18: =BX18/$AR18 -> 23.602817 | ... CM18: =BZ18/$AR18 -> 76.042816 | CO18: 11 | CP18: Other Nonmetallic Minerals | CQ18: 436.36594 | CR18: 351.34226 | CS18: 0.80348773 | CT18: 0 | CU18: 11.145155 | CW18: 11 | CX18: Other Nonmetallic Minerals | CY18: =CQ18/$AR18 -> 1.5568449 | CZ18: =CR18/$AR18 -> 1.2535016 | DA18: =CS18/$AR18 -> 0.0028666439 | DB18: =CT18/$AR18 -> 0 | DC18: =CU18/$AR18 -> 0.039763134
A19: 27t28 | B19: Basic metals and fabricated metal | C19: c12 | D19: 5.3915921 | E19: 0.86736334 | F19: 1.0242407 | G19: 0.7388868 | H19: 0.077989632 | I19: 0.010170561 | J19: 0.21518996 | K19: 0.31077493 | L19: 0.14353341 | M19: 1.1610611 | N19: 4.2278059 | O19: 680.66175 | P19: 1.3994914 | Q19: 0.3175684 | R19: 0.80725516 | S19: 0.54063281 | T19: 3.5194957 | U19: 39.760639 | V19: 0.040742772 | W19: 0.46117166 | X19: 1.0820738 | Y19: 0.16646097 | Z19: 0.29113884 | AA19: 0.0028093971 | AB19: 0.015018278 | AC19: 0.088317371 | AD19: 0.68821235 | AE19: 0.0096207525 | AF19: 0.19080627 | AG19: 0.14693076 | AH19: 0.021620347 | AI19: 0.14276341 | AJ19: 0.050785418 | AK19: 0.59048227 | AL19: 13.142784 | AM19: 0.0042810917 | AN19: 0 | AO19: 0.36787173 | AP19: 8.9889044 | AQ19: 960.72219 | AR19: 1728.3904 | AT19: 983.22603 | AV19: 1728.3904 | AW19: =AV19-AR19 -> 0 | AY19: 668.72253 | AZ19: =AY19/$AR19 -> 0.38690479 | BB19: c12 | BC19: Basic metals and fabricated metal | BD19: =$AY19*BQ19/$BZ19 -> 23.721576 | BE19: =$AY19*BR19/$BZ19 -> 95.733504 | BF19: =$AY19*BS19/$BZ19 -> 28.804771 | BG19: =$AY19*BT19/$BZ19 -> 5.6479943 | BH19: =$AY19*BU19/$BZ19 -> 70.882329 | BI19: =$AY19*BV19/$BZ19 -> 11.295989 | BJ19: =$AY19*BW19/$BZ19 -> 203.3278 | BK19: =$AY19*BX19/$BZ19 -> 207.56379 | BL19: =$AY19*BY19/$BZ19 -> 21.744778 | BM19: =SUM(BD19:BL19) -> 668.72253 | BO19: c12 | BP19: Basic metals and fabricated metal | BQ19: 5049.2891 | BR19: 20377.488 | BS19: 6131.2797 | BT19: 1202.2117 | BU19: 15087.757 | BV19: 2404.4234 | BW19: 43279.621 | BX19: 44181.28 | BY19: 4628.515 | BZ19: 142341.87 | CB19: c12 | CC19: Basic metals and fabricated metal | CD19: =BQ19/$AR19 -> 2.9213823 | CE19: =BR19/$AR19 -> 11.789864 | CF19: =BS19/$AR19 -> 3.5473928 | CG19: =BT19/$AR19 -> 0.69556721 | CH19: =BU19/$AR19 -> 8.7293685 | CI19: =BV19/$AR19 -> 1.3911344 | CJ19: =BW19/$AR19 -> 25.04042 | CK19: =BX19/$AR19 -> 25.562095 | ... CM19: =BZ19/$AR19 -> 82.355157 | CO19: 12 | CP19: Basic Metals and Fabricated Metal | CQ19: 1297.7736 | CR19: 2080.1698 | CS19: 1.3834284 | CT19: 0 | CU19: 19.189494 | CW19: 12 | CX19: Basic Metals and Fabricated Metal | CY19: =CQ19/$AR19 -> 0.75085676 | CZ19: =CR19/$AR19 -> 1.2035301 | DA19: =CS19/$AR19 -> 0.00080041428 | DB19: =CT19/$AR19 -> 0 | DC19: =CU19/$AR19 -> 0.011102523
A20: 29 | B20: Machinery, nec | C20: c13 | D20: 2.8659537 | E20: 0.12127128 | F20: 0.14301149 | G20: 0.018525718 | H20: 0.0019553928 | I20: 0.0011933615 | J20: 0.027885612 | K20: 0.033765802 | L20: 0.015594954 | M20: 0.073923135 | N20: 0.26917849 | O20: 0.59948273 | P20: 0.17149107 | Q20: 0.03891424 | R20: 0.098919542 | S20: 0.020215163 | T20: 1.1289642 | U20: 3.5368231 | V20: 0.0079612419 | W20: 0.31620733 | X20: 1.4569704 | Y20: 0.33468868 | Z20: 1.2109127 | AA20: 0.013114207 | AB20: 0.070105008 | AC20: 0.35235485 | AD20: 2.2434052 | AE20: 0.02805891 | AF20: 0.19473144 | AG20: 0.14995334 | AH20: 0.33365425 | AI20: 0.18939591 | AJ20: 0.10855432 | AK20: 0.408204 | AL20: 12.91017 | AM20: 0.037978036 | AN20: 0 | AO20: 0.13540937 | AP20: 0.022426628 | AQ20: 4.506938 | AR20: 34.198262 | AT20: 17.612922 | AV20: 34.198262 | AW20: =AV20-AR20 -> 0 | AY20: 15.466766 | AZ20: =AY20/$AR20 -> 0.45226758 | BB20: c13 | BC20: Machinery, nec | BD20: =$AY20*BQ20/$BZ20 -> 0.54865216 | BE20: =$AY20*BR20/$BZ20 -> 2.2142033 | BF20: =$AY20*BS20/$BZ20 -> 0.66622048 | BG20: =$AY20*BT20/$BZ20 -> 0.13063147 | BH20: =$AY20*BU20/$BZ20 -> 1.6394249 | BI20: =$AY20*BV20/$BZ20 -> 0.26126293 | BJ20: =$AY20*BW20/$BZ20 -> 4.7027328 | BK20: =$AY20*BX20/$BZ20 -> 4.8007064 | BL20: =$AY20*BY20/$BZ20 -> 0.50293114 | BM20: =SUM(BD20:BL20) -> 15.466766 | BO20: c13 | BP20: Machinery, nec | BQ20: 116.78412 | BR20: 471.30734 | BS20: 141.80929 | BT20: 27.805743 | BU20: 348.96207 | BV20: 55.611485 | BW20: 1001.0067 | BX20: 1021.861 | BY20: 107.05211 | BZ20: 3292.1999 | CB20: c13 | CC20: Machinery, nec | CD20: =BQ20/$AR20 -> 3.4149138 | CE20: =BR20/$AR20 -> 13.781616 | CF20: =BS20/$AR20 -> 4.146681 | CG20: =BT20/$AR20 -> 0.81307472 | CH20: =BU20/$AR20 -> 10.204088 | CI20: =BV20/$AR20 -> 1.6261494 | CJ20: =BW20/$AR20 -> 29.27069 | CK20: =BX20/$AR20 -> 29.880496 | ... CM20: =BZ20/$AR20 -> 96.268046 | CO20: 13 | CP20: Machinery, nec | CQ20: 4162.2653 | CR20: 42.037746 | CS20: 0.046555572 | CT20: 0 | CU20: 0.64577097 | CW20: 13 | CX20: Machinery, nec | CY20: =CQ20/$AR20 -> 121.70985 | CZ20: =CR20/$AR20 -> 1.2292363 | DA20: =CS20/$AR20 -> 0.0013613432 | DB20: =CT20/$AR20 -> 0 | DC20: =CU20/$AR20 -> 0.018883151
A21: 30t33 | B21: Electrical and optical equipment | C21: c14 | D21: 0.64764109 | E21: 0.027404581 | F21: 0.03231738 | G21: 0.0041863957 | H21: 0.0004418748 | I21: 0.00026967287 | J21: 0.0063015212 | K21: 0.007630312 | L21: 0.0035241089 | M21: 0.016704966 | N21: 0.060828287 | O21: 0.13546962 | P21: 0.038753125 | Q21: 0.0087937432 | R21: 0.022353592 | S21: 0.0045681724 | T21: 0.27909076 | U21: 0.79924249 | V21: 0.0017990616 | W21: 0.071455746 | X21: 0.32924254 | Y21: 0.075632115 | Z21: 0.30711024 | AA21: 0.002963516 | AB21: 0.015842155 | AC21: 0.093162316 | AD21: 0.54039789 | AE21: 0.0063406828 | AF21: 0.044004926 | AG21: 0.033886083 | AH21: 0.075398358 | AI21: 0.042799217 | AJ21: 0.024530836 | AK21: 0.092244926 | AL21: 2.9176493 | AM21: 0.0085828665 | AN21: 0 | AO21: 0.030601912 | AP21: 0.0050667365 | AQ21: 1.0129548 | AR21: 7.827188 | AT21: 3.9748557 | AV21: 7.827188 | AW21: =AV21-AR21 -> 0 | AY21: 3.5736685 | AZ21: =AY21/$AR21 -> 0.45657119 | BB21: c14 | BC21: Electrical and optical equipment | BD21: =$AY21*BQ21/$BZ21 -> 0.12676865 | BE21: =$AY21*BR21/$BZ21 -> 0.51160204 | BF21: =$AY21*BS21/$BZ21 -> 0.15393336 | BG21: =$AY21*BT21/$BZ21 -> 0.030183011 | BH21: =$AY21*BU21/$BZ21 -> 0.37879679 | BI21: =$AY21*BV21/$BZ21 -> 0.060366022 | BJ21: =$AY21*BW21/$BZ21 -> 1.0865884 | BK21: =$AY21*BX21/$BZ21 -> 1.1092257 | BL21: =$AY21*BY21/$BZ21 -> 0.11620459 | BM21: =SUM(BD21:BL21) -> 3.5736685 | BO21: c14 | BP21: Electrical and optical equipment | BQ21: 26.983517 | BR21: 108.89776 | BS21: 32.765699 | BT21: 6.4246469 | BU21: 80.629318 | BV21: 12.849294 | BW21: 231.28729 | BX21: 236.10577 | BY21: 24.73489 | BZ21: 760.67819 | CB21: c14 | CC21: Electrical and optical equipment | CD21: =BQ21/$AR21 -> 3.4474088 | CE21: =BR21/$AR21 -> 13.912757 | CF21: =BS21/$AR21 -> 4.1861393 | CG21: =BT21/$AR21 -> 0.82081163 | CH21: =BU21/$AR21 -> 10.301186 | CI21: =BV21/$AR21 -> 1.6416233 | CJ21: =BW21/$AR21 -> 29.549219 | CK21: =BX21/$AR21 -> 30.164827 | ... CM21: =BZ21/$AR21 -> 97.184096 | CO21: 14 | CP21: Electrical and Optical Equipment | CQ21: 9.6804775 | CR21: 9.0456519 | CS21: 0.015848715 | CT21: 0 | CU21: 0.21983707 | CW21: 14 | CX21: Electrical and Optical Equipment | CY21: =CQ21/$AR21 -> 1.2367759 | CZ21: =CR21/$AR21 -> 1.1556707 | DA21: =CS21/$AR21 -> 0.0020248288 | DB21: =CT21/$AR21 -> 0 | DC21: =CU21/$AR21 -> 0.02808634
A22: 34t35 | B22: Transport equipment | C22: c15 | D22: 1.6610626 | E22: 0.070286964 | F22: 0.082887256 | G22: 0.010737221 | H22: 0.0011333156 | I22: 0.00069165396 | J22: 0.016162071 | K22: 0.019570139 | L22: 0.0090385951 | M22: 0.042844711 | N22: 0.15601171 | O22: 0.34745096 | P22: 0.099393581 | Q22: 0.022554094 | R22: 0.057332244 | S22: 0.011716397 | T22: 0.71580886 | U22: 2.0498882 | V22: 0.0046142132 | W22: 0.1832689 | X22: 0.8444376 | Y22: 0.1939804 | Z22: 0.78767291 | AA22: 0.0076007927 | AB22: 0.040631784 | AC22: 0.23894167 | AD22: 1.24061 | AE22: 0.016262512 | AF22: 0.11286334 | AG22: 0.086910647 | AH22: 0.19338087 | AI22: 0.10977095 | AJ22: 0.062916414 | AK22: 0.23658876 | AL22: 7.482564 | AM22: 0.022011503 | AN22: 0 | AO22: 0.078481249 | AP22: 0.012949662 | AQ22: 2.6064163 | AR22: 19.937445 | AT22: 10.202423 | AV22: 19.937445 | AW22: =AV22-AR22 -> 0 | AY22: 9.1232064 | AZ22: =AY22/$AR22 -> 0.45759155 | BB22: c15 | BC22: Transport equipment | BD22: =$AY22*BQ22/$BZ22 -> 0.32362725 | BE22: =$AY22*BR22/$BZ22 -> 1.3060671 | BF22: =$AY22*BS22/$BZ22 -> 0.39297595 | BG22: =$AY22*BT22/$BZ22 -> 0.077054108 | BH22: =$AY22*BU22/$BZ22 -> 0.96702906 | BI22: =$AY22*BV22/$BZ22 -> 0.15410822 | BJ22: =$AY22*BW22/$BZ22 -> 2.7739479 | BK22: =$AY22*BX22/$BZ22 -> 2.8317385 | BL22: =$AY22*BY22/$BZ22 -> 0.29665832 | BM22: =SUM(BD22:BL22) -> 9.1232064 | BO22: c15 | BP22: Transport equipment | BQ22: 68.88613 | BR22: 278.00474 | BS22: 83.647443 | BT22: 16.401459 | BU22: 205.83832 | BV22: 32.802919 | BW22: 590.45254 | BX22: 602.75363 | BY22: 63.145619 | BZ22: 1941.9328 | CB22: c15 | CC22: Transport equipment | CD22: =BQ22/$AR22 -> 3.4551132 | CE22: =BR22/$AR22 -> 13.94385 | CF22: =BS22/$AR22 -> 4.1954946 | CG22: =BT22/$AR22 -> 0.822646 | CH22: =BU22/$AR22 -> 10.324207 | CI22: =BV22/$AR22 -> 1.645292 | CJ22: =BW22/$AR22 -> 29.615256 | CK22: =BX22/$AR22 -> 30.23224 | ... CM22: =BZ22/$AR22 -> 97.401286 | CO22: 15 | CP22: Transport Equipment | CQ22: 15.437027 | CR22: 21.672981 | CS22: 0.019811355 | CT22: 0 | CU22: 0.27480272 | CW22: 15 | CX22: Transport Equipment | CY22: =CQ22/$AR22 -> 0.77427307 | CZ22: =CR22/$AR22 -> 1.0870491 | DA22: =CS22/$AR22 -> 0.0009936757 | DB22: =CT22/$AR22 -> 0 | DC22: =CU22/$AR22 -> 0.013783247
A23: 36t37 | B23: Manufacturing, nec; recycling | C23: c16 | D23: 0.0017112077 | E23: 0.0080712653 | F23: 0.30706453 | G23: 3.0423322 | H23: 0.34615032 | I23: 0 | J23: 0.040262542 | K23: 0 | L23: 0 | M23: 0.05850331 | N23: 0.21302983 | O23: 0.10325335 | P23: 0.021236006 | Q23: 0.004818811 | R23: 0.012249361 | S23: 0.70692028 | T23: 0.036661567 | U23: 2.8368506 | V23: 0.0086505854 | W23: 0.25665942 | X23: 0.42610576 | Y23: 0.42437033 | Z23: 0.31384598 | AA23: 0.0030285138 | AB23: 0.016189616 | AC23: 0.095205614 | AD23: 0.30738921 | AE23: 0.013310401 | AF23: 0.097376394 | AG23: 0.07498489 | AH23: 0.054185194 | AI23: 0.24338495 | AJ23: 0.023079637 | AK23: 1.5009901 | AL23: 10.177277 | AM23: 0.040736869 | AN23: 0 | AO23: 0.84144122 | AP23: 3.6331984 | AQ23: 1.8568745 | AR23: 28.1474 | AT23: 16.549528 | AV23: 28.1474 | AW23: =AV23-AR23 -> 0 | AY23: 10.264209 | AZ23: =AY23/$AR23 -> 0.36465921 | BB23: c16 | BC23: Manufacturing, nec; recycling | BD23: =$AY23*BQ23/$BZ23 -> 0.364102 | BE23: =$AY23*BR23/$BZ23 -> 1.4694116 | BF23: =$AY23*BS23/$BZ23 -> 0.44212385 | BG23: =$AY23*BT23/$BZ23 -> 0.086690951 | BH23: =$AY23*BU23/$BZ23 -> 1.0879714 | BI23: =$AY23*BV23/$BZ23 -> 0.1733819 | BJ23: =$AY23*BW23/$BZ23 -> 3.1208742 | BK23: =$AY23*BX23/$BZ23 -> 3.1858925 | BL23: =$AY23*BY23/$BZ23 -> 0.33376016 | BM23: =SUM(BD23:BL23) -> 10.264209 | BO23: c16 | BP23: Manufacturing, nec; recycling | BQ23: 77.501437 | BR23: 312.77366 | BS23: 94.108888 | BT23: 18.452723 | BU23: 231.58168 | BV23: 36.905446 | BW23: 664.29803 | BX23: 678.13757 | BY23: 71.042984 | BZ23: 2184.8024 | CB23: c16 | CC23: Manufacturing, nec; recycling | CD23: =BQ23/$AR23 -> 2.7534137 | CE23: =BR23/$AR23 -> 11.111991 | CF23: =BS23/$AR23 -> 3.343431 | CG23: =BT23/$AR23 -> 0.6555747 | CH23: =BU23/$AR23 -> 8.2274625 | CI23: =BV23/$AR23 -> 1.3111494 | CJ23: =BW23/$AR23 -> 23.600689 | CK23: =BX23/$AR23 -> 24.09237 | ... CM23: =BZ23/$AR23 -> 77.620045 | CO23: 16 | CP23: Manufacturing, nec; Recycling | CQ23: 2873.8377 | CR23: 31.96825 | CS23: 0.070442352 | CT23: 0 | CU23: 0.97710381 | CW23: 16 | CX23: Manufacturing, nec; Recycling | CY23: =CQ23/$AR23 -> 102.09958 | CZ23: =CR23/$AR23 -> 1.1357443 | DA23: =CS23/$AR23 -> 0.0025026238 | DB23: =CT23/$AR23 -> 0 | DC23: =CU23/$AR23 -> 0.034713821
A24: E | B24: Electricity, gas, and water supply | C24: c17 | D24: 0.45508647 | E24: 1.7147421 | F24: 7.3802835 | G24: 1.62566 | H24: 0.1715887 | I24: 0.10168416 | J24: 2.1221881 | K24: 2.3717278 | L24: 1.0953978 | M24: 1.4892664 | N24: 5.4229098 | O24: 9.3004469 | P24: 2.3998646 | Q24: 0.54457009 | R24: 1.3842908 | S24: 0.33339062 | T24: 10.25499 | U24: 14.52273 | V24: 0.10227816 | W24: 2.6427501 | X24: 5.4360366 | Y24: 7.0283699 | Z24: 1.4427623 | AA24: 0.013922196 | AB24: 0.074424299 | AC24: 0.43766393 | AD24: 2.2009126 | AE24: 0.86124928 | AF24: 2.2418582 | AG24: 1.7263474 | AH24: 7.2926161 | AI24: 7.5921529 | AJ24: 6.9421565 | AK24: 2.8603908 | AL24: 55.165759 | AM24: 0.016126186 | AN24: 0.70802153 | AO24: 67.713824 | AP24: -2.9758683 | AQ24: 126.35687 | AR24: 358.57144 | AT24: 246.98473 | AV24: 358.57144 | AW24: =AV24-AR24 -> 0 | AY24: 158.31998 | AZ24: =AY24/$AR24 -> 0.44152981 | BB24: c17 | BC24: Electricity, gas, and water supply | BD24: =$AY24*BQ24/$BZ24 -> 8.9769061 | BE24: =$AY24*BR24/$BZ24 -> 21.218142 | BF24: =$AY24*BS24/$BZ24 -> 9.3849473 | BG24: =$AY24*BT24/$BZ24 -> 5.3045354 | BH24: =$AY24*BU24/$BZ24 -> 35.907625 | BI24: =$AY24*BV24/$BZ24 -> 7.3447414 | BJ24: =$AY24*BW24/$BZ24 -> 24.890512 | BK24: =$AY24*BX24/$BZ24 -> 37.947831 | BL24: =$AY24*BY24/$BZ24 -> 7.3447414 | BM24: =SUM(BD24:BL24) -> 158.31998 | BO24: c17 | BP24: Electricity, gas, and water supply | BQ24: 2200 | BR24: 5200 | BS24: 2300 | BT24: 1300 | BU24: 8800 | BV24: 1800 | BW24: 6100 | BX24: 9300 | BY24: 1800 | BZ24: 38800 | CB24: c17 | CC24: Electricity, gas, and water supply | CD24: =BQ24/$AR24 -> 6.135458 | CE24: =BR24/$AR24 -> 14.501992 | CF24: =BS24/$AR24 -> 6.4143424 | CG24: =BT24/$AR24 -> 3.6254979 | CH24: =BU24/$AR24 -> 24.541832 | CI24: =BV24/$AR24 -> 5.0199202 | CJ24: =BW24/$AR24 -> 17.011952 | CK24: =BX24/$AR24 -> 25.936254 | ... CM24: =BZ24/$AR24 -> 108.20717 | CO24: 17 | CP24: Electricity, Gas, and Water Supply | CQ24: 252288.19 | CR24: 2977.6219 | CS24: 0.68518742 | CT24: 0 | CU24: 9.5042146 | CW24: 17 | CX24: Electricity, Gas, and Water Supply | CY24: =CQ24/$AR24 -> 703.59254 | CZ24: =CR24/$AR24 -> 8.3041247 | DA24: =CS24/$AR24 -> 0.0019108812 | DB24: =CT24/$AR24 -> 0 | DC24: =CU24/$AR24 -> 0.026505777
A25: F | B25: Construction | C25: c18 | D25: 0.0041450161 | E25: 0.028444388 | F25: 2.2826376 | G25: 0.74450922 | H25: 0.078583079 | I25: 0 | J25: 0.47581337 | K25: 0.08345063 | L25: 0.038542213 | M25: 0.75559166 | N25: 2.7513582 | O25: 2.8826521 | P25: 0.023293338 | Q25: 0.0052856545 | R25: 0.013436072 | S25: 0.016478161 | T25: 0.67159142 | U25: 300.02434 | V25: 0 | W25: 5.8537826 | X25: 31.098644 | Y25: 2.7707979 | Z25: 1.5173743 | AA25: 0.014642179 | AB25: 0.078273129 | AC25: 0.46029759 | AD25: 0.38491158 | AE25: 0.2124143 | AF25: 9.6081916 | AG25: 7.3988075 | AH25: 0 | AI25: 15.543909 | AJ25: 0.8066327 | AK25: 5.1031497 | AL25: 0.16736333 | AM25: 0 | AN25: 0.30988797 | AO25: 1425.3024 | AP25: 34.846036 | AQ25: 120.02962 | AR25: 1972.3873 | AT25: 1580.6553 | AV25: 1972.3873 | AW25: =AV25-AR25 -> 0 | AY25: 607.03135 | AZ25: =AY25/$AR25 -> 0.30776479 | BB25: c18 | BC25: Construction | BD25: =$AY25*BQ25/$BZ25 -> 66.972942 | BE25: =$AY25*BR25/$BZ25 -> 95.947052 | BF25: =$AY25*BS25/$BZ25 -> 41.561223 | BG25: =$AY25*BT25/$BZ25 -> 8.78723 | BH25: =$AY25*BU25/$BZ25 -> 153.89527 | BI25: =$AY25*BV25/$BZ25 -> 17.811953 | BJ25: =$AY25*BW25/$BZ25 -> 83.834924 | BK25: =$AY25*BX25/$BZ25 -> 86.447344 | BL25: =$AY25*BY25/$BZ25 -> 51.773409 | BM25: =SUM(BD25:BL25) -> 607.03135 | BO25: c18 | BP25: Construction | BQ25: 28200 | BR25: 40400 | BS25: 17500 | BT25: 3700 | BU25: 64800 | BV25: 7500 | BW25: 35300 | BX25: 36400 | BY25: 21800 | BZ25: 255600 | CB25: c18 | CC25: Construction | CD25: =BQ25/$AR25 -> 14.297395 | CE25: =BR25/$AR25 -> 20.482793 | CF25: =BS25/$AR25 -> 8.8724969 | CG25: =BT25/$AR25 -> 1.8758993 | CH25: =BU25/$AR25 -> 32.853588 | CI25: =BV25/$AR25 -> 3.8024987 | CJ25: =BW25/$AR25 -> 17.897094 | CK25: =BX25/$AR25 -> 18.454793 | ... CM25: =BZ25/$AR25 -> 129.58915 | CO25: 18 | CP25: Construction | CQ25: 1428.788 | CR25: 12556.871 | CS25: 2.0860453 | CT25: 0 | CU25: 28.935473 | CW25: 18 | CX25: Construction | CY25: =CQ25/$AR25 -> 0.72439523 | CZ25: =CR25/$AR25 -> 6.3663314 | DA25: =CS25/$AR25 -> 0.0010576246 | DB25: =CT25/$AR25 -> 0 | DC25: =CU25/$AR25 -> 0.01467028
A26: 50 | B26: Sale, maintenance, and repair of motor vehicles and motorcycles; retail sale of fuel | C26: c19 | D26: 7.7280942 | E26: 0.98303583 | F26: 0.21724663 | G26: 0.23800081 | H26: 0.025121027 | I26: 0.013233396 | J26: 0.20585859 | K26: 0.30414702 | L26: 0.14047227 | M26: 0.20276132 | N26: 0.7383208 | O26: 0.27910548 | P26: 0.090935024 | Q26: 0.020634704 | R26: 0.052453175 | S26: 0.020751358 | T26: 0.75573332 | U26: 0.1908958 | V26: 0.077844655 | W26: 0.88899529 | X26: 0.49821708 | Y26: 0.21821058 | Z26: 0.94364763 | AA26: 0.0091058991 | AB26: 0.048677675 | AC26: 0.28625681 | AD26: 1.7459804 | AE26: 0.068785356 | AF26: 0.29178625 | AG26: 0.2246906 | AH26: 1.5598073 | AI26: 0.17896967 | AJ26: 0.45258977 | AK26: 0.66976481 | AL26: 4.3147224 | AM26: 0 | AN26: 0 | AO26: 0.80986466 | AP26: 0 | AQ26: 0.6311207 | AR26: 26.125838 | AT26: 5.7557078 | AV26: 26.125838 | AW26: =AV26-AR26 -> 0 | AY26: 19.93217 | AZ26: =AY26/$AR26 -> 0.76292939 | BB26: c19 | BC26: Sale of motor vehicles and fuel | BD26: =$AY26*BQ26/$BZ26 -> 1.3600654 | BE26: =$AY26*BR26/$BZ26 -> 2.4058732 | BF26: =$AY26*BS26/$BZ26 -> 0.98913844 | BG26: =$AY26*BT26/$BZ26 -> 0.22667756 | BH26: =$AY26*BU26/$BZ26 -> 5.3320744 | BI26: =$AY26*BV26/$BZ26 -> 0.57699743 | BJ26: =$AY26*BW26/$BZ26 -> 2.4831496 | BK26: =$AY26*BX26/$BZ26 -> 5.254798 | BL26: =$AY26*BY26/$BZ26 -> 1.303396 | BM26: =SUM(BD26:BL26) -> 19.93217 | BO26: c19 | BP26: Sale, maintenance, and repair of motor vehicles and motorcycles; retail sale of fuel | BQ26: 399.17228 | BR26: 706.11156 | BS26: 290.30711 | BT26: 66.528713 | BU26: 1564.9368 | BV26: 169.34581 | BW26: 728.79181 | BX26: 1542.2565 | BY26: 382.5401 | BZ26: 5849.9907 | CB26: c19 | CC26: Sale, maintenance, and repair of motor vehicles and motorcycles; retail sale of fuel | CD26: =BQ26/$AR26 -> 15.278831 | CE26: =BR26/$AR26 -> 27.027327 | CF26: =BS26/$AR26 -> 11.111877 | CG26: =BT26/$AR26 -> 2.5464719 | CH26: =BU26/$AR26 -> 59.899964 | CI26: =BV26/$AR26 -> 6.4819284 | CJ26: =BW26/$AR26 -> 27.895442 | CK26: =BX26/$AR26 -> 59.031848 | ... CM26: =BZ26/$AR26 -> 223.9159 | CO26: 19 | CP26: Sale, Maintenance, and Repair of Motor Vehicles and Motorcycles; Retail Sale of Fuel | CQ26: 53.232881 | CR26: 11.498623 | CS26: 0.10636737 | CT26: 0 | CU26: 1.4754186 | CW26: 19 | CX26: Sale, Maintenance, and Repair of Motor Vehicles and Motorcycles; Retail Sale of Fuel | CY26: =CQ26/$AR26 -> 2.0375569 | CZ26: =CR26/$AR26 -> 0.44012456 | DA26: =CS26/$AR26 -> 0.0040713475 | DB26: =CT26/$AR26 -> 0 | DC26: =CU26/$AR26 -> 0.056473542
A27: 51 | B27: Wholesale trade and commission trade, except of motor vehicles and motorcycles | C27: c20 | D27: 84.772409 | E27: 0.67405622 | F27: 19.588989 | G27: 1.8929788 | H27: 0.19980425 | I27: 0.010058311 | J27: 0.18018352 | K27: 0.91003486 | L27: 0.42030548 | M27: 0.42155756 | N27: 1.53503 | O27: 14.774361 | P27: 0.31626574 | Q27: 0.071766077 | R27: 0.18242853 | S27: 0.14813335 | T27: 1.7050147 | U27: 12.226744 | V27: 0.028480711 | W27: 1.3047515 | X27: 13.789032 | Y27: 6.143356 | Z27: 1.6473018 | AA27: 0.015895938 | AB27: 0.084975388 | AC27: 0.49971129 | AD27: 1.818355 | AE27: 0.11641211 | AF27: 1.2462706 | AG27: 0.95969318 | AH27: 6.1222822 | AI27: 3.1607376 | AJ27: 2.356737 | AK27: 0.90121179 | AL27: 143.48005 | AM27: 0.20578427 | AN27: 0.62410365 | AO27: 8.2949234 | AP27: 3.5399523 | AQ27: 35.4427 | AR27: 371.81284 | AT27: 191.58752 | AV27: 371.81284 | AW27: =AV27-AR27 -> 0 | AY27: 247.09928 | AZ27: =AY27/$AR27 -> 0.66457972 | BB27: c20 | BC27: Wholesale trade | BD27: =$AY27*BQ27/$BZ27 -> 16.860742 | BE27: =$AY27*BR27/$BZ27 -> 29.82563 | BF27: =$AY27*BS27/$BZ27 -> 12.262357 | BG27: =$AY27*BT27/$BZ27 -> 2.8101236 | BH27: =$AY27*BU27/$BZ27 -> 66.101771 | BI27: =$AY27*BV27/$BZ27 -> 7.1530419 | BJ27: =$AY27*BW27/$BZ27 -> 30.783627 | BK27: =$AY27*BX27/$BZ27 -> 65.143774 | BL27: =$AY27*BY27/$BZ27 -> 16.158211 | BM27: =SUM(BD27:BL27) -> 247.09928 | BO27: c20 | BP27: Wholesale trade and commission trade, except of motor vehicles and motorcycles | BQ27: 4948.542 | BR27: 8753.6709 | BS27: 3598.9396 | BT27: 824.757 | BU27: 19400.534 | BV27: 2099.3815 | BW27: 9034.838 | BX27: 19119.367 | BY27: 4742.3527 | BZ27: 72522.383 | CB27: c20 | CC27: Wholesale trade and commission trade, except of motor vehicles and motorcycles | CD27: =BQ27/$AR27 -> 13.309228 | CE27: =BR27/$AR27 -> 23.543218 | CF27: =BS27/$AR27 -> 9.6794387 | CG27: =BT27/$AR27 -> 2.2182047 | CH27: =BU27/$AR27 -> 52.178224 | CI27: =BV27/$AR27 -> 5.6463393 | CJ27: =BW27/$AR27 -> 24.299424 | CK27: =BX27/$AR27 -> 51.422018 | ... CM27: =BZ27/$AR27 -> 195.05077 | CO27: 20 | CP27: Wholesale Trade and Commission Trade, Except of Motor Vehicles and Motorcycles | CQ27: 785.16851 | CR27: 144.6064 | CS27: 1.6601254 | CT27: 0 | CU27: 23.027551 | CW27: 20 | CX27: Wholesale Trade and Commission Trade, Except of Motor Vehicles and Motorcycles | CY27: =CQ27/$AR27 -> 2.1117305 | CZ27: =CR27/$AR27 -> 0.38892256 | DA27: =CS27/$AR27 -> 0.004464949 | DB27: =CT27/$AR27 -> 0 | DC27: =CU27/$AR27 -> 0.061933177
A28: 52 | B28: Retail trade, except of motor vehicles and motorcycles; repair of household goods | C28: c21 | D28: 323.68263 | E28: 4.8382916 | F28: 77.412788 | G28: 10.495491 | H28: 1.1078009 | I28: 0.082437332 | J28: 1.1771412 | K28: 5.3726162 | L28: 2.4813775 | M28: 2.1643943 | N28: 7.8812729 | O28: 28.722708 | P28: 1.2203792 | Q28: 0.2769248 | R28: 0.70393961 | S28: 0.83534631 | T28: 10.367665 | U28: 81.946425 | V28: 0.49834794 | W28: 8.8712092 | X28: 72.984659 | Y28: 23.995627 | Z28: 19.458499 | AA28: 0.22241284 | AB28: 1.1889589 | AC28: 6.9918622 | AD28: 13.509339 | AE28: 0.54153818 | AF28: 6.4384765 | AG28: 4.957962 | AH28: 26.145268 | AI28: 12.944607 | AJ28: 10.658818 | AK28: 4.0803819 | AL28: 710.27983 | AM28: 0.59280509 | AN28: 0.18340836 | AO28: 24.220663 | AP28: 2.9250788 | AQ28: 174.3868 | AR28: 1686.8462 | AT28: 912.58859 | AV28: 1686.8462 | AW28: =AV28-AR28 -> 0 | AY28: 1051.2196 | AZ28: =AY28/$AR28 -> 0.62318642 | BB28: c21 | BC28: Retail trade | BD28: =$AY28*BQ28/$BZ28 -> 71.729642 | BE28: =$AY28*BR28/$BZ28 -> 126.88539 | BF28: =$AY28*BS28/$BZ28 -> 52.167013 | BG28: =$AY28*BT28/$BZ28 -> 11.95494 | BH28: =$AY28*BU28/$BZ28 -> 281.2128 | BI28: =$AY28*BV28/$BZ28 -> 30.430757 | BJ28: =$AY28*BW28/$BZ28 -> 130.96094 | BK28: =$AY28*BX28/$BZ28 -> 277.13725 | BL28: =$AY28*BY28/$BZ28 -> 68.740907 | BM28: =SUM(BD28:BL28) -> 1051.2196 | BO28: c21 | BP28: Retail trade, except of motor vehicles and motorcycles; repair of household goods | BQ28: 21052.286 | BR28: 37240.218 | BS28: 15310.753 | BT28: 3508.7143 | BU28: 82534.529 | BV28: 8931.2727 | BW28: 38436.37 | BX28: 81338.377 | BY28: 20175.107 | BZ28: 308527.63 | CB28: c21 | CC28: Retail trade, except of motor vehicles and motorcycles; repair of household goods | CD28: =BQ28/$AR28 -> 12.480264 | CE28: =BR28/$AR28 -> 22.076831 | CF28: =BS28/$AR28 -> 9.0765556 | CG28: =BT28/$AR28 -> 2.080044 | CH28: =BU28/$AR28 -> 48.928308 | CI28: =BV28/$AR28 -> 5.2946574 | CJ28: =BW28/$AR28 -> 22.785937 | CK28: =BX28/$AR28 -> 48.219202 | ... CM28: =BZ28/$AR28 -> 182.90205 | CO28: 21 | CP28: Retail Trade, Except of Motor Vehicles and Motorcycles; Repair of Household Goods | CQ28: 863.19586 | CR28: 621.45712 | CS28: 1.6753642 | CT28: 0 | CU28: 23.238928 | CW28: 21 | CX28: Retail Trade, Except of Motor Vehicles and Motorcycles; Repair of Household Goods | CY28: =CQ28/$AR28 -> 0.51172174 | CZ28: =CR28/$AR28 -> 0.36841363 | DA28: =CS28/$AR28 -> 0.00099319322 | DB28: =CT28/$AR28 -> 0 | DC28: =CU28/$AR28 -> 0.013776554
A29: H | B29: Hotels and restaurants | C29: c22 | D29: 22.222117 | E29: 0.48786389 | F29: 15.116265 | G29: 0.82774264 | H29: 0.087368382 | I29: 0.0020309594 | J29: 0.11253247 | K29: 0.45547766 | L29: 0.2103653 | M29: 0.24209787 | N29: 0.88155811 | O29: 0.53741241 | P29: 0.0083381636 | Q29: 0.0018920712 | R29: 0.0048096227 | S29: 0.014047743 | T29: 0.48924581 | U29: 7.8576863 | V29: 0.048738762 | W29: 1.209883 | X29: 14.817012 | Y29: 6.8477139 | Z29: 0.74192198 | AA29: 0.0071593108 | AB29: 0.038271741 | AC29: 0.22506306 | AD29: 1.3703293 | AE29: 1.0082035 | AF29: 1.4229148 | AG29: 1.0957185 | AH29: 8.8702898 | AI29: 3.088634 | AJ29: 2.363976 | AK29: 0.95145625 | AL29: 206.1096 | AM29: 0 | AN29: 0 | AO29: 5.3930385 | AP29: -0.031138913 | AQ29: 3.9678517 | AR29: 309.10548 | AT29: 215.43935 | AV29: 309.10548 | AW29: =AV29-AR29 -> 0 | AY29: 126.21938 | AZ29: =AY29/$AR29 -> 0.40833756 | BB29: c22 | BC29: Hotels and restaurants | BD29: =$AY29*BQ29/$BZ29 -> 11.127378 | BE29: =$AY29*BR29/$BZ29 -> 11.891022 | BF29: =$AY29*BS29/$BZ29 -> 13.200125 | BG29: =$AY29*BT29/$BZ29 -> 0.32727584 | BH29: =$AY29*BU29/$BZ29 -> 39.491284 | BI29: =$AY29*BV29/$BZ29 -> 2.6182067 | BJ29: =$AY29*BW29/$BZ29 -> 17.236527 | BK29: =$AY29*BX29/$BZ29 -> 23.127492 | BL29: =$AY29*BY29/$BZ29 -> 7.2000684 | BM29: =SUM(BD29:BL29) -> 126.21938 | BO29: c22 | BP29: Hotels and restaurants | BQ29: 10200 | BR29: 10900 | BS29: 12100 | BT29: 300 | BU29: 36200 | BV29: 2400 | BW29: 15800 | BX29: 21200 | BY29: 6600 | BZ29: 115700 | CB29: c22 | CC29: Hotels and restaurants | CD29: =BQ29/$AR29 -> 32.998444 | CE29: =BR29/$AR29 -> 35.263043 | CF29: =BS29/$AR29 -> 39.145213 | CG29: =BT29/$AR29 -> 0.97054247 | CH29: =BU29/$AR29 -> 117.11212 | CI29: =BV29/$AR29 -> 7.7643397 | CJ29: =BW29/$AR29 -> 51.115237 | CK29: =BX29/$AR29 -> 68.585001 | ... CM29: =BZ29/$AR29 -> 374.30588 | CO29: 22 | CP29: Hotels and Restaurants | CQ29: 450.56904 | CR29: 146.66766 | CS29: 0.92919785 | CT29: 0 | CU29: 12.888876 | CW29: 22 | CX29: Hotels and Restaurants | CY29: =CQ29/$AR29 -> 1.4576546 | CZ29: =CR29/$AR29 -> 0.47449065 | DA29: =CS29/$AR29 -> 0.0030060866 | DB29: =CT29/$AR29 -> 0 | DC29: =CU29/$AR29 -> 0.041697339
A30: 60 | B30: Inland transport | C30: c23 | D30: 23.570966 | E30: 3.0988574 | F30: 8.8379126 | G30: 3.5915735 | H30: 0.37909121 | I30: 0.040534958 | J30: 0.57839075 | K30: 1.4363298 | L30: 0.66337819 | M30: 1.7403438 | N30: 6.3371654 | O30: 16.117289 | P30: 0.11057016 | Q30: 0.02509025 | R30: 0.063779122 | S30: 0.54768566 | T30: 6.7272577 | U30: 29.511003 | V30: 0.1966127 | W30: 4.1956679 | X30: 12.314637 | Y30: 2.5216567 | Z30: 9.358252 | AA30: 0.090304152 | AB30: 0.48274159 | AC30: 2.8388387 | AD30: 5.3896388 | AE30: 0.21624592 | AF30: 1.3177703 | AG30: 1.0147517 | AH30: 3.9430937 | AI30: 2.0238908 | AJ30: 2.8138665 | AK30: 2.2968369 | AL30: 112.59844 | AM30: 0.061767031 | AN30: 0.90253793 | AO30: 48.203178 | AP30: 0.10132249 | AQ30: 178.7272 | AR30: 494.98646 | AT30: 340.59444 | AV30: 494.98646 | AW30: =AV30-AR30 -> 0 | AY30: 208.29383 | AZ30: =AY30/$AR30 -> 0.42080713 | BB30: c23 | BC30: Inland transport | BD30: =$AY30*BQ30/$BZ30 -> 17.120041 | BE30: =$AY30*BR30/$BZ30 -> 27.765195 | BF30: =$AY30*BS30/$BZ30 -> 9.5477152 | BG30: =$AY30*BT30/$BZ30 -> 3.0728279 | BH30: =$AY30*BU30/$BZ30 -> 47.628832 | BI30: =$AY30*BV30/$BZ30 -> 5.5969365 | BJ30: =$AY30*BW30/$BZ30 -> 42.361127 | BK30: =$AY30*BX30/$BZ30 -> 44.99498 | BL30: =$AY30*BY30/$BZ30 -> 10.206178 | BM30: =SUM(BD30:BL30) -> 208.29383 | BO30: c23 | BP30: Inland transport | BQ30: 11390.429 | BR30: 18472.94 | BS30: 6352.3548 | BT30: 2044.436 | BU30: 31688.759 | BV30: 3723.7942 | BW30: 28184.011 | BX30: 29936.385 | BY30: 6790.4483 | BZ30: 138583.56 | CB30: c23 | CC30: Inland transport | CD30: =BQ30/$AR30 -> 23.011598 | CE30: =BR30/$AR30 -> 37.320091 | CF30: =BS30/$AR30 -> 12.833391 | CG30: =BT30/$AR30 -> 4.1302868 | CH30: =BU30/$AR30 -> 64.019445 | CI30: =BV30/$AR30 -> 7.5230223 | CJ30: =BW30/$AR30 -> 56.938953 | CK30: =BX30/$AR30 -> 60.479199 | ... CM30: =BZ30/$AR30 -> 279.97444 | CO30: 23 | CP30: Inland Transport | CQ30: 260.49153 | CR30: 46.311048 | CS30: 0.30924277 | CT30: 0 | CU30: 4.2894974 | CW30: 23 | CX30: Inland Transport | CY30: =CQ30/$AR30 -> 0.52625991 | CZ30: =CR30/$AR30 -> 0.093560232 | DA30: =CS30/$AR30 -> 0.00062474996 | DB30: =CT30/$AR30 -> 0 | DC30: =CU30/$AR30 -> 0.0086658883
A31: 61 | B31: Water transport | C31: c24 | D31: 0.20492814 | E31: 0.026941751 | F31: 0.076837625 | G31: 0.03122547 | H31: 0.0032958539 | I31: 0.00035241465 | J31: 0.0050285824 | K31: 0.012487583 | L31: 0.005767471 | M31: 0.015130709 | N31: 0.055095899 | O31: 0.14012519 | P31: 0.00096130714 | Q31: 0.00021813694 | R31: 0.00055450155 | S31: 0.0047616295 | T31: 0.058487397 | U31: 0.25657138 | V31: 0.0017093689 | W31: 0.044348842 | X31: 0.10706459 | Y31: 0.021923515 | Z31: 0.081361504 | AA31: 0.0007851126 | AB31: 0.0041969998 | AC31: 0.024681125 | AD31: 0.046858016 | AE31: 0.0018800619 | AF31: 0.011456816 | AG31: 0.0088223444 | AH31: 0.034281619 | AI31: 0.017595893 | AJ31: 0.024464014 | AK31: 0.019968911 | AL31: 0.97894847 | AM31: 0.00053701226 | AN31: 0.0078468063 | AO31: 0.41908599 | AP31: 0.0008809136 | AQ31: 1.8674728 | AR31: 4.6249418 | AT31: 3.274772 | AV31: 4.6249418 | AW31: =AV31-AR31 -> 0 | AY31: 1.8757086 | AZ31: =AY31/$AR31 -> 0.40556372 | BB31: c24 | BC31: Water transport | BD31: =$AY31*BQ31/$BZ31 -> 0.15416783 | BE31: =$AY31*BR31/$BZ31 -> 0.25002859 | BF31: =$AY31*BS31/$BZ31 -> 0.085978212 | BG31: =$AY31*BT31/$BZ31 -> 0.027671149 | BH31: =$AY31*BU31/$BZ31 -> 0.42890281 | BI31: =$AY31*BV31/$BZ31 -> 0.050401021 | BJ31: =$AY31*BW31/$BZ31 -> 0.38146655 | BK31: =$AY31*BX31/$BZ31 -> 0.40518468 | BL31: =$AY31*BY31/$BZ31 -> 0.091907744 | BM31: =SUM(BD31:BL31) -> 1.8757086 | BO31: c24 | BP31: Water transport | BQ31: 102.57205 | BR31: 166.35083 | BS31: 57.203645 | BT31: 18.410368 | BU31: 285.36071 | BV31: 33.533171 | BW31: 253.80008 | BX31: 269.5804 | BY31: 61.148724 | BZ31: 1247.96 | CB31: c24 | CC31: Water transport | CD31: =BQ31/$AR31 -> 22.17802 | CE31: =BR31/$AR31 -> 35.9682 | CF31: =BS31/$AR31 -> 12.368511 | CG31: =BT31/$AR31 -> 3.9806703 | CH31: =BU31/$AR31 -> 61.70039 | CI31: =BV31/$AR31 -> 7.2505066 | CJ31: =BW31/$AR31 -> 54.876384 | CK31: =BX31/$AR31 -> 58.288387 | ... CM31: =BZ31/$AR31 -> 269.83258 | CO31: 24 | CP31: Water Transport | CQ31: 2685.5474 | CR31: 0.44518108 | CS31: 0.018702939 | CT31: 0 | CU31: 0.25942792 | CW31: 24 | CX31: Water Transport | CY31: =CQ31/$AR31 -> 580.6662 | CZ31: =CR31/$AR31 -> 0.096256579 | DA31: =CS31/$AR31 -> 0.0040439296 | DB31: =CT31/$AR31 -> 0 | DC31: =CU31/$AR31 -> 0.056093229
A32: 62 | B32: Air transport | C32: c25 | D32: 1.2204839 | E32: 0.16045611 | F32: 0.45761933 | G32: 0.18596851 | H32: 0.019629009 | I32: 0.0020988645 | J32: 0.029948564 | K32: 0.074371891 | L32: 0.034349139 | M32: 0.090113472 | N32: 0.32813285 | O32: 0.83453902 | P32: 0.0057252255 | Q32: 0.0012991511 | R32: 0.0033024268 | S32: 0.028358682 | T32: 0.34833148 | U32: 1.5280538 | V32: 0.010180432 | W32: 0.26412695 | X32: 0.63764108 | Y32: 0.13056916 | Z32: 0.48456205 | AA32: 0.0046758695 | AB32: 0.024995935 | AC32: 0.14699257 | AD32: 0.27907076 | AE32: 0.011197023 | AF32: 0.068232985 | AG32: 0.052542949 | AH32: 0.20416992 | AI32: 0.10479528 | AJ32: 0.14569953 | AK32: 0.11892819 | AL32: 5.8302914 | AM32: 0.0031982664 | AN32: 0.046732968 | AO32: 2.4959367 | AP32: 0.0052464284 | AQ32: 9.2689609 | AR32: 25.691529 | AT32: 17.650367 | AV32: 25.691529 | AW32: =AV32-AR32 -> 0 | AY32: 10.931601 | AZ32: =AY32/$AR32 -> 0.42549439 | BB32: c25 | BC32: Air transport | BD32: =$AY32*BQ32/$BZ32 -> 0.89848779 | BE32: =$AY32*BR32/$BZ32 -> 1.4571629 | BF32: =$AY32*BS32/$BZ32 -> 0.50107973 | BG32: =$AY32*BT32/$BZ32 -> 0.16126704 | BH32: =$AY32*BU32/$BZ32 -> 2.4996391 | BI32: =$AY32*BV32/$BZ32 -> 0.29373639 | BJ32: =$AY32*BW32/$BZ32 -> 2.2231813 | BK32: =$AY32*BX32/$BZ32 -> 2.3614102 | BL32: =$AY32*BY32/$BZ32 -> 0.53563695 | BM32: =SUM(BD32:BL32) -> 10.931601 | BO32: c25 | BP32: Air transport | BQ32: 597.78839 | BR32: 969.49014 | BS32: 333.38198 | BT32: 107.29535 | BU32: 1663.0779 | BV32: 195.43082 | BW32: 1479.1431 | BX32: 1571.1105 | BY32: 356.37385 | BZ32: 7273.092 | CB32: c25 | CC32: Air transport | CD32: =BQ32/$AR32 -> 23.267918 | CE32: =BR32/$AR32 -> 37.73579 | CF32: =BS32/$AR32 -> 12.976339 | CG32: =BT32/$AR32 -> 4.176293 | CH32: =BU32/$AR32 -> 64.732541 | CI32: =BV32/$AR32 -> 7.6068194 | CJ32: =BW32/$AR32 -> 57.573182 | CK32: =BX32/$AR32 -> 61.152861 | ... CM32: =BZ32/$AR32 -> 283.093 | CO32: 25 | CP32: Air Transport | CQ32: 2514.5134 | CR32: 2.4468433 | CS32: 0.093386397 | CT32: 0 | CU32: 1.29536 | CW32: 25 | CX32: Air Transport | CY32: =CQ32/$AR32 -> 97.873249 | CZ32: =CR32/$AR32 -> 0.095239304 | DA32: =CS32/$AR32 -> 0.0036349101 | DB32: =CT32/$AR32 -> 0 | DC32: =CU32/$AR32 -> 0.050419731
A33: 63 | B33: Other supporting and auxiliary transport activities; activities of travel agencies | C33: c26 | D33: 7.175256 | E33: 0.94332559 | F33: 2.6903559 | G33: 1.0933137 | H33: 0.11539945 | I33: 0.012339278 | J33: 0.17606838 | K33: 0.43723426 | L33: 0.20193947 | M33: 0.52977942 | N33: 1.9291015 | O33: 4.9062764 | P33: 0.033658748 | Q33: 0.0076377426 | R33: 0.019415052 | S33: 0.16672142 | T33: 2.0478498 | U33: 8.9834675 | V33: 0.059851024 | W33: 1.5528091 | X33: 3.7487084 | Y33: 0.76761948 | Z33: 2.8487528 | AA33: 0.027489557 | AB33: 0.14695174 | AC33: 0.86417311 | AD33: 1.6406642 | AE33: 0.065827589 | AF33: 0.40114347 | AG33: 0.30890135 | AH33: 1.2003202 | AI33: 0.61609417 | AJ33: 0.8565713 | AK33: 0.6991819 | AL33: 34.276433 | AM33: 0.01880269 | AN33: 0.27474432 | AO33: 14.673676 | AP33: 0.030843887 | AQ33: 54.422225 | AR33: 150.97092 | AT33: 103.69673 | AV33: 150.97092 | AW33: =AV33-AR33 -> 0 | AY33: 64.172019 | AZ33: =AY33/$AR33 -> 0.4250621 | BB33: c26 | BC33: Travel agencies | BD33: =$AY33*BQ33/$BZ33 -> 5.2744125 | BE33: =$AY33*BR33/$BZ33 -> 8.5540152 | BF33: =$AY33*BS33/$BZ33 -> 2.9414993 | BG33: =$AY33*BT33/$BZ33 -> 0.94668943 | BH33: =$AY33*BU33/$BZ33 -> 14.673686 | BI33: =$AY33*BV33/$BZ33 -> 1.7243272 | BJ33: =$AY33*BW33/$BZ33 -> 13.05079 | BK33: =$AY33*BX33/$BZ33 -> 13.862238 | BL33: =$AY33*BY33/$BZ33 -> 3.1443613 | BM33: =SUM(BD33:BL33) -> 64.172019 | BO33: c26 | BP33: Other supporting and auxiliary transport activities; activities of travel agencies | BQ33: 3509.2102 | BR33: 5691.2191 | BS33: 1957.0595 | BT33: 629.85824 | BU33: 9762.8028 | BV33: 1147.2418 | BW33: 8683.0458 | BX33: 9222.9243 | BY33: 2092.0292 | BZ33: 42695.391 | CB33: c26 | CC33: Other supporting and auxiliary transport activities; activities of travel agencies | CD33: =BQ33/$AR33 -> 23.244278 | CE33: =BR33/$AR33 -> 37.697452 | CF33: =BS33/$AR33 -> 12.963155 | CG33: =BT33/$AR33 -> 4.17205 | CH33: =BU33/$AR33 -> 64.666775 | CI33: =BV33/$AR33 -> 7.599091 | CJ33: =BW33/$AR33 -> 57.514689 | CK33: =BX33/$AR33 -> 61.090732 | ... CM33: =BZ33/$AR33 -> 282.80539 | CO33: 26 | CP33: Other Supporting and Auxiliary Transport Activities; Activities of Travel Agencies | CQ33: 217.0119 | CR33: 70.642919 | CS33: 0.41658453 | CT33: 0 | CU33: 5.7784318 | CW33: 26 | CX33: Other Supporting and Auxiliary Transport Activities; Activities of Travel Agencies | CY33: =CQ33/$AR33 -> 1.4374417 | CZ33: =CR33/$AR33 -> 0.467924 | DA33: =CS33/$AR33 -> 0.0027593692 | DB33: =CT33/$AR33 -> 0 | DC33: =CU33/$AR33 -> 0.03827513
A34: 64 | B34: Post and telecommunications | C34: c27 | D34: 11.25499 | E34: 1.7414565 | F34: 10.034153 | G34: 3.3061682 | H34: 0.34896664 | I34: 0.019591147 | J34: 0.38204776 | K34: 1.7684164 | L34: 0.81675452 | M34: 3.8620489 | N34: 11.396607 | O34: 7.3883244 | P34: 0.13066724 | Q34: 0.029650619 | R34: 0.075371527 | S34: 0.301764 | T34: 3.5421185 | U34: 33.436163 | V34: 0.10405208 | W34: 5.0383073 | X34: 11.661759 | Y34: 2.8383474 | Z34: 6.4817336 | AA34: 0.062546665 | AB34: 0.33435757 | AC34: 1.9662429 | AD34: 19.306123 | AE34: 0.52366397 | AF34: 8.0515591 | AG34: 6.2001195 | AH34: 17.250852 | AI34: 1.543059 | AJ34: 2.0503388 | AK34: 8.232956 | AL34: 189.77805 | AM34: 0.026734332 | AN34: 0.49054297 | AO34: 65.884809 | AP34: -0.29938746 | AQ34: 80.99204 | AR34: 518.35407 | AT34: 336.87279 | AV34: 518.35407 | AW34: =AV34-AR34 -> 0 | AY34: 265.07173 | AZ34: =AY34/$AR34 -> 0.51137194 | BB34: c27 | BC34: Post and telecommunications | BD34: =$AY34*BQ34/$BZ34 -> 11.483252 | BE34: =$AY34*BR34/$BZ34 -> 29.665067 | BF34: =$AY34*BS34/$BZ34 -> 18.181815 | BG34: =$AY34*BT34/$BZ34 -> 4.7846882 | BH34: =$AY34*BU34/$BZ34 -> 37.320568 | BI34: =$AY34*BV34/$BZ34 -> 2.8708129 | BJ34: =$AY34*BW34/$BZ34 -> 25.837316 | BK34: =$AY34*BX34/$BZ34 -> 121.53108 | BL34: =$AY34*BY34/$BZ34 -> 13.397127 | BM34: =SUM(BD34:BL34) -> 265.07173 | BO34: c27 | BP34: Post and telecommunications | BQ34: 1200 | BR34: 3100 | BS34: 1900 | BT34: 500 | BU34: 3900 | BV34: 300 | BW34: 2700 | BX34: 12700 | BY34: 1400 | BZ34: 27700 | CB34: c27 | CC34: Post and telecommunications | CD34: =BQ34/$AR34 -> 2.3150199 | CE34: =BR34/$AR34 -> 5.9804681 | CF34: =BS34/$AR34 -> 3.6654482 | CG34: =BT34/$AR34 -> 0.96459164 | CH34: =BU34/$AR34 -> 7.5238148 | CI34: =BV34/$AR34 -> 0.57875498 | CJ34: =BW34/$AR34 -> 5.2087948 | CK34: =BX34/$AR34 -> 24.500628 | ... CM34: =BZ34/$AR34 -> 53.438377 | CO34: 27 | CP34: Post and Telecommunications | CQ34: 480.98372 | CR34: 227.95505 | CS34: 0.90596729 | CT34: 0 | CU34: 12.566646 | CW34: 27 | CX34: Post and Telecommunications | CY34: =CQ34/$AR34 -> 0.92790574 | CZ34: =CR34/$AR34 -> 0.43976707 | DA34: =CS34/$AR34 -> 0.0017477769 | DB34: =CT34/$AR34 -> 0 | DC34: =CU34/$AR34 -> 0.024243363
A35: J | B35: Financial intermediation | C35: c28 | D35: 0.26617085 | E35: 0.39238565 | F35: 11.559338 | G35: 0.19154012 | H35: 0.020217094 | I35: 0.0092184252 | J35: 0.47823482 | K35: 0.27253471 | L35: 0.12587192 | M35: 0.25775077 | N35: 0.93855551 | O35: 0.17441133 | P35: 0.20255273 | Q35: 0.045962661 | R35: 0.11683654 | S35: 0.27004607 | T35: 3.2853739 | U35: 0.093118953 | V35: 0.381943 | W35: 4.0020623 | X35: 4.1665609 | Y35: 4.7496614 | Z35: 8.2542483 | AA35: 0.079650867 | AB35: 0.42579201 | AC35: 2.5039377 | AD35: 5.8112928 | AE35: 1306.6954 | AF35: 2.6467686 | AG35: 2.0381495 | AH35: 3.9328514 | AI35: 2.9876474 | AJ35: 0 | AK35: 7.0454204 | AL35: 75.627318 | AM35: 0 | AN35: 26.744167 | AO35: 32.59822 | AP35: 2.236418 | AQ35: 81.038591 | AR35: 1592.6662 | AT35: 218.24471 | AV35: 1592.6662 | AW35: =AV35-AR35 -> 0 | AY35: 213.81454 | AZ35: =AY35/$AR35 -> 0.13424944 | BB35: c28 | BC35: Financial intermediation | BD35: =$AY35*BQ35/$BZ35 -> 6.7449383 | BE35: =$AY35*BR35/$BZ35 -> 43.167605 | BF35: =$AY35*BS35/$BZ35 -> 39.120642 | BG35: =$AY35*BT35/$BZ35 -> 2.6979753 | BH35: =$AY35*BU35/$BZ35 -> 18.885827 | BI35: =$AY35*BV35/$BZ35 -> 4.7214568 | BJ35: =$AY35*BW35/$BZ35 -> 10.117407 | BK35: =$AY35*BX35/$BZ35 -> 66.774889 | BL35: =$AY35*BY35/$BZ35 -> 21.583803 | BM35: =SUM(BD35:BL35) -> 213.81454 | BO35: c28 | BP35: Financial intermediation | BQ35: 1000 | BR35: 6400 | BS35: 5800 | BT35: 400 | BU35: 2800 | BV35: 700 | BW35: 1500 | BX35: 9900 | BY35: 3200 | BZ35: 31700 | CB35: c28 | CC35: Financial intermediation | CD35: =BQ35/$AR35 -> 0.62787797 | CE35: =BR35/$AR35 -> 4.018419 | CF35: =BS35/$AR35 -> 3.6416922 | CG35: =BT35/$AR35 -> 0.25115119 | CH35: =BU35/$AR35 -> 1.7580583 | CI35: =BV35/$AR35 -> 0.43951458 | CJ35: =BW35/$AR35 -> 0.94181695 | CK35: =BX35/$AR35 -> 6.2159919 | ... CM35: =BZ35/$AR35 -> 19.903732 | CO35: 28 | CP35: Financial Intermediation | CQ35: 556813.45 | CR35: 729.25986 | CS35: 2.393611 | CT35: 0 | CU35: 33.201708 | CW35: 28 | CX35: Financial Intermediation | CY35: =CQ35/$AR35 -> 349.6109 | CZ35: =CR35/$AR35 -> 0.4578862 | DA35: =CS35/$AR35 -> 0.0015028956 | DB35: =CT35/$AR35 -> 0 | DC35: =CU35/$AR35 -> 0.020846621
A36: 70 | B36: Real estate activities | C36: c29 | D36: 1.0790666 | E36: 9.7342418 | F36: 6.8011932 | G36: 2.3899936 | H36: 0.25226425 | I36: 0.011538041 | J36: 1.8439787 | K36: 0.59325419 | L36: 0.27399828 | M36: 1.9221673 | N36: 6.9992444 | O36: 3.0801627 | P36: 0.21430322 | Q36: 0.048629046 | R36: 0.12361446 | S36: 0.14311255 | T36: 0.66005865 | U36: 4.9853361 | V36: 0.069401441 | W36: 6.3421667 | X36: 8.7665029 | Y36: 7.0535952 | Z36: 10.012679 | AA36: 0.096619165 | AB36: 0.51649994 | AC36: 3.0373601 | AD36: 4.327977 | AE36: 0 | AF36: 8.8262411 | AG36: 6.796665 | AH36: 0.60437906 | AI36: 4.236845 | AJ36: 5.5819008 | AK36: 7.8092193 | AL36: 95.34181 | AM36: 0 | AN36: 50.464468 | AO36: 11.990997 | AP36: 0.00027994074 | AQ36: 0.69984723 | AR36: 273.73161 | AT36: 158.4974 | AV36: 273.73161 | AW36: =AV36-AR36 -> 0 | AY36: 168.01209 | AZ36: =AY36/$AR36 -> 0.61378402 | BB36: c29 | BC36: Real estate activities | BD36: =$AY36*BQ36/$BZ36 -> 3.733602 | BE36: =$AY36*BR36/$BZ36 -> 9.3340049 | BF36: =$AY36*BS36/$BZ36 -> 0 | BG36: =$AY36*BT36/$BZ36 -> 0 | BH36: =$AY36*BU36/$BZ36 -> 0 | BI36: =$AY36*BV36/$BZ36 -> 0 | BJ36: =$AY36*BW36/$BZ36 -> 7.467204 | BK36: =$AY36*BX36/$BZ36 -> 147.47728 | BL36: =$AY36*BY36/$BZ36 -> 0 | BM36: =SUM(BD36:BL36) -> 168.01209 | BO36: c29 | BP36: Real estate activities | BQ36: 200 | BR36: 500 | BS36: 0 | BT36: 0 | BU36: 0 | BV36: 0 | BW36: 400 | BX36: 7900 | BY36: 0 | BZ36: 9000 | CB36: c29 | CC36: Real estate activities | CD36: =BQ36/$AR36 -> 0.73064269 | CE36: =BR36/$AR36 -> 1.8266067 | CF36: =BS36/$AR36 -> 0 | CG36: =BT36/$AR36 -> 0 | CH36: =BU36/$AR36 -> 0 | CI36: =BV36/$AR36 -> 0 | CJ36: =BW36/$AR36 -> 1.4612854 | CK36: =BX36/$AR36 -> 28.860386 | ... CM36: =BZ36/$AR36 -> 32.878921 | CO36: 29 | CP36: Real Estate Activities | CQ36: 92.081631 | CR36: 124.2129 | CS36: 0.14530379 | CT36: 0 | CU36: 2.0155046 | CW36: 29 | CX36: Real Estate Activities | CY36: =CQ36/$AR36 -> 0.33639385 | CZ36: =CR36/$AR36 -> 0.45377624 | DA36: =CS36/$AR36 -> 0.00053082574 | DB36: =CT36/$AR36 -> 0 | DC36: =CU36/$AR36 -> 0.0073630683
A37: 71t74 | B37: Renting of M&Eq and other business activities | C37: c30 | D37: 0.81013658 | E37: 8.1080952 | F37: 5.1061681 | G37: 1.7943483 | H37: 0.18939378 | I37: 0.0086624764 | J37: 1.3844137 | K37: 0.44540061 | L37: 0.20571115 | M37: 1.4431158 | N37: 5.2548601 | O37: 2.3125102 | P37: 0.16089357 | Q37: 0.036509488 | R37: 0.092806691 | S37: 0.10744537 | T37: 0.49555575 | U37: 3.7428674 | V37: 0.05210489 | W37: 4.7615423 | X37: 6.5816742 | Y37: 5.2956653 | Z37: 7.5172725 | AA37: 0.072539286 | AB37: 0.38777542 | AC37: 2.280375 | AD37: 3.2493383 | AE37: 0 | AF37: 7.6057643 | AG37: 5.8568343 | AH37: 0.45375289 | AI37: 3.1809187 | AJ37: 4.1907535 | AK37: 5.8629692 | AL37: 71.584324 | AM37: 0 | AN37: 37.889619 | AO37: 6.8522821 | AP37: 0.00027010418 | AQ37: 0.50165062 | AR37: 205.87632 | AT37: 116.82815 | AV37: 205.87632 | AW37: =AV37-AR37 -> 0 | AY37: 126.3636 | AZ37: =AY37/$AR37 -> 0.61378402 | BB37: c30 | BC37: Other business activities | BD37: =$AY37*BQ37/$BZ37 -> 10.657171 | BE37: =$AY37*BR37/$BZ37 -> 20.70536 | BF37: =$AY37*BS37/$BZ37 -> 11.570642 | BG37: =$AY37*BT37/$BZ37 -> 2.7404153 | BH37: =$AY37*BU37/$BZ37 -> 21.009851 | BI37: =$AY37*BV37/$BZ37 -> 1.522453 | BJ37: =$AY37*BW37/$BZ37 -> 16.746983 | BK37: =$AY37*BX37/$BZ37 -> 35.320909 | BL37: =$AY37*BY37/$BZ37 -> 6.0898118 | BM37: =SUM(BD37:BL37) -> 126.3636 | BO37: c30 | BP37: Renting of M&Eq and other business activities | BQ37: 3500 | BR37: 6800 | BS37: 3800 | BT37: 900 | BU37: 6900 | BV37: 500 | BW37: 5500 | BX37: 11600 | BY37: 2000 | BZ37: 41500 | CB37: c30 | CC37: Renting of M&Eq and other business activities | CD37: =BQ37/$AR37 -> 17.000498 | CE37: =BR37/$AR37 -> 33.029539 | CF37: =BS37/$AR37 -> 18.457684 | CG37: =BT37/$AR37 -> 4.3715567 | CH37: =BU37/$AR37 -> 33.515268 | CI37: =BV37/$AR37 -> 2.4286426 | CJ37: =BW37/$AR37 -> 26.715069 | CK37: =BX37/$AR37 -> 56.344508 | ... CM37: =BZ37/$AR37 -> 201.57734 | CO37: 30 | CP37: Renting of M&Eq and Other Business Activities | CQ37: 179.46376 | CR37: 92.549438 | CS37: 0.28825826 | CT37: 0 | CU37: 3.9984219 | CW37: 30 | CX37: Renting of M&Eq and Other Business Activities | CY37: =CQ37/$AR37 -> 0.87170667 | CZ37: =CR37/$AR37 -> 0.44953902 | DA37: =CS37/$AR37 -> 0.0014001526 | DB37: =CT37/$AR37 -> 0 | DC37: =CU37/$AR37 -> 0.019421476
A38: L | B38: Public administration and defense; compulsory social security | C38: c31 | D38: 0 | E38: 0 | F38: 0 | G38: 0 | H38: 0 | I38: 0 | J38: 0 | K38: 0 | L38: 0 | M38: 0.43176134 | N38: 1.5721853 | O38: 0 | P38: 0 | Q38: 0 | R38: 0 | S38: 0 | T38: 0 | U38: 0 | V38: 0 | W38: 0 | X38: 0 | Y38: 0.13236161 | Z38: 0.0016900157 | AA38: 1.6308113e-05 | AB38: 8.7178766e-05 | AC38: 0.00051266861 | AD38: 0.033124187 | AE38: 0 | AF38: 0.87725857 | AG38: 0.67553475 | AH38: 1.0906421 | AI38: 0 | AJ38: 0 | AK38: 0.11110532 | AL38: 0.0052932809 | AM38: 0 | AN38: 241.962 | AO38: 27.250586 | AP38: 9.9805288 | AQ38: 325.30421 | AR38: 609.4289 | AT38: 604.50262 | AV38: 609.4289 | AW38: =AV38-AR38 -> 0 | AY38: 402.33629 | AZ38: =AY38/$AR38 -> 0.66018578 | BB38: c31 | BC38: Public administration and defense | BD38: =$AY38*BQ38/$BZ38 -> 18.812749 | BE38: =$AY38*BR38/$BZ38 -> 59.431185 | BF38: =$AY38*BS38/$BZ38 -> 29.929374 | BG38: =$AY38*BT38/$BZ38 -> 16.674937 | BH38: =$AY38*BU38/$BZ38 -> 57.720935 | BI38: =$AY38*BV38/$BZ38 -> 14.537124 | BJ38: =$AY38*BW38/$BZ38 -> 48.31456 | BK38: =$AY38*BX38/$BZ38 -> 141.09562 | BL38: =$AY38*BY38/$BZ38 -> 15.819812 | BM38: =SUM(BD38:BL38) -> 402.33629 | BO38: c31 | BP38: Public administration and defense; compulsory social security | BQ38: 4400 | BR38: 13900 | BS38: 7000 | BT38: 3900 | BU38: 13500 | BV38: 3400 | BW38: 11300 | BX38: 33000 | BY38: 3700 | BZ38: 94100 | CB38: c31 | CC38: Public administration and defense; compulsory social security | CD38: =BQ38/$AR38 -> 7.2198742 | CE38: =BR38/$AR38 -> 22.808239 | CF38: =BS38/$AR38 -> 11.486164 | CG38: =BT38/$AR38 -> 6.399434 | CH38: =BU38/$AR38 -> 22.151887 | CI38: =BV38/$AR38 -> 5.5789937 | CJ38: =BW38/$AR38 -> 18.54195 | CK38: =BX38/$AR38 -> 54.149057 | ... CM38: =BZ38/$AR38 -> 154.40686 | CO38: 31 | CP38: Public Administration and Defense; Compulsory Social Security | CQ38: 160.52704 | CR38: 265.46136 | CS38: 0.20337752 | CT38: 0 | CU38: 2.8210436 | CW38: 31 | CX38: Public Administration and Defense; Compulsory Social Security | CY38: =CQ38/$AR38 -> 0.26340569 | CZ38: =CR38/$AR38 -> 0.43559036 | DA38: =CS38/$AR38 -> 0.00033371821 | DB38: =CT38/$AR38 -> 0 | DC38: =CU38/$AR38 -> 0.0046289955
A39: M | B39: Education | C39: c32 | D39: 0 | E39: 0 | F39: 1.2642125 | G39: 0 | H39: 0 | I39: 0 | J39: 0 | K39: 0.083910429 | L39: 0.038754574 | M39: 0 | N39: 0 | O39: 0 | P39: 0.27316215 | Q39: 0.061985138 | R39: 0.1575655 | S39: 0.0098257744 | T39: 0.87017065 | U39: 0.24595707 | V39: 0 | W39: 0.093010634 | X39: 0.89151892 | Y39: 0.20471879 | Z39: 0.18846109 | AA39: 0.0018185895 | AB39: 0.0097216878 | AC39: 0.057169932 | AD39: 0.52880621 | AE39: 0.18094382 | AF39: 0.85728637 | AG39: 0.66015511 | AH39: 2.4679763 | AI39: 7.552299 | AJ39: 0.71751283 | AK39: 0.89469172 | AL39: 40.202329 | AM39: 0 | AN39: 431.64659 | AO39: 93.692613 | AP39: 0.0033048903 | AQ39: 9.1925071 | AR39: 593.04898 | AT39: 574.73734 | AV39: 593.04898 | AW39: =AV39-AR39 -> 0 | AY39: 450.39388 | AZ39: =AY39/$AR39 -> 0.75945478 | BB39: c32 | BC39: Education | BD39: =$AY39*BQ39/$BZ39 -> 35.821822 | BE39: =$AY39*BR39/$BZ39 -> 80.162247 | BF39: =$AY39*BS39/$BZ39 -> 29.269049 | BG39: =$AY39*BT39/$BZ39 -> 37.350802 | BH39: =$AY39*BU39/$BZ39 -> 71.862069 | BI39: =$AY39*BV39/$BZ39 -> 23.371554 | BJ39: =$AY39*BW39/$BZ39 -> 58.97495 | BK39: =$AY39*BX39/$BZ39 -> 93.923069 | BL39: =$AY39*BY39/$BZ39 -> 19.658317 | BM39: =SUM(BD39:BL39) -> 450.39388 | BO39: c32 | BP39: Education | BQ39: 16400 | BR39: 36700 | BS39: 13400 | BT39: 17100 | BU39: 32900 | BV39: 10700 | BW39: 27000 | BX39: 43000 | BY39: 9000 | BZ39: 206200 | CB39: c32 | CC39: Education | CD39: =BQ39/$AR39 -> 27.653703 | CE39: =BR39/$AR39 -> 61.883591 | CF39: =BS39/$AR39 -> 22.595098 | CG39: =BT39/$AR39 -> 28.834044 | CH39: =BU39/$AR39 -> 55.476025 | CI39: =BV39/$AR39 -> 18.042355 | CJ39: =BW39/$AR39 -> 45.527437 | CK39: =BX39/$AR39 -> 72.506659 | ... CM39: =BZ39/$AR39 -> 347.69472 | CO39: 32 | CP39: Education | CQ39: 243.87957 | CR39: 262.32522 | CS39: 0.32032846 | CT39: 0 | CU39: 4.4432666 | CW39: 32 | CX39: Education | CY39: =CQ39/$AR39 -> 0.41123006 | CZ39: =CR39/$AR39 -> 0.44233314 | DA39: =CS39/$AR39 -> 0.00054013828 | DB39: =CT39/$AR39 -> 0 | DC39: =CU39/$AR39 -> 0.0074922423
A40: N | B40: Health and social work | C40: c33 | D40: 0.002314876 | E40: 0.059560584 | F40: 0.20106209 | G40: 0.063967332 | H40: 0.0067517631 | I40: 0 | J40: 0.016504876 | K40: 0.084071498 | L40: 0.038828965 | M40: 0.028288954 | N40: 0.1030094 | O40: 0 | P40: 0.021681133 | Q40: 0.004919818 | R40: 0.01250612 | S40: 0 | T40: 0.1630117 | U40: 0.49814858 | V40: 0.017553422 | W40: 0.087111616 | X40: 0.062679169 | Y40: 0.072182552 | Z40: 0.089110992 | AA40: 0.00085989269 | AB40: 0.0045967539 | AC40: 0.027031943 | AD40: 0.022604741 | AE40: 0.0084733907 | AF40: 0.075273249 | AG40: 0.057964319 | AH40: 1.7421271 | AI40: 5.0266139 | AJ40: 2.1825327 | AK40: 0.77191004 | AL40: 32.696148 | AM40: 0 | AN40: 278.46882 | AO40: 9.9643014 | AP40: 0.0023768698 | AQ40: 0.23610606 | AR40: 332.92101 | AT40: 321.36775 | AV40: 332.92101 | AW40: =AV40-AR40 -> 0 | AY40: 239.5103 | AZ40: =AY40/$AR40 -> 0.7194208 | BB40: c33 | BC40: Health and social work | BD40: =$AY40*BQ40/$BZ40 -> 13.262785 | BE40: =$AY40*BR40/$BZ40 -> 40.308464 | BF40: =$AY40*BS40/$BZ40 -> 21.064423 | BG40: =$AY40*BT40/$BZ40 -> 8.3217475 | BH40: =$AY40*BU40/$BZ40 -> 38.488082 | BI40: =$AY40*BV40/$BZ40 -> 8.8418567 | BJ40: =$AY40*BW40/$BZ40 -> 45.249502 | BK40: =$AY40*BX40/$BZ40 -> 54.351413 | BL40: =$AY40*BY40/$BZ40 -> 9.6220205 | BM40: =SUM(BD40:BL40) -> 239.5103 | BO40: c33 | BP40: Health and social work | BQ40: 5100 | BR40: 15500 | BS40: 8100 | BT40: 3200 | BU40: 14800 | BV40: 3400 | BW40: 17400 | BX40: 20900 | BY40: 3700 | BZ40: 92100 | CB40: c33 | CC40: Health and social work | CD40: =BQ40/$AR40 -> 15.318949 | CE40: =BR40/$AR40 -> 46.557591 | CF40: =BS40/$AR40 -> 24.330096 | CG40: =BT40/$AR40 -> 9.6118897 | CH40: =BU40/$AR40 -> 44.45499 | CI40: =BV40/$AR40 -> 10.212633 | CJ40: =BW40/$AR40 -> 52.26465 | CK40: =BX40/$AR40 -> 62.777655 | ... CM40: =BZ40/$AR40 -> 276.6422 | CO40: 33 | CP40: Health and Social Work | CQ40: 270.22345 | CR40: 144.99474 | CS40: 0.49903368 | CT40: 0 | CU40: 6.9220816 | CW40: 33 | CX40: Health and Social Work | CY40: =CQ40/$AR40 -> 0.81167436 | CZ40: =CR40/$AR40 -> 0.43552295 | DA40: =CS40/$AR40 -> 0.0014989552 | DB40: =CT40/$AR40 -> 0 | DC40: =CU40/$AR40 -> 0.020791964
A41: O | B41: Other community, social, and personal services | C41: c34 | D41: 0.001926974 | E41: 0.53161153 | F41: 0.93270358 | G41: 0.071673751 | H41: 0.0075651771 | I41: 0.014949274 | J41: 0.14628683 | K41: 0.67046334 | L41: 0.30965783 | M41: 0.17776081 | N41: 0.64728569 | O41: 0 | P41: 0.10308509 | Q41: 0.02339176 | R41: 0.05946158 | S41: 0.025535074 | T41: 0.49083909 | U41: 8.7843968 | V41: 0.25976903 | W41: 1.962981 | X41: 3.0045706 | Y41: 4.6295777 | Z41: 1.3257 | AA41: 0.012792582 | AB41: 0.068385688 | AC41: 0.40215292 | AD41: 2.3309711 | AE41: 0.19438435 | AF41: 6.9006645 | AG41: 5.3138707 | AH41: 0.92874049 | AI41: 2.8604256 | AJ41: 2.293591 | AK41: 12.706118 | AL41: 42.743987 | AM41: 62.285562 | AN41: 47.812877 | AO41: 19.442025 | AP41: -0.71682955 | AQ41: 0.054861118 | AR41: 229.81577 | AT41: 171.62248 | AV41: 229.81577 | AW41: =AV41-AR41 -> 0 | AY41: 115.6436 | AZ41: =AY41/$AR41 -> 0.50320132 | BB41: c34 | BC41: Other services | BD41: =$AY41*BQ41/$BZ41 -> 8.7707226 | BE41: =$AY41*BR41/$BZ41 -> 13.318505 | BF41: =$AY41*BS41/$BZ41 -> 6.17199 | BG41: =$AY41*BT41/$BZ41 -> 4.7102029 | BH41: =$AY41*BU41/$BZ41 -> 8.2834602 | BI41: =$AY41*BV41/$BZ41 -> 2.9235742 | BJ41: =$AY41*BW41/$BZ41 -> 13.480925 | BK41: =$AY41*BX41/$BZ41 -> 50.188024 | BL41: =$AY41*BY41/$BZ41 -> 7.7961978 | BM41: =SUM(BD41:BL41) -> 115.6436 | BO41: c34 | BP41: Other community, social, and personal services | BQ41: 5400 | BR41: 8200 | BS41: 3800 | BT41: 2900 | BU41: 5100 | BV41: 1800 | BW41: 8300 | BX41: 30900 | BY41: 4800 | BZ41: 71200 | CB41: c34 | CC41: Other community, social, and personal services | CD41: =BQ41/$AR41 -> 23.497082 | CE41: =BR41/$AR41 -> 35.680754 | CF41: =BS41/$AR41 -> 16.534983 | CG41: =BT41/$AR41 -> 12.618803 | CH41: =BU41/$AR41 -> 22.191688 | CI41: =BV41/$AR41 -> 7.8323606 | CJ41: =BW41/$AR41 -> 36.115885 | CK41: =BX41/$AR41 -> 134.45552 | ... CM41: =BZ41/$AR41 -> 309.81337 | CO41: 34 | CP41: Other Community, Social, and Personal Services | CQ41: 481.27813 | CR41: 100.88187 | CS41: 1.0234676 | CT41: 0 | CU41: 14.19649 | CW41: 34 | CX41: Other Community, Social, and Personal Services | CY41: =CQ41/$AR41 -> 2.094191 | CZ41: =CR41/$AR41 -> 0.43896843 | DA41: =CS41/$AR41 -> 0.0044534265 | DB41: =CT41/$AR41 -> 0 | DC41: =CU41/$AR41 -> 0.061773348
B42: Imports
A43: AtB | B43: Agriculture, hunting, forestry, and fishing | C43: m1 | D43: 60.93888 | E43: 0.018023626 | F43: 5.3344811 | G43: 0.72748519 | H43: 0.07102508 | I43: 0.0012588239 | J43: 0.0039153743 | K43: 0.013529272 | L43: 0.006831358 | M43: 0.0025070698 | N43: 0.0098635547 | O43: 0.0016186863 | P43: 0.00085538976 | Q43: 4.3080095e-05 | R43: 0.00045238012 | S43: 0.00055481357 | T43: 0.0016188368 | U43: 0.010544501 | V43: 1.8929419e-05 | W43: 0.043007087 | X43: 0.0075273551 | Y43: 0.57613366 | Z43: 0.0010188827 | AA43: 3.5576301e-06 | AB43: 0.00029813201 | AC43: 0.00023713859 | AD43: 0.00042181148 | AE43: 0.00040112698 | AF43: 0.011116745 | AG43: 0.012555262 | AH43: 0.86164253 | AI43: 0.52729682 | AJ43: 0.59316433 | AK43: 0.0034314361 | AL43: 48.913089 | AM43: 0.004378909 | AN43: 0.57688474 | AO43: 0.35881036 | AP43: -0.20389796 | AQ43: 0 | AR43: 119.43103
A44: C | B44: Mining and quarrying | C44: m2 | D44: 0.070545245 | E44: 3.004542 | F44: 1.4456991 | G44: 0.18514316 | H44: 0.022590686 | I44: 0.004780242 | J44: 0.017934582 | K44: 6.6451643 | L44: 2.9711616 | M44: 1.1675153 | N44: 4.3228845 | O44: 2.339303 | P44: 0.46213002 | Q44: 0.10659577 | R44: 0.28500978 | S44: 0.58282071 | T44: 12.167513 | U44: 8.5279803 | V44: 0.13099734 | W44: 0.064575869 | X44: 0.33750202 | Y44: 0.11939123 | Z44: 0.47034031 | AA44: 0.0036976877 | AB44: 0.02279409 | AC44: 0.14330994 | AD44: 0.24173085 | AE44: 0.0038667494 | AF44: 0.0074271961 | AG44: 0.02582904 | AH44: 0.99469064 | AI44: 5.1899032 | AJ44: 0.03450782 | AK44: 0.091667429 | AL44: 14.714975 | AM44: 0 | AN44: 0 | AO44: 1.7279155 | AP44: -0.36761708 | AQ44: 0 | AR44: 68.286818
A45: 15t16 | B45: Food, beverages, and tobacco | C45: m3 | D45: 6.9162991 | E45: 0.19800904 | F45: 56.18871 | G45: 0.83717189 | H45: 0.087920242 | I45: 0.0010834215 | J45: 0.025293227 | K45: 2.3951316 | L45: 1.0907267 | M45: 0.48068187 | N45: 1.7785157 | O45: 0.43101278 | P45: 0.0036839823 | Q45: 0.00061602377 | R45: 0.0020182907 | S45: 0.0056098384 | T45: 1.3860224 | U45: 41.378002 | V45: 0.0048592444 | W45: 4.9695404 | X45: 61.198632 | Y45: 23.093043 | Z45: 3.8522758 | AA45: 0.029277262 | AB45: 0.14687732 | AC45: 1.1619019 | AD45: 3.7005283 | AE45: 0.72774145 | AF45: 5.3334783 | AG45: 4.0964553 | AH45: 19.721814 | AI45: 9.4934316 | AJ45: 5.1745403 | AK45: 2.1674679 | AL45: 308.37235 | AM45: 0.59913565 | AN45: 0.0010641028 | AO45: 20.790934 | AP45: 22.042098 | AQ45: 0 | AR45: 609.88395
A46: 17t18 | B46: Textiles and textile products | C46: m4 | D46: 0.0053895608 | E46: 0.1046249 | F46: 0.81626803 | G46: 7.7906692 | H46: 0.88433189 | I46: 0.016572442 | J46: 0.2223868 | K46: 2.3143823 | L46: 1.053033 | M46: 0.18770744 | N46: 0.69428367 | O46: 0.21125638 | P46: 0.21863518 | Q46: 0.048819723 | R46: 0.12753748 | S46: 0.76137515 | T46: 0.36648277 | U46: 0.07660468 | V46: 0.012848861 | W46: 0.085472125 | X46: 0.81770333 | Y46: 3.0067484 | Z46: 0.26255323 | AA46: 0.0020599905 | AB46: 0.010426806 | AC46: 0.079252656 | AD46: 0.19673826 | AE46: 0.010088715 | AF46: 0.12954635 | AG46: 0.11016763 | AH46: 2.339726 | AI46: 1.1673992 | AJ46: 1.4091052 | AK46: 1.1724132 | AL46: 254.30547 | AM46: 1.3228894 | AN46: 1.6842425e-05 | AO46: 0.277667 | AP46: 4.5957306 | AQ46: 0 | AR46: 287.21439
A47: 19 | B47: Leather, leather products, and footwear | C47: m5 | D47: 0.00052283402 | E47: 0.011153685 | F47: 0.081925913 | G47: 0.8728028 | H47: 0.092411013 | I47: 0.0017026541 | J47: 0.022912022 | K47: 0.23623358 | L47: 0.10740542 | M47: 0.019027308 | N47: 0.070387677 | O47: 0.021178111 | P47: 0.021982511 | Q47: 0.0049072825 | R47: 0.01281149 | S47: 0.077263137 | T47: 0.037268365 | U47: 0.0077771102 | V47: 0.0013242177 | W47: 0.0085515048 | X47: 0.084180147 | Y47: 0.30923032 | Z47: 0.027051657 | AA47: 0.00021086548 | AB47: 0.0010637633 | AC47: 0.0081621773 | AD47: 0.019491849 | AE47: 0.0010788302 | AF47: 0.012798698 | AG47: 0.011206367 | AH47: 0.24789767 | AI47: 0.12043905 | AJ47: 0.14617262 | AK47: 0.12265496 | AL47: 26.087137 | AM47: 0.13452848 | AN47: 0 | AO47: 0.029728049 | AP47: 0.48046309 | AQ47: 0 | AR47: 29.553044
A48: 20 | B48: Wood and products of wood and cork | C48: m6 | D48: 0.0070039877 | E48: 0.042120428 | F48: 0.33598001 | G48: 0.0044766068 | H48: 0.00072913282 | I48: 0.20603 | J48: 1.7030681 | K48: 0.14524905 | L48: 0.066829644 | M48: 0.1491586 | N48: 0.55198342 | O48: 0.31561404 | P48: 0.058035033 | Q48: 0.013111019 | R48: 0.033450846 | S48: 1.0271339 | T48: 0.20427454 | U48: 4.2487004 | V48: 0.018208425 | W48: 0.61879752 | X48: 0.97278908 | Y48: 0.72958362 | Z48: 0.11071508 | AA48: 0.0010074428 | AB48: 0.0053084612 | AC48: 0.033499452 | AD48: 0.13402489 | AE48: 0.0013423801 | AF48: 0.090610771 | AG48: 0.068398853 | AH48: 0.30811007 | AI48: 0.29018589 | AJ48: 0.027560674 | AK48: 0.55138219 | AL48: 25.697848 | AM48: 0.0051730991 | AN48: 1.8793866e-05 | AO48: 0.093162256 | AP48: 0.17722195 | AQ48: 0 | AR48: 39.047898
A49: 21t22 | B49: Pulp, paper, paper products, printing, and publishing | C49: m7 | D49: 0.051278095 | E49: 0.48415683 | F49: 1.9733796 | G49: 0.11597423 | H49: 0.012254069 | I49: 1.0033502 | J49: 6.2092339 | K49: 0.80106226 | L49: 0.36743825 | M49: 0.58873761 | N49: 2.177288 | O49: 1.6805066 | P49: 0.35888827 | Q49: 0.080513409 | R49: 0.20710313 | S49: 3.5881159 | T49: 1.4380089 | U49: 14.833097 | V49: 0.10756232 | W49: 2.6594434 | X49: 8.2286292 | Y49: 3.5541325 | Z49: 0.44966071 | AA49: 0.0040384648 | AB49: 0.021255289 | AC49: 0.13610992 | AD49: 0.6446032 | AE49: 0.67767378 | AF49: 0.37142767 | AG49: 0.27957567 | AH49: 2.2752939 | AI49: 3.4889589 | AJ49: 0.52175428 | AK49: 2.7903201 | AL49: 91.583483 | AM49: 0.025114568 | AN49: 1.2397479 | AO49: 0.31874171 | AP49: 1.640643 | AQ49: 0 | AR49: 156.98856
A50: 23 | B50: Coke, refined petroleum, and nuclear fuel | C50: m8 | D50: 21.875088 | E50: 9.773694 | F50: 2.1786967 | G50: 1.130519 | H50: 0.12135729 | I50: 0.10632314 | J50: 1.714191 | K50: 3.7239466 | L50: 1.8883986 | M50: 0.42194129 | N50: 1.5607631 | O50: 5.1659035 | P50: 0.84951963 | Q50: 0.19233709 | R50: 0.48681071 | S50: 0.18932155 | T50: 15.288785 | U50: 87.369736 | V50: 1.3578785 | W50: 9.5813029 | X50: 75.332519 | Y50: 0.16580829 | Z50: 57.051365 | AA50: 0.42395443 | AB50: 2.2483497 | AC50: 16.949596 | AD50: 23.104354 | AE50: 0.77848956 | AF50: 4.4076636 | AG50: 2.9506241 | AH50: 6.6561461 | AI50: 0.48031854 | AJ50: 4.2314042 | AK50: 1.8445858 | AL50: 341.13731 | AM50: 7.880575 | AN50: 0.0033132672 | AO50: 80.983697 | AP50: 43.04704 | AQ50: 0 | AR50: 834.65363
A51: 24 | B51: Chemicals and chemical products | C51: m9 | D51: 9.8386638 | E51: 4.0388284 | F51: 0.89509344 | G51: 0.48469985 | H51: 0.051435518 | I51: 0.041605128 | J51: 0.71133879 | K51: 1.7535785 | L51: 0.80242456 | M51: 0.17892986 | N51: 0.66168955 | O51: 2.0270473 | P51: 0.33490719 | Q51: 0.075279511 | R51: 0.18719675 | S51: 0.084394017 | T51: 6.3507406 | U51: 33.707782 | V51: 0.62124643 | W51: 4.1524453 | X51: 32.161627 | Y51: 0.064204734 | Z51: 20.124514 | AA51: 0.1985177 | AB51: 1.0319307 | AC51: 5.8320279 | AD51: 9.5628859 | AE51: 0.33745618 | AF51: 1.9206432 | AG51: 1.1872561 | AH51: 2.386782 | AI51: 0.13672882 | AJ51: 1.4750075 | AK51: 0.68377142 | AL51: 133.68858 | AM51: 3.0396285 | AN51: 1.2276606e-06 | AO51: 39.22902 | AP51: 20.656522 | AQ51: 0 | AR51: 340.71643
A52: 25 | B52: Rubber and plastics | C52: m10 | D52: 0.079545699 | E52: 0.010703203 | F52: 0.71305142 | G52: 0.023883569 | H52: 0.0025461808 | I52: 0.00012594729 | J52: 0.002902395 | K52: 0.011897033 | L52: 0.0054773872 | M52: 1.5875142 | N52: 5.8704112 | O52: 0.011523166 | P52: 0.037624942 | Q52: 0.0086360562 | R52: 0.021433397 | S52: 0.0085944687 | T52: 0.57011828 | U52: 22.308086 | V52: 0.0001531658 | W52: 0.92061669 | X52: 3.9659858 | Y52: 0.35498156 | Z52: 0.98193418 | AA52: 0.0087392171 | AB52: 0.045740219 | AC52: 0.29696788 | AD52: 0.58863697 | AE52: 0.0017463353 | AF52: 0.64227442 | AG52: 0.40982128 | AH52: 0.029997495 | AI52: 0.055147748 | AJ52: 0.0063989387 | AK52: 0.073559232 | AL52: 10.729342 | AM52: 0.011670062 | AN52: 1.2629474e-07 | AO52: 3.3659439 | AP52: 1.770685 | AQ52: 0 | AR52: 55.534417
A53: 26 | B53: Other nonmetallic minerals | C53: m11 | D53: 0.27978905 | E53: 0.033030973 | F53: 2.3407297 | G53: 0.078459811 | H53: 0.0082918091 | I53: 0.00084085793 | J53: 0.0092871193 | K53: 0.039475289 | L53: 0.018116161 | M53: 4.3590671 | N53: 17.741588 | O53: 0.036497431 | P53: 0.11740981 | Q53: 0.026369283 | R53: 0.066028517 | S53: 0.028098849 | T53: 1.7340879 | U53: 63.002521 | V53: 0.00043261961 | W53: 2.8561635 | X53: 12.347307 | Y53: 1.0888447 | Z53: 3.0350918 | AA53: 0.026742096 | AB53: 0.13919814 | AC53: 0.91812479 | AD53: 1.9015863 | AE53: 0.005609046 | AF53: 2.0910492 | AG53: 1.3110465 | AH53: 0.089756171 | AI53: 0.15511542 | AJ53: 0.018382876 | AK53: 0.22216739 | AL53: 36.252771 | AM53: 0.039377969 | AN53: 3.2251912e-08 | AO53: 11.800541 | AP53: 6.2491385 | AQ53: 0 | AR53: 170.46813
A54: 27t28 | B54: Basic metals and fabricated metal | C54: m12 | D54: 4.3648903 | E54: 0.77612154 | F54: 1.0285498 | G54: 0.56602628 | H54: 0.059205335 | I54: 0.0092994478 | J54: 0.18092583 | K54: 0.22208707 | L54: 0.11889628 | M54: 0.98869456 | N54: 3.6576666 | O54: 211.30576 | P54: 0.86872009 | Q54: 0.19873039 | R54: 0.50133063 | S54: 0.42821171 | T54: 3.4361119 | U54: 39.734576 | V54: 0.053505114 | W54: 0.48447583 | X54: 1.3085959 | Y54: 0.15654509 | Z54: 0.3523913 | AA54: 0.0028896352 | AB54: 0.015522191 | AC54: 0.10602947 | AD54: 0.70404674 | AE54: 0.011174691 | AF54: 0.1843707 | AG54: 0.1424201 | AH54: 0.024082281 | AI54: 0.11675806 | AJ54: 0.040256787 | AK54: 0.57311635 | AL54: 13.92045 | AM54: 0.011584803 | AN54: 0.0008615324 | AO54: 0.3364146 | AP54: 12.547579 | AQ54: 0 | AR54: 299.53887
A55: 29 | B55: Machinery, nec | C55: m13 | D55: 57.269319 | E55: 2.8500553 | F55: 3.7471866 | G55: 0.35237492 | H55: 0.037378304 | I55: 0.025950376 | J55: 0.59500655 | K55: 0.71187969 | L55: 0.32822903 | M55: 1.6059314 | N55: 5.9399753 | O55: 5.0235027 | P55: 2.8022501 | Q55: 0.62683279 | R55: 1.6010026 | S55: 0.49133308 | T55: 27.327055 | U55: 88.948423 | V55: 0.25995321 | W55: 8.3206985 | X55: 43.646791 | Y55: 8.0653738 | Z55: 35.686076 | AA55: 0.35756323 | AB55: 1.8698509 | AC55: 10.360616 | AD55: 54.721749 | AE55: 0.9408141 | AF55: 4.8611748 | AG55: 3.6852706 | AH55: 7.6355105 | AI55: 4.2328989 | AJ55: 2.3148366 | AK55: 10.118102 | AL55: 253.40005 | AM55: 0.91447023 | AN55: 0.014433052 | AO55: 2.9551299 | AP55: 1.1589225 | AQ55: 0 | AR55: 655.80397
A56: 30t33 | B56: Electrical and optical equipment | C56: m14 | D56: 13.679419 | E56: 0.67965016 | F56: 0.89177766 | G56: 0.083995073 | H56: 0.0089035999 | I56: 0.0060635478 | J56: 0.14220079 | K56: 0.17024599 | L56: 0.077948205 | M56: 0.38308194 | N56: 1.4169569 | O56: 1.2008232 | P56: 0.66793472 | Q56: 0.15001655 | R56: 0.38172961 | S56: 0.1176943 | T56: 7.1354366 | U56: 21.176834 | V56: 0.061846972 | W56: 1.9780816 | X56: 10.372133 | Y56: 1.9206507 | Z56: 9.5273512 | AA56: 0.085247056 | AB56: 0.44623413 | AC56: 2.8837074 | AD56: 13.962128 | AE56: 0.22760477 | AF56: 1.1746002 | AG56: 0.87884677 | AH56: 1.8440191 | AI56: 1.0210003 | AJ56: 0.55483877 | AK56: 2.4199729 | AL56: 61.849938 | AM56: 0.21949577 | AN56: 2.1110029e-05 | AO56: 0.84190852 | AP56: 0.29152594 | AQ56: 0 | AR56: 160.93187
A57: 34t35 | B57: Transport equipment | C57: m15 | D57: 34.429821 | E57: 1.7548005 | F57: 2.1300864 | G57: 0.23711066 | H57: 0.025151058 | I57: 0.014485059 | J57: 0.40039179 | K57: 0.47916266 | L57: 0.21896871 | M57: 1.0101861 | N57: 3.737055 | O57: 2.8825539 | P57: 1.6438597 | Q57: 0.36876384 | R57: 0.94789084 | S57: 0.31241409 | T57: 17.897812 | U57: 53.20028 | V57: 0.15622092 | W57: 5.0370832 | X57: 26.358362 | Y57: 5.0282466 | Z57: 24.300635 | AA57: 0.21141557 | AB57: 1.1069463 | AC57: 7.3510419 | AD57: 31.767907 | AE57: 0.58126923 | AF57: 2.8421091 | AG57: 2.2162358 | AH57: 4.8835247 | AI57: 2.351708 | AJ57: 1.2610009 | AK57: 5.9337132 | AL57: 192.65582 | AM57: 0.90293962 | AN57: 0.017432366 | AO57: 2.8427644 | AP57: 0.55701824 | AQ57: 0 | AR57: 440.05419
A58: 36t37 | B58: Manufacturing, nec; recycling | C58: m16 | D58: 0.0047461183 | E58: 0.025965079 | F58: 0.83433039 | G58: 8.3808705 | H58: 0.95623371 | I58: 0.00038382892 | J58: 0.12845687 | K58: 0.006916634 | L58: 1.6498526e-05 | M58: 0.17027553 | N58: 0.63009117 | O58: 0.088990237 | P58: 0.047754433 | Q58: 0.010664142 | R58: 0.027760536 | S58: 1.8494998 | T58: 0.10390328 | U58: 9.4506013 | V58: 0.033528304 | W58: 0.82895867 | X58: 1.5571676 | Y58: 1.2507613 | Z58: 1.2505415 | AA58: 0.0088067371 | AB58: 0.042893283 | AC58: 0.37667133 | AD58: 0.82388977 | AE58: 0.088349451 | AF58: 0.27293956 | AG58: 0.22793421 | AH58: 0.15857633 | AI58: 0.62103316 | AJ58: 0.054559733 | AK58: 4.3592875 | AL58: 27.633495 | AM58: 0.1425542 | AN58: 0.00038630855 | AO58: 2.3065716 | AP58: 15.275207 | AQ58: 0 | AR58: 80.031572
A59: E | B59: Electricity, gas, and water supply | C59: m17 | D59: 0.15068301 | E59: 0.48038093 | F59: 1.6127547 | G59: 0.37816418 | H59: 0.04280557 | I59: 0.019232378 | J59: 0.56874325 | K59: 0.62582367 | L59: 0.2842197 | M59: 0.34472151 | N59: 1.2796892 | O59: 0.64380175 | P59: 0.44413377 | Q59: 0.098573326 | R59: 0.26123416 | S59: 0.089144965 | T59: 2.3076326 | U59: 4.1147632 | V59: 0.029181427 | W59: 0.69825491 | X59: 1.605841 | Y59: 1.9128703 | Z59: 0.47073924 | AA59: 0.0028735499 | AB59: 0.016790387 | AC59: 0.14234028 | AD59: 0.4172709 | AE59: 0.88110889 | AF59: 0.47971104 | AG59: 0.46037362 | AH59: 1.6852746 | AI59: 2.4541182 | AJ59: 2.1868463 | AK59: 0.75166339 | AL59: 13.518513 | AM59: 0.025126439 | AN59: 0.23105395 | AO59: 13.224556 | AP59: -0.69662136 | AQ59: 0 | AR59: 54.244387
A60: F | B60: Construction | C60: m18 | D60: 0.036182069 | E60: 0.012867582 | F60: 0.025754764 | G60: 0.020164768 | H60: 0.0033101051 | I60: 0.0015198076 | J60: 0.0041622001 | K60: 0.0052058234 | L60: 0.00096358733 | M60: 0.0027195242 | N60: 0.01774287 | O60: 0.0079519953 | P60: 0.0039550484 | Q60: 0.00080716977 | R60: 0.0023897484 | S60: 0.0026259235 | T60: 0.010276265 | U60: 0.94257688 | V60: 0.0001129316 | W60: 0.01935795 | X60: 0.095624005 | Y60: 0.010350857 | Z60: 0.011480835 | AA60: 3.3286953e-05 | AB60: 0.0010134113 | AC60: 0.0032281856 | AD60: 0.0029036922 | AE60: 0.0042189497 | AF60: 0.023127721 | AG60: 0.031695117 | AH60: 0.0022755386 | AI60: 0.05000982 | AJ60: 0.0041215198 | AK60: 0.016001405 | AL60: 0.0038544922 | AM60: 0.0032642995 | AN60: 0.0037289895 | AO60: 3.1536398 | AP60: 0.11911723 | AQ60: 0 | AR60: 4.6603361
A61: 50 | B61: Sale, maintenance, and repair of motor vehicles and motorcycles; retail sale of fuel | C61: m19 | D61: 0.11056569 | E61: 0.037749539 | F61: 0.064354941 | G61: 0.058517104 | H61: 0.0076158599 | I61: 0.0059197366 | J61: 0.0065634766 | K61: 0.015910225 | L61: 0.0075376823 | M61: 0.0064321929 | N61: 0.01971669 | O61: 0.018640614 | P61: 0.0074455258 | Q61: 0.0056298927 | R61: 0.0066857751 | S61: 0.0068827325 | T61: 0.026992545 | U61: 0.019188995 | V61: 0.00034690193 | W61: 0.0084738946 | X61: 0.0073527448 | Y61: 0.0072301824 | Z61: 0.018462629 | AA61: 4.3712006e-06 | AB61: 0.0029321228 | AC61: 0.0041881242 | AD61: 0.0062864301 | AE61: 0.0080808797 | AF61: 0.0035430925 | AG61: 0.031446699 | AH61: 0.0063542478 | AI61: 0.0091348021 | AJ61: 0.010943862 | AK61: 0.0066271942 | AL61: 0.0097292728 | AM61: 0.0097170088 | AN61: 0.008253211 | AO61: 0.011486045 | AP61: 0.0080080223 | AQ61: 0 | AR61: 0.61095096
A62: 51 | B62: Wholesale trade and commission trade, except of motor vehicles and motorcycles | C62: m20 | D62: 0.22401138 | E62: 0.073430056 | F62: 0.23120741 | G62: 0.12181787 | H62: 0.014611523 | I62: 0.012170782 | J62: 0.012543138 | K62: 0.031773007 | L62: 0.014482905 | M62: 0.012457796 | N62: 0.038614351 | O62: 0.058563777 | P62: 0.015671194 | Q62: 0.01243196 | R62: 0.014211231 | S62: 0.014089645 | T62: 0.059291884 | U62: 0.063953722 | V62: 0.013066525 | W62: 1.334884 | X62: 0.13229592 | Y62: 0.04022406 | Z62: 0.28704176 | AA62: 0.062032601 | AB62: 0.90277656 | AC62: 0.021154233 | AD62: 0.19079753 | AE62: 0.22997518 | AF62: 0.027314575 | AG62: 0.060109753 | AH62: 1.3707856 | AI62: 0.13357452 | AJ62: 0.024647412 | AK62: 0.012606656 | AL62: 5.4212211 | AM62: 0.39706439 | AN62: 0.017080289 | AO62: 0.12972825 | AP62: 0.034378705 | AQ62: 0 | AR62: 11.868093
A63: 52 | B63: Retail trade, except of motor vehicles and motorcycles; repair of household goods | C63: m21 | D63: 0.10479619 | E63: 0.042424907 | F63: 0.06540582 | G63: 0.055678521 | H63: 0.0074872305 | I63: 0.014724554 | J63: 0.0060177577 | K63: 0.033073993 | L63: 0.0077236389 | M63: 0.006537221 | N63: 0.018047788 | O63: 0.017695051 | P63: 0.02610983 | Q63: 0.0058355693 | R63: 0.011233341 | S63: 0.010605404 | T63: 0.025930933 | U63: 0.02048521 | V63: 0.00033799632 | W63: 0.040159409 | X63: 0.015241231 | Y63: 0.010152821 | Z63: 0.043429599 | AA63: 0.0051692924 | AB63: 0.087327841 | AC63: 0.0050048415 | AD63: 0.026848911 | AE63: 0.03541878 | AF63: 0.0048715722 | AG63: 0.029753659 | AH63: 0.19926258 | AI63: 0.022411257 | AJ63: 0.012648099 | AK63: 0.0047566546 | AL63: 0.43469183 | AM63: 0.25150122 | AN63: 0.0079244253 | AO63: 0.019600938 | AP63: 0.0074879877 | AQ63: 0 | AR63: 1.7438139
A64: H | B64: Hotels and restaurants | C64: m22 | D64: 0.055287387 | E64: 0.018876947 | F64: 0.032238405 | G64: 0.030338812 | H64: 0.0026693013 | I64: 0.00085623902 | J64: 0.0053620533 | K64: 0.011271311 | L64: 0.0055854305 | M64: 0.0018322513 | N64: 0.0060617105 | O64: 0.0092852202 | P64: 0.004607117 | Q64: 0.001916195 | R64: 0.0033299012 | S64: 0.0034264384 | T64: 0.013460324 | U64: 0.0095629246 | V64: 0.00017191405 | W64: 0.0043711058 | X64: 0.0037001358 | Y64: 0.0036090136 | Z64: 0.0085400591 | AA64: 6.7165844e-05 | AB64: 0.0035264353 | AC64: 0.0010115048 | AD64: 0.0031977788 | AE64: 0.0052015807 | AF64: 0.001766905 | AG64: 0.014612097 | AH64: 0.0038893149 | AI64: 0.0039935824 | AJ64: 0.0028357131 | AK64: 0.0065779152 | AL64: 0.012881043 | AM64: 0.0052333274 | AN64: 0.004125808 | AO64: 0.0057787022 | AP64: 0.0039656459 | AQ64: 0 | AR64: 0.31502472
A65: 60 | B65: Inland transport | C65: m23 | D65: 23.235529 | E65: 3.617166 | F65: 9.4543501 | G65: 3.7316118 | H65: 0.39562295 | I65: 0.034311024 | J65: 0.72489376 | K65: 1.6466354 | L65: 0.74740236 | M65: 1.8231854 | N65: 6.7446847 | O65: 5.392197 | P65: 0.093035603 | Q65: 0.021380067 | R65: 0.054350525 | S65: 0.66186108 | T65: 7.0975415 | U65: 36.25179 | V65: 0.27005212 | W65: 5.0296782 | X65: 16.709078 | Y65: 3.0251519 | Z65: 13.422935 | AA65: 0.095672941 | AB65: 0.47025061 | AC65: 4.0465206 | AD65: 5.2840385 | AE65: 0.72520094 | AF65: 1.3961035 | AG65: 1.1844144 | AH65: 4.2144294 | AI65: 2.435034 | AJ65: 3.3860693 | AK65: 2.6861285 | AL65: 129.2204 | AM65: 0.075989876 | AN65: 1.3125625 | AO65: 45.745869 | AP65: 0.27615487 | AQ65: 0 | AR65: 342.73928
A66: 61 | B66: Water transport | C66: m24 | D66: 0.16454355 | E66: 0.026821429 | F66: 0.069426616 | G66: 0.025603652 | H66: 0.0030045973 | I66: 0.0084909502 | J66: 0.0054478518 | K66: 0.012417175 | L66: 0.0052030304 | M66: 0.013911706 | N66: 0.051680949 | O66: 0.038664957 | P66: 0.0098564222 | Q66: 0.00059120333 | R66: 0.0024135508 | S66: 0.0046270074 | T66: 0.052002227 | U66: 0.27409608 | V66: 0.001702884 | W66: 0.11062101 | X66: 0.12611828 | Y66: 0.021541479 | Z66: 0.098992275 | AA66: 0.095626918 | AB66: 0.037326431 | AC66: 0.046292682 | AD66: 0.067783449 | AE66: 0.065982901 | AF66: 0.010293516 | AG66: 0.0087775226 | AH66: 0.42674774 | AI66: 0.030572318 | AJ66: 0.025023551 | AK66: 0.020389934 | AL66: 0.98612383 | AM66: 0.00054901711 | AN66: 0.014429069 | AO66: 0.33206153 | AP66: 0.5976664 | AQ66: 0 | AR66: 3.8934257
A67: 62 | B67: Air transport | C67: m25 | D67: 1.1995775 | E67: 0.18934298 | F67: 0.48859889 | G67: 0.19226273 | H67: 0.02028838 | I67: 0.0026569469 | J67: 0.037528572 | K67: 0.085361739 | L67: 0.038737148 | M67: 0.094273916 | N67: 0.34990178 | O67: 0.27784844 | P67: 0.0066668232 | Q67: 0.0020652145 | R67: 0.0030276778 | S67: 0.034156669 | T67: 0.36443538 | U67: 1.8775892 | V67: 0.012207676 | W67: 0.39361711 | X67: 0.86511298 | Y67: 0.15480497 | Z67: 0.69550899 | AA67: 0.018764713 | AB67: 0.12698913 | AC67: 0.20942654 | AD67: 0.28880079 | AE67: 0.025341098 | AF67: 0.072413297 | AG67: 0.064366259 | AH67: 0.33322493 | AI67: 0.1222284 | AJ67: 0.17462894 | AK67: 0.13906821 | AL67: 6.9119519 | AM67: 0.0038492419 | AN67: 0.068298791 | AO67: 2.3592982 | AP67: 0.0059497127 | AQ67: 0 | AR67: 18.310172
A68: 63 | B68: Other supporting and auxiliary transport activities; activities of travel agencies | C68: m26 | D68: 6.7415047 | E68: 1.0610481 | F68: 2.7696294 | G68: 1.1121752 | H68: 0.11772569 | I68: 0.0097414581 | J68: 0.21577552 | K68: 0.48951618 | L68: 0.22297935 | M68: 0.54152286 | N68: 2.0035176 | O68: 1.5790673 | P68: 0.026677515 | Q68: 0.005966134 | R68: 0.015471748 | S68: 0.1971131 | T68: 2.0897363 | U68: 10.729116 | V68: 0.078872432 | W68: 1.8097022 | X68: 4.9391787 | Y68: 0.89155842 | Z68: 3.9857131 | AA68: 0.028748351 | AB68: 0.14023733 | AC68: 1.1970245 | AD68: 1.554686 | AE68: 0.21688498 | AF68: 0.40744476 | AG68: 0.34985183 | AH68: 1.2487358 | AI68: 0.700865 | AJ68: 0.99260873 | AK68: 0.7959147 | AL68: 38.281411 | AM68: 0.023274047 | AN68: 0.3919624 | AO68: 13.413706 | AP68: 0.034749815 | AQ68: 0 | AR68: 101.41142
A69: 64 | B69: Post and telecommunications | C69: m27 | D69: 4.0838533 | E69: 0.77979574 | F69: 3.4796296 | G69: 1.3375938 | H69: 0.14139662 | I69: 0.0078322138 | J69: 0.17243617 | K69: 0.85307696 | L69: 0.38829569 | M69: 1.5620146 | N69: 4.687083 | O69: 0.7523002 | P69: 0.039374977 | Q69: 0.0092152209 | R69: 0.023470208 | S69: 0.13868118 | T69: 1.276475 | U69: 16.124484 | V69: 0.05161552 | W69: 2.2417224 | X69: 5.9304679 | Y69: 1.2307922 | Z69: 3.5836967 | AA69: 0.020546705 | AB69: 0.11176205 | AC69: 1.0732688 | AD69: 6.4561144 | AE69: 0.63869967 | AF69: 2.787802 | AG69: 2.7001722 | AH69: 6.6874496 | AI69: 0.66459749 | AJ69: 0.94134337 | AK69: 3.5564057 | AL69: 79.487428 | AM69: 0.059088895 | AN69: 0.2704472 | AO69: 20.195205 | AP69: -0.14813776 | AQ69: 0 | AR69: 174.3975
A70: J | B70: Financial intermediation | C70: m28 | D70: 0.059818503 | E70: 0.027944896 | F70: 0.1590045 | G70: 0.021656917 | H70: 0.0011202527 | I70: 0.018390969 | J70: 0.0080204676 | K70: 0.041308366 | L70: 0.0018771782 | M70: 0.0035571577 | N70: 0.019509712 | O70: 0.016047124 | P70: 0.034482673 | Q70: 0.00079564069 | R70: 0.017570754 | S70: 0.012186144 | T70: 0.053745076 | U70: 0.09109308 | V70: 0.0049223881 | W70: 0.14024248 | X70: 0.069289282 | Y70: 0.088271801 | Z70: 0.13705642 | AA70: 0.0076634112 | AB70: 0.020734052 | AC70: 0.038989259 | AD70: 0.099088812 | AE70: 39.229062 | AF70: 0.032889033 | AG70: 0.0282659 | AH70: 0.095908289 | AI70: 0.16440044 | AJ70: 0.00047677432 | AK70: 0.096709066 | AL70: 0.96343545 | AM70: 0.14228413 | AN70: 0.41254604 | AO70: 0.45835619 | AP70: 0.31083326 | AQ70: 0 | AR70: 43.129554
A71: 70 | B71: Real estate activities | C71: m29 | D71: 0.36281209 | E71: 0.12515839 | F71: 0.21071872 | G71: 0.21987261 | H71: 0.011223825 | I71: 0.0013486673 | J71: 0.040316831 | K71: 0.037446011 | L71: 0.032225476 | M71: 0.0050184203 | N71: 0.093603906 | O71: 0.063931056 | P71: 0.025195961 | Q71: 0.018660717 | R71: 0.021837794 | S71: 0.021861009 | T71: 0.086340654 | U71: 0.06412428 | V71: 0.00090416923 | W71: 0.020689878 | X71: 0.020279292 | Y71: 0.021070234 | Z71: 0.060378705 | AA71: 4.7978927e-06 | AB71: 0.011603832 | AC71: 0.012058305 | AD71: 0.02084756 | AE71: 0.067913727 | AF71: 0.011556168 | AG71: 0.066210246 | AH71: 0.021202342 | AI71: 0.022030356 | AJ71: 0.01732119 | AK71: 0.048763388 | AL71: 0.029741193 | AM71: 0.026850211 | AN71: 0.024078982 | AO71: 0.027351692 | AP71: 0.027894039 | AQ71: 0 | AR71: 2.0004467
A72: 71t74 | B72: Renting of M&Eq and other business activities | C72: m30 | D72: 0.030069462 | E72: 0.037490426 | F72: 0.04140307 | G72: 0.070008131 | H72: 0.0096954069 | I72: 0.003073409 | J72: 0.010703989 | K72: 0.013429149 | L72: 0.0088560021 | M72: 0.0057457188 | N72: 0.013824139 | O72: 0.024012603 | P72: 0.014050254 | Q72: 0.0021369407 | R72: 0.0060146749 | S72: 0.0080849302 | T72: 0.018117143 | U72: 0.02302323 | V72: 0.00017420771 | W72: 0.0068566689 | X72: 0.0045327713 | Y72: 0.010581132 | Z72: 0.011332807 | AA72: 8.0015501e-05 | AB72: 0.0069255061 | AC72: 0.0054098551 | AD72: 0.010920172 | AE72: 0.011223819 | AF72: 0.0095799129 | AG72: 0.044090687 | AH72: 0.012523517 | AI72: 0.014391802 | AJ72: 0.0060299992 | AK72: 0.015670196 | AL72: 0.040348041 | AM72: 0.014924114 | AN72: 0.01374322 | AO72: 0.024850223 | AP72: 0.015941151 | AQ72: 0 | AR72: 0.6198685
A73: L | B73: Public administration and defense; compulsory social security | C73: m31 | D73: 0.00031403942 | E73: 0.00046528596 | F73: 0.00052424339 | G73: 0.00033024543 | H73: 0 | I73: 0.00015240977 | J73: 5.9694592e-07 | K73: 0.00045165296 | L73: 6.1733587e-07 | M73: 0.24464282 | N73: 0.90545845 | O73: 0.00030705464 | P73: 0.00039504005 | Q73: 5.7454961e-07 | R73: 0.00026569748 | S73: 0.00026496609 | T73: 0.00023666149 | U73: 0.00026875758 | V73: 1.9801618e-06 | W73: 0.00026661384 | X73: 0.00015974355 | Y73: 0.084302338 | Z73: 0.0011561219 | AA73: 2.2447215e-05 | AB73: 0.00022418875 | AC73: 0.00034163205 | AD73: 0.011408104 | AE73: 0.00083970529 | AF73: 0.39957356 | AG73: 0.42661375 | AH73: 0.54343799 | AI73: 0.0013635457 | AJ73: 1.4562121e-06 | AK73: 0.07083737 | AL73: 0.0053006058 | AM73: 0.0017972039 | AN73: 155.77555 | AO73: 11.858185 | AP73: 7.0137073 | AQ73: 0 | AR73: 177.34917
A74: M | B74: Education | C74: m32 | D74: 0.0002893638 | E74: 0.00062389871 | F74: 0.00029113078 | G74: 0.00022227651 | H74: 7.5546378e-06 | I74: 0.00010577158 | J74: 0.00010368702 | K74: 0.00099616546 | L74: 3.6721121e-05 | M74: 2.5903087e-05 | N74: 4.0644723e-06 | O74: 0.00020108449 | P74: 0.00017009991 | Q74: 6.3556423e-07 | R74: 0.00023363378 | S74: 0.00018945082 | T74: 0.00018716103 | U74: 0.00029766054 | V74: 3.3713144e-06 | W74: 0.00020120897 | X74: 0.00018888195 | Y74: 0.00018521887 | Z74: 6.681832e-05 | AA74: 1.4838186e-05 | AB74: 0.00015136488 | AC74: 3.0324042e-05 | AD74: 0.00051766377 | AE74: 0.0014605296 | AF74: 8.7072591e-05 | AG74: 0.00020804678 | AH74: 0.00043257943 | AI74: 0.0021069249 | AJ74: 6.0336472e-06 | AK74: 4.1552969e-05 | AL74: 0.013270353 | AM74: 0.0058947599 | AN74: 0.00034453168 | AO74: 0.00026372742 | AP74: 7.6223455e-05 | AQ74: 0 | AR74: 0.029538289
A75: N | B75: Health and social work | C75: m33 | D75: 0.00066707421 | E75: 0.0025851558 | F75: 0.0084063029 | G75: 0.0022144092 | H75: 0.00023906568 | I75: 1.1540758e-05 | J75: 0.00085757738 | K75: 0.0034412148 | L75: 0.001508635 | M75: 0.00099740587 | N75: 0.0036929188 | O75: 5.9179853e-05 | P75: 0.00061849473 | Q75: 0.00013811032 | R75: 0.00035690383 | S75: 1.0987458e-05 | T75: 0.0055366832 | U75: 0.021473664 | V75: 0.00074611671 | W75: 0.0035778581 | X75: 0.0027415444 | Y75: 0.0028273048 | Z75: 0.0044961876 | AA75: 2.9774621e-05 | AB75: 0.00024245504 | AC75: 0.0012695481 | AD75: 0.00071206235 | AE75: 0.0011488582 | AF75: 0.0024564629 | AG75: 0.0022335093 | AH75: 0.055942229 | AI75: 0.16902111 | AJ75: 0.074747696 | AK75: 0.028372717 | AL75: 1.1894198 | AM75: 1.9592883e-05 | AN75: 12.975531 | AO75: 0.30976923 | AP75: 0.00071834189 | AQ75: 0 | AR75: 14.878839
B76: Other community, social, and personal services | C76: m34 | D76: 0.011205062 | E76: 0.0030508485 | F76: 0.0025765929 | G76: 0.0042518836 | H76: 0.0031444041 | I76: 0.00026755829 | J76: 0.00095989113 | K76: 0.001155647 | L76: 0.00030585291 | M76: 0.00026697239 | N76: 0.0022852038 | O76: 0.0019358245 | P76: 0.0013483471 | Q76: 0.00014472883 | R76: 0.00076233437 | S76: 0.00055765836 | T76: 0.0030348667 | U76: 0.0013552481 | V76: 4.8121176e-05 | W76: 0.00053648784 | X76: 0.00066196654 | Y76: 0.00074233555 | Z76: 0.001148196 | AA76: 7.6485367e-06 | AB76: 0.00043659244 | AC76: 0.0003371304 | AD76: 0.00025860408 | AE76: 0.00071950702 | AF76: 0.00033768236 | AG76: 0.0032822879 | AH76: 0.00070442762 | AI76: 0.00014867835 | AJ76: 0.00014799722 | AK76: 0.0026634741 | AL76: 0.00046670116 | AM76: 0.00099041343 | AN76: 0.00020915846 | AO76: 0.0012451425 | AP76: 0.00061559156 | AQ76: 0 | AR76: 0.054317069
B77: Total intermediate consumption | C77: r60 | D77: 2130.919 | E77: 71.703374 | F77: 454.17767 | G77: 84.083192 | H77: 8.9092517 | I77: 2.1804125 | J77: 25.513153 | K77: 51.994283 | L77: 24.021066 | M77: 46.590629 | N77: 171.06175 | O77: 1034.0297 | P77: 18.000615 | Q77: 4.0846457 | R77: 10.383122 | S77: 17.322648 | T77: 187.73099 | U77: 1305.1147 | V77: 5.6753212 | W77: 118.03253 | X77: 594.24996 | Y77: 174.38637 | Z77: 272.12365 | AA77: 2.618038 | AB77: 13.995323 | AC77: 82.310435 | AD77: 236.90333 | AE77: 1357.7837 | AF77: 98.965925 | AG77: 76.208912 | AH77: 198.32859 | AI77: 137.86819 | AJ77: 90.053371 | AK77: 109.70857 | AL77: 5641.103 | AM77: 81.576762 | AN77: 1302.2102 | AO77: 2211.367 | AP77: 218.46816 | AQ77: 2712.8316 | AR77: 21384.589
B78: Taxes less subsidies on products | C78: r99 | D78: 15.486795 | E78: 2.7387704 | F78: 14.711517 | G78: 2.9191188 | H78: 0.30930277 | I78: 0.087125338 | J78: 0.71558914 | K78: 3.1833664 | L78: 1.4720349 | M78: 2.4768402 | N78: 9.0939452 | O78: 25.638143 | P78: 0.73088198 | Q78: 0.1688737 | R78: 0.43111711 | S78: 0.56054317 | T78: 12.520469 | U78: 60.241219 | V78: 0.51834717 | W78: 6.6810378 | X78: 41.376584 | Y78: 8.4997351 | Z78: 14.56898 | AA78: 0.13119525 | AB78: 0.76460393 | AC78: 4.4884712 | AD78: 16.379008 | AE78: 21.067911 | AF78: 6.7535982 | AG78: 3.3038121 | AH78: 8.7640204 | AI78: 4.7869095 | AJ78: 3.3573403 | AK78: 4.4635985 | AL78: 544.85445 | AM78: 2.0436796 | AN78: 17.904822 | AO78: 132.82491 | AP78: 7.2167301 | AQ78: 0 | AR78: 1004.2354
B79: Cif/ fob adjustments on exports | C79: r61 | D79: 0 | E79: 0 | F79: 0 | G79: 0 | H79: 0 | I79: 0 | J79: 0 | K79: 0 | L79: 0 | M79: 0 | N79: 0 | O79: 0 | P79: 0 | Q79: 0 | R79: 0 | S79: 0 | T79: 0 | U79: 0 | V79: 0 | W79: 0 | X79: 0 | Y79: 0 | Z79: 0 | AA79: 0 | AB79: 0 | AC79: 0 | AD79: 0 | AE79: 0 | AF79: 0 | AG79: 0 | AH79: 0 | AI79: 0 | AJ79: 0 | AK79: 0 | AL79: 0 | AM79: 0 | AN79: 0 | AO79: 0 | AP79: 0 | AQ79: 0 | AR79: 0
B80: Direct purchases abroad by residents | C80: r62 | D80: 0 | E80: 0 | F80: 0 | G80: 0 | H80: 0 | I80: 0 | J80: 0 | K80: 0 | L80: 0 | M80: 0 | N80: 0 | O80: 0 | P80: 0 | Q80: 0 | R80: 0 | S80: 0 | T80: 0 | U80: 0 | V80: 0 | W80: 0 | X80: 0 | Y80: 0 | Z80: 0 | AA80: 0 | AB80: 0 | AC80: 0 | AD80: 0 | AE80: 0 | AF80: 0 | AG80: 0 | AH80: 0 | AI80: 0 | AJ80: 0 | AK80: 0 | AL80: 0 | AM80: 0 | AN80: 0 | AO80: 0 | AP80: 0 | AQ80: 0 | AR80: 0
B81: Purchases on the domestic territory by nonresidents | C81: r63 | D81: 0 | E81: 0 | F81: 0 | G81: 0 | H81: 0 | I81: 0 | J81: 0 | K81: 0 | L81: 0 | M81: 0 | N81: 0 | O81: 0 | P81: 0 | Q81: 0 | R81: 0 | S81: 0 | T81: 0 | U81: 0 | V81: 0 | W81: 0 | X81: 0 | Y81: 0 | Z81: 0 | AA81: 0 | AB81: 0 | AC81: 0 | AD81: 0 | AE81: 0 | AF81: 0 | AG81: 0 | AH81: 0 | AI81: 0 | AJ81: 0 | AK81: 0 | AL81: 0 | AM81: 0 | AN81: 0 | AO81: 0 | AP81: 0 | AQ81: 0 | AR81: 0
B82: Value added at basic prices | C82: r64 | D82: 908.06214 | E82: 70.980728 | F82: 174.12816 | G82: 41.308522 | H82: 4.3769511 | I82: 1.6822554 | J82: 13.251194 | K82: 29.52951 | L82: 13.654874 | M82: 27.272356 | N82: 100.13295 | O82: 668.72253 | P82: 15.466766 | Q82: 3.5736685 | R82: 9.1232064 | S82: 10.264209 | T82: 158.31998 | U82: 607.03135 | V82: 19.93217 | W82: 247.09928 | X82: 1051.2196 | Y82: 126.21938 | Z82: 208.29383 | AA82: 1.8757086 | AB82: 10.931601 | AC82: 64.172019 | AD82: 265.07173 | AE82: 213.81454 | AF82: 168.01209 | AG82: 126.3636 | AH82: 402.33629 | AI82: 450.39388 | AJ82: 239.5103 | AK82: 115.6436 | AL82: 0 | AM82: 0 | AN82: 0 | AO82: 0 | AP82: 0 | AQ82: 0 | AR82: 6567.771
B83: International transport margins | D83: 0 | E83: 0 | F83: 0 | G83: 0 | H83: 0 | I83: 0 | J83: 0 | K83: 0 | L83: 0 | M83: 0 | N83: 0 | O83: 0 | P83: 0 | Q83: 0 | R83: 0 | S83: 0 | T83: 0 | U83: 0 | V83: 0 | W83: 0 | X83: 0 | Y83: 0 | Z83: 0 | AA83: 0 | AB83: 0 | AC83: 0 | AD83: 0 | AE83: 0 | AF83: 0 | AG83: 0 | AH83: 0 | AI83: 0 | AJ83: 0 | AK83: 0 | AL83: 0 | AM83: 0 | AN83: 0 | AO83: 0 | AP83: 0 | AQ83: 0 | AR83: 0
B84: Output at basic prices | C84: r69 | D84: 3054.468 | E84: 145.42287 | F84: 643.01735 | G84: 128.31083 | H84: 13.595506 | I84: 3.9497932 | J84: 39.479936 | K84: 84.707159 | L84: 39.147976 | M84: 76.339825 | N84: 280.28864 | O84: 1728.3904 | P84: 34.198262 | Q84: 7.827188 | R84: 19.937445 | S84: 28.1474 | T84: 358.57144 | U84: 1972.3873 | V84: 26.125838 | W84: 371.81284 | X84: 1686.8462 | Y84: 309.10548 | Z84: 494.98646 | AA84: 4.6249418 | AB84: 25.691529 | AC84: 150.97092 | AD84: 518.35407 | AE84: 1592.6662 | AF84: 273.73161 | AG84: 205.87632 | AH84: 609.4289 | AI84: 593.04898 | AJ84: 332.92101 | AK84: 229.81577 | AL84: 6185.9574 | AM84: 83.620442 | AN84: 1320.115 | AO84: 2344.1919 | AP84: 225.68489 | AQ84: 2712.8316 | AR84: 28956.596
B86: $ = United States dollar; cif = cost, insurance, and freight; fob = free on board; M&Eq = machinery and equipment; nec = not elsewhere classified; NPISHs = nonprofit institutions serving households.
B87: Source: Asian Development Bank Multiregional Input–Output Database
B89: Social vectors
D91: GDP Computation
D92: Production approach | I92: Expenditure approach
D93: Total output at basic prices | H93: 410979.72 | I93: Household final consumption expenditure | M93: 168320.46
D94: - Intermediate consumption | H94: -178510.77 | I94: + NPISH final consumption expenditure | M94: 0
D95: = Value added at basic prices | H95: 232468.95 | I95: + Government consumption expenditure | M95: 14736.415
D96: + Taxes less subsidies on products | H96: 13164.537 | I96: + Gross fixed capital formation | M96: 75579.066
I97: + Changes in inventories | M97: 0
I98: + Acquisitions less disposals of valuables
I99: + Exports of goods and services | M99: 30734.208
I100: - Imports of goods and services | M100: -43736.659
I101: - Direct purchases abroad by residents | M101: 0
D102: = Gross domestic product | H102: 245633.49 | I102: = Gross domestic product | M102: 245633.49
D105: Agriculture, hunting, forestry, and fishing | E105: Mining and quarrying | F105: Food, beverages, and tobacco | G105: Textiles and textile products | H105: Leather, leather products, and footwear | I105: Wood and products of wood and cork | J105: Pulp, paper, paper products, printing, and publishing | K105: Coke, refined petroleum, and nuclear fuel | L105: Chemicals and chemical products | M105: Rubber and plastics | N105: Other nonmetallic minerals | O105: Basic metals and fabricated metal | P105: Machinery, nec | Q105: Electrical and optical equipment | R105: Transport equipment | S105: Manufacturing, nec; recycling | T105: Electricity, gas, and water supply | U105: Construction | V105: Sale, maintenance, and repair of motor vehicles and motorcycles; retail sale of fuel | W105: Wholesale trade and commission trade, except of motor vehicles and motorcycles | X105: Retail trade, except of motor vehicles and motorcycles; repair of household goods | Y105: Hotels and restaurants | Z105: Inland transport | AA105: Water transport | AB105: Air transport | AC105: Other supporting and auxiliary transport activities; activities of travel agencies | AD105: Post and telecommunications | AE105: Financial intermediation | AF105: Real estate activities | AG105: Renting of M&Eq and other business activities | AH105: Public administration and defense; compulsory social security | AI105: Education | AJ105: Health and social work | AK105: Other community, social, and personal services
...
